Workbook

Sheet Maman-Frère-Copine & famille
A1: 🎁 Idées cadeaux – Maman-Frère-Copine & famille
A2: Lignes jaunes = automatiques depuis « Ma wish list » (statut et notes se modifient là-bas). Lignes blanches = tes idées perso.
A3: Pour qui | B3: Idée cadeau | C3: Où l'acheter / lien | D3: Statut | E3: Notes
A4: =IFERROR(INDEX('Ma wish list'!$E$4:$E$40,MATCH(1,'Ma wish list'!$I$4:$I$40,0))&"","") | B4: =IFERROR(INDEX('Ma wish list'!$A$4:$A$40,MATCH(1,'Ma wish list'!$I$4:$I$40,0))&"","") | C4: =IFERROR(INDEX('Ma wish list'!$D$4:$D$40,MATCH(1,'Ma wish list'!$I$4:$I$40,0))&"","") | D4: =IFERROR(INDEX('Ma wish list'!$F$4:$F$40,MATCH(1,'Ma wish list'!$I$4:$I$40,0))&"","") | E4: =IFERROR(INDEX('Ma wish list'!$G$4:$G$40,MATCH(1,'Ma wish list'!$I$4:$I$40,0))&"","")
A5: =IFERROR(INDEX('Ma wish list'!$E$4:$E$40,MATCH(2,'Ma wish list'!$I$4:$I$40,0))&"","") | B5: =IFERROR(INDEX('Ma wish list'!$A$4:$A$40,MATCH(2,'Ma wish list'!$I$4:$I$40,0))&"","") | C5: =IFERROR(INDEX('Ma wish list'!$D$4:$D$40,MATCH(2,'Ma wish list'!$I$4:$I$40,0))&"","") | D5: =IFERROR(INDEX('Ma wish list'!$F$4:$F$40,MATCH(2,'Ma wish list'!$I$4:$I$40,0))&"","") | E5: =IFERROR(INDEX('Ma wish list'!$G$4:$G$40,MATCH(2,'Ma wish list'!$I$4:$I$40,0))&"","")
A6: =IFERROR(INDEX('Ma wish list'!$E$4:$E$40,MATCH(3,'Ma wish list'!$I$4:$I$40,0))&"","") | B6: =IFERROR(INDEX('Ma wish list'!$A$4:$A$40,MATCH(3,'Ma wish list'!$I$4:$I$40,0))&"","") | C6: =IFERROR(INDEX('Ma wish list'!$D$4:$D$40,MATCH(3,'Ma wish list'!$I$4:$I$40,0))&"","") | D6: =IFERROR(INDEX('Ma wish list'!$F$4:$F$40,MATCH(3,'Ma wish list'!$I$4:$I$40,0))&"","") | E6: =IFERROR(INDEX('Ma wish list'!$G$4:$G$40,MATCH(3,'Ma wish list'!$I$4:$I$40,0))&"","")
A7: =IFERROR(INDEX('Ma wish list'!$E$4:$E$40,MATCH(4,'Ma wish list'!$I$4:$I$40,0))&"","") | B7: =IFERROR(INDEX('Ma wish list'!$A$4:$A$40,MATCH(4,'Ma wish list'!$I$4:$I$40,0))&"","") | C7: =IFERROR(INDEX('Ma wish list'!$D$4:$D$40,MATCH(4,'Ma wish list'!$I$4:$I$40,0))&"","") | D7: =IFERROR(INDEX('Ma wish list'!$F$4:$F$40,MATCH(4,'Ma wish list'!$I$4:$I$40,0))&"","") | E7: =IFERROR(INDEX('Ma wish list'!$G$4:$G$40,MATCH(4,'Ma wish list'!$I$4:$I$40,0))&"","")
A8: =IFERROR(INDEX('Ma wish list'!$E$4:$E$40,MATCH(5,'Ma wish list'!$I$4:$I$40,0))&"","") | B8: =IFERROR(INDEX('Ma wish list'!$A$4:$A$40,MATCH(5,'Ma wish list'!$I$4:$I$40,0))&"","") | C8: =IFERROR(INDEX('Ma wish list'!$D$4:$D$40,MATCH(5,'Ma wish list'!$I$4:$I$40,0))&"","") | D8: =IFERROR(INDEX('Ma wish list'!$F$4:$F$40,MATCH(5,'Ma wish list'!$I$4:$I$40,0))&"","") | E8: =IFERROR(INDEX('Ma wish list'!$G$4:$G$40,MATCH(5,'Ma wish list'!$I$4:$I$40,0))&"","")
A9: =IFERROR(INDEX('Ma wish list'!$E$4:$E$40,MATCH(6,'Ma wish list'!$I$4:$I$40,0))&"","") | B9: =IFERROR(INDEX('Ma wish list'!$A$4:$A$40,MATCH(6,'Ma wish list'!$I$4:$I$40,0))&"","") | C9: =IFERROR(INDEX('Ma wish list'!$D$4:$D$40,MATCH(6,'Ma wish list'!$I$4:$I$40,0))&"","") | D9: =IFERROR(INDEX('Ma wish list'!$F$4:$F$40,MATCH(6,'Ma wish list'!$I$4:$I$40,0))&"","") | E9: =IFERROR(INDEX('Ma wish list'!$G$4:$G$40,MATCH(6,'Ma wish list'!$I$4:$I$40,0))&"","")
A10: =IFERROR(INDEX('Ma wish list'!$E$4:$E$40,MATCH(7,'Ma wish list'!$I$4:$I$40,0))&"","") | B10: =IFERROR(INDEX('Ma wish list'!$A$4:$A$40,MATCH(7,'Ma wish list'!$I$4:$I$40,0))&"","") | C10: =IFERROR(INDEX('Ma wish list'!$D$4:$D$40,MATCH(7,'Ma wish list'!$I$4:$I$40,0))&"","") | D10: =IFERROR(INDEX('Ma wish list'!$F$4:$F$40,MATCH(7,'Ma wish list'!$I$4:$I$40,0))&"","") | E10: =IFERROR(INDEX('Ma wish list'!$G$4:$G$40,MATCH(7,'Ma wish list'!$I$4:$I$40,0))&"","")
A11: =IFERROR(INDEX('Ma wish list'!$E$4:$E$40,MATCH(8,'Ma wish list'!$I$4:$I$40,0))&"","") | B11: =IFERROR(INDEX('Ma wish list'!$A$4:$A$40,MATCH(8,'Ma wish list'!$I$4:$I$40,0))&"","") | C11: =IFERROR(INDEX('Ma wish list'!$D$4:$D$40,MATCH(8,'Ma wish list'!$I$4:$I$40,0))&"","") | D11: =IFERROR(INDEX('Ma wish list'!$F$4:$F$40,MATCH(8,'Ma wish list'!$I$4:$I$40,0))&"","") | E11: =IFERROR(INDEX('Ma wish list'!$G$4:$G$40,MATCH(8,'Ma wish list'!$I$4:$I$40,0))&"","")
A12: =IFERROR(INDEX('Ma wish list'!$E$4:$E$40,MATCH(9,'Ma wish list'!$I$4:$I$40,0))&"","") | B12: =IFERROR(INDEX('Ma wish list'!$A$4:$A$40,MATCH(9,'Ma wish list'!$I$4:$I$40,0))&"","") | C12: =IFERROR(INDEX('Ma wish list'!$D$4:$D$40,MATCH(9,'Ma wish list'!$I$4:$I$40,0))&"","") | D12: =IFERROR(INDEX('Ma wish list'!$F$4:$F$40,MATCH(9,'Ma wish list'!$I$4:$I$40,0))&"","") | E12: =IFERROR(INDEX('Ma wish list'!$G$4:$G$40,MATCH(9,'Ma wish list'!$I$4:$I$40,0))&"","")
A13: =IFERROR(INDEX('Ma wish list'!$E$4:$E$40,MATCH(10,'Ma wish list'!$I$4:$I$40,0))&"","") | B13: =IFERROR(INDEX('Ma wish list'!$A$4:$A$40,MATCH(10,'Ma wish list'!$I$4:$I$40,0))&"","") | C13: =IFERROR(INDEX('Ma wish list'!$D$4:$D$40,MATCH(10,'Ma wish list'!$I$4:$I$40,0))&"","") | D13: =IFERROR(INDEX('Ma wish list'!$F$4:$F$40,MATCH(10,'Ma wish list'!$I$4:$I$40,0))&"","") | E13: =IFERROR(INDEX('Ma wish list'!$G$4:$G$40,MATCH(10,'Ma wish list'!$I$4:$I$40,0))&"","")
A14: =IFERROR(INDEX('Ma wish list'!$E$4:$E$40,MATCH(11,'Ma wish list'!$I$4:$I$40,0))&"","") | B14: =IFERROR(INDEX('Ma wish list'!$A$4:$A$40,MATCH(11,'Ma wish list'!$I$4:$I$40,0))&"","") | C14: =IFERROR(INDEX('Ma wish list'!$D$4:$D$40,MATCH(11,'Ma wish list'!$I$4:$I$40,0))&"","") | D14: =IFERROR(INDEX('Ma wish list'!$F$4:$F$40,MATCH(11,'Ma wish list'!$I$4:$I$40,0))&"","") | E14: =IFERROR(INDEX('Ma wish list'!$G$4:$G$40,MATCH(11,'Ma wish list'!$I$4:$I$40,0))&"","")
A15: =IFERROR(INDEX('Ma wish list'!$E$4:$E$40,MATCH(12,'Ma wish list'!$I$4:$I$40,0))&"","") | B15: =IFERROR(INDEX('Ma wish list'!$A$4:$A$40,MATCH(12,'Ma wish list'!$I$4:$I$40,0))&"","") | C15: =IFERROR(INDEX('Ma wish list'!$D$4:$D$40,MATCH(12,'Ma wish list'!$I$4:$I$40,0))&"","") | D15: =IFERROR(INDEX('Ma wish list'!$F$4:$F$40,MATCH(12,'Ma wish list'!$I$4:$I$40,0))&"","") | E15: =IFERROR(INDEX('Ma wish list'!$G$4:$G$40,MATCH(12,'Ma wish list'!$I$4:$I$40,0))&"","")
A16: =IFERROR(INDEX('Ma wish list'!$E$4:$E$40,MATCH(13,'Ma wish list'!$I$4:$I$40,0))&"","") | B16: =IFERROR(INDEX('Ma wish list'!$A$4:$A$40,MATCH(13,'Ma wish list'!$I$4:$I$40,0))&"","") | C16: =IFERROR(INDEX('Ma wish list'!$D$4:$D$40,MATCH(13,'Ma wish list'!$I$4:$I$40,0))&"","") | D16: =IFERROR(INDEX('Ma wish list'!$F$4:$F$40,MATCH(13,'Ma wish list'!$I$4:$I$40,0))&"","") | E16: =IFERROR(INDEX('Ma wish list'!$G$4:$G$40,MATCH(13,'Ma wish list'!$I$4:$I$40,0))&"","")
A17: =IFERROR(INDEX('Ma wish list'!$E$4:$E$40,MATCH(14,'Ma wish list'!$I$4:$I$40,0))&"","") | B17: =IFERROR(INDEX('Ma wish list'!$A$4:$A$40,MATCH(14,'Ma wish list'!$I$4:$I$40,0))&"","") | C17: =IFERROR(INDEX('Ma wish list'!$D$4:$D$40,MATCH(14,'Ma wish list'!$I$4:$I$40,0))&"","") | D17: =IFERROR(INDEX('Ma wish list'!$F$4:$F$40,MATCH(14,'Ma wish list'!$I$4:$I$40,0))&"","") | E17: =IFERROR(INDEX('Ma wish list'!$G$4:$G$40,MATCH(14,'Ma wish list'!$I$4:$I$40,0))&"","")
A18: =IFERROR(INDEX('Ma wish list'!$E$4:$E$40,MATCH(15,'Ma wish list'!$I$4:$I$40,0))&"","") | B18: =IFERROR(INDEX('Ma wish list'!$A$4:$A$40,MATCH(15,'Ma wish list'!$I$4:$I$40,0))&"","") | C18: =IFERROR(INDEX('Ma wish list'!$D$4:$D$40,MATCH(15,'Ma wish list'!$I$4:$I$40,0))&"","") | D18: =IFERROR(INDEX('Ma wish list'!$F$4:$F$40,MATCH(15,'Ma wish list'!$I$4:$I$40,0))&"","") | E18: =IFERROR(INDEX('Ma wish list'!$G$4:$G$40,MATCH(15,'Ma wish list'!$I$4:$I$40,0))&"","")
A19: =IFERROR(INDEX('Ma wish list'!$E$4:$E$40,MATCH(16,'Ma wish list'!$I$4:$I$40,0))&"","") | B19: =IFERROR(INDEX('Ma wish list'!$A$4:$A$40,MATCH(16,'Ma wish list'!$I$4:$I$40,0))&"","") | C19: =IFERROR(INDEX('Ma wish list'!$D$4:$D$40,MATCH(16,'Ma wish list'!$I$4:$I$40,0))&"","") | D19: =IFERROR(INDEX('Ma wish list'!$F$4:$F$40,MATCH(16,'Ma wish list'!$I$4:$I$40,0))&"","") | E19: =IFERROR(INDEX('Ma wish list'!$G$4:$G$40,MATCH(16,'Ma wish list'!$I$4:$I$40,0))&"","")
A20: =IFERROR(INDEX('Ma wish list'!$E$4:$E$40,MATCH(17,'Ma wish list'!$I$4:$I$40,0))&"","") | B20: =IFERROR(INDEX('Ma wish list'!$A$4:$A$40,MATCH(17,'Ma wish list'!$I$4:$I$40,0))&"","") | C20: =IFERROR(INDEX('Ma wish list'!$D$4:$D$40,MATCH(17,'Ma wish list'!$I$4:$I$40,0))&"","") | D20: =IFERROR(INDEX('Ma wish list'!$F$4:$F$40,MATCH(17,'Ma wish list'!$I$4:$I$40,0))&"","") | E20: =IFERROR(INDEX('Ma wish list'!$G$4:$G$40,MATCH(17,'Ma wish list'!$I$4:$I$40,0))&"","")
A21: =IFERROR(INDEX('Ma wish list'!$E$4:$E$40,MATCH(18,'Ma wish list'!$I$4:$I$40,0))&"","") | B21: =IFERROR(INDEX('Ma wish list'!$A$4:$A$40,MATCH(18,'Ma wish list'!$I$4:$I$40,0))&"","") | C21: =IFERROR(INDEX('Ma wish list'!$D$4:$D$40,MATCH(18,'Ma wish list'!$I$4:$I$40,0))&"","") | D21: =IFERROR(INDEX('Ma wish list'!$F$4:$F$40,MATCH(18,'Ma wish list'!$I$4:$I$40,0))&"","") | E21: =IFERROR(INDEX('Ma wish list'!$G$4:$G$40,MATCH(18,'Ma wish list'!$I$4:$I$40,0))&"","")
A22: =IFERROR(INDEX('Ma wish list'!$E$4:$E$40,MATCH(19,'Ma wish list'!$I$4:$I$40,0))&"","") | B22: =IFERROR(INDEX('Ma wish list'!$A$4:$A$40,MATCH(19,'Ma wish list'!$I$4:$I$40,0))&"","") | C22: =IFERROR(INDEX('Ma wish list'!$D$4:$D$40,MATCH(19,'Ma wish list'!$I$4:$I$40,0))&"","") | D22: =IFERROR(INDEX('Ma wish list'!$F$4:$F$40,MATCH(19,'Ma wish list'!$I$4:$I$40,0))&"","") | E22: =IFERROR(INDEX('Ma wish list'!$G$4:$G$40,MATCH(19,'Ma wish list'!$I$4:$I$40,0))&"","")
A23: =IFERROR(INDEX('Ma wish list'!$E$4:$E$40,MATCH(20,'Ma wish list'!$I$4:$I$40,0))&"","") | B23: =IFERROR(INDEX('Ma wish list'!$A$4:$A$40,MATCH(20,'Ma wish list'!$I$4:$I$40,0))&"","") | C23: =IFERROR(INDEX('Ma wish list'!$D$4:$D$40,MATCH(20,'Ma wish list'!$I$4:$I$40,0))&"","") | D23: =IFERROR(INDEX('Ma wish list'!$F$4:$F$40,MATCH(20,'Ma wish list'!$I$4:$I$40,0))&"","") | E23: =IFERROR(INDEX('Ma wish list'!$G$4:$G$40,MATCH(20,'Ma wish list'!$I$4:$I$40,0))&"","")
A24: =IFERROR(INDEX('Ma wish list'!$E$4:$E$40,MATCH(21,'Ma wish list'!$I$4:$I$40,0))&"","") | B24: =IFERROR(INDEX('Ma wish list'!$A$4:$A$40,MATCH(21,'Ma wish list'!$I$4:$I$40,0))&"","") | C24: =IFERROR(INDEX('Ma wish list'!$D$4:$D$40,MATCH(21,'Ma wish list'!$I$4:$I$40,0))&"","") | D24: =IFERROR(INDEX('Ma wish list'!$F$4:$F$40,MATCH(21,'Ma wish list'!$I$4:$I$40,0))&"","") | E24: =IFERROR(INDEX('Ma wish list'!$G$4:$G$40,MATCH(21,'Ma wish list'!$I$4:$I$40,0))&"","")
A25: =IFERROR(INDEX('Ma wish list'!$E$4:$E$40,MATCH(22,'Ma wish list'!$I$4:$I$40,0))&"","") | B25: =IFERROR(INDEX('Ma wish list'!$A$4:$A$40,MATCH(22,'Ma wish list'!$I$4:$I$40,0))&"","") | C25: =IFERROR(INDEX('Ma wish list'!$D$4:$D$40,MATCH(22,'Ma wish list'!$I$4:$I$40,0))&"","") | D25: =IFERROR(INDEX('Ma wish list'!$F$4:$F$40,MATCH(22,'Ma wish list'!$I$4:$I$40,0))&"","") | E25: =IFERROR(INDEX('Ma wish list'!$G$4:$G$40,MATCH(22,'Ma wish list'!$I$4:$I$40,0))&"","")
A26: =IFERROR(INDEX('Ma wish list'!$E$4:$E$40,MATCH(23,'Ma wish list'!$I$4:$I$40,0))&"","") | B26: =IFERROR(INDEX('Ma wish list'!$A$4:$A$40,MATCH(23,'Ma wish list'!$I$4:$I$40,0))&"","") | C26: =IFERROR(INDEX('Ma wish list'!$D$4:$D$40,MATCH(23,'Ma wish list'!$I$4:$I$40,0))&"","") | D26: =IFERROR(INDEX('Ma wish list'!$F$4:$F$40,MATCH(23,'Ma wish list'!$I$4:$I$40,0))&"","") | E26: =IFERROR(INDEX('Ma wish list'!$G$4:$G$40,MATCH(23,'Ma wish list'!$I$4:$I$40,0))&"","")
A27: =IFERROR(INDEX('Ma wish list'!$E$4:$E$40,MATCH(24,'Ma wish list'!$I$4:$I$40,0))&"","") | B27: =IFERROR(INDEX('Ma wish list'!$A$4:$A$40,MATCH(24,'Ma wish list'!$I$4:$I$40,0))&"","") | C27: =IFERROR(INDEX('Ma wish list'!$D$4:$D$40,MATCH(24,'Ma wish list'!$I$4:$I$40,0))&"","") | D27: =IFERROR(INDEX('Ma wish list'!$F$4:$F$40,MATCH(24,'Ma wish list'!$I$4:$I$40,0))&"","") | E27: =IFERROR(INDEX('Ma wish list'!$G$4:$G$40,MATCH(24,'Ma wish list'!$I$4:$I$40,0))&"","")
A28: =IFERROR(INDEX('Ma wish list'!$E$4:$E$40,MATCH(25,'Ma wish list'!$I$4:$I$40,0))&"","") | B28: =IFERROR(INDEX('Ma wish list'!$A$4:$A$40,MATCH(25,'Ma wish list'!$I$4:$I$40,0))&"","") | C28: =IFERROR(INDEX('Ma wish list'!$D$4:$D$40,MATCH(25,'Ma wish list'!$I$4:$I$40,0))&"","") | D28: =IFERROR(INDEX('Ma wish list'!$F$4:$F$40,MATCH(25,'Ma wish list'!$I$4:$I$40,0))&"","") | E28: =IFERROR(INDEX('Ma wish list'!$G$4:$G$40,MATCH(25,'Ma wish list'!$I$4:$I$40,0))&"","")
A29: =IFERROR(INDEX('Ma wish list'!$E$4:$E$40,MATCH(26,'Ma wish list'!$I$4:$I$40,0))&"","") | B29: =IFERROR(INDEX('Ma wish list'!$A$4:$A$40,MATCH(26,'Ma wish list'!$I$4:$I$40,0))&"","") | C29: =IFERROR(INDEX('Ma wish list'!$D$4:$D$40,MATCH(26,'Ma wish list'!$I$4:$I$40,0))&"","") | D29: =IFERROR(INDEX('Ma wish list'!$F$4:$F$40,MATCH(26,'Ma wish list'!$I$4:$I$40,0))&"","") | E29: =IFERROR(INDEX('Ma wish list'!$G$4:$G$40,MATCH(26,'Ma wish list'!$I$4:$I$40,0))&"","")
A30: =IFERROR(INDEX('Ma wish list'!$E$4:$E$40,MATCH(27,'Ma wish list'!$I$4:$I$40,0))&"","") | B30: =IFERROR(INDEX('Ma wish list'!$A$4:$A$40,MATCH(27,'Ma wish list'!$I$4:$I$40,0))&"","") | C30: =IFERROR(INDEX('Ma wish list'!$D$4:$D$40,MATCH(27,'Ma wish list'!$I$4:$I$40,0))&"","") | D30: =IFERROR(INDEX('Ma wish list'!$F$4:$F$40,MATCH(27,'Ma wish list'!$I$4:$I$40,0))&"","") | E30: =IFERROR(INDEX('Ma wish list'!$G$4:$G$40,MATCH(27,'Ma wish list'!$I$4:$I$40,0))&"","")
A31: =IFERROR(INDEX('Ma wish list'!$E$4:$E$40,MATCH(28,'Ma wish list'!$I$4:$I$40,0))&"","") | B31: =IFERROR(INDEX('Ma wish list'!$A$4:$A$40,MATCH(28,'Ma wish list'!$I$4:$I$40,0))&"","") | C31: =IFERROR(INDEX('Ma wish list'!$D$4:$D$40,MATCH(28,'Ma wish list'!$I$4:$I$40,0))&"","") | D31: =IFERROR(INDEX('Ma wish list'!$F$4:$F$40,MATCH(28,'Ma wish list'!$I$4:$I$40,0))&"","") | E31: =IFERROR(INDEX('Ma wish list'!$G$4:$G$40,MATCH(28,'Ma wish list'!$I$4:$I$40,0))&"","")
A32: =IFERROR(INDEX('Ma wish list'!$E$4:$E$40,MATCH(29,'Ma wish list'!$I$4:$I$40,0))&"","") | B32: =IFERROR(INDEX('Ma wish list'!$A$4:$A$40,MATCH(29,'Ma wish list'!$I$4:$I$40,0))&"","") | C32: =IFERROR(INDEX('Ma wish list'!$D$4:$D$40,MATCH(29,'Ma wish list'!$I$4:$I$40,0))&"","") | D32: =IFERROR(INDEX('Ma wish list'!$F$4:$F$40,MATCH(29,'Ma wish list'!$I$4:$I$40,0))&"","") | E32: =IFERROR(INDEX('Ma wish list'!$G$4:$G$40,MATCH(29,'Ma wish list'!$I$4:$I$40,0))&"","")
A33: =IFERROR(INDEX('Ma wish list'!$E$4:$E$40,MATCH(30,'Ma wish list'!$I$4:$I$40,0))&"","") | B33: =IFERROR(INDEX('Ma wish list'!$A$4:$A$40,MATCH(30,'Ma wish list'!$I$4:$I$40,0))&"","") | C33: =IFERROR(INDEX('Ma wish list'!$D$4:$D$40,MATCH(30,'Ma wish list'!$I$4:$I$40,0))&"","") | D33: =IFERROR(INDEX('Ma wish list'!$F$4:$F$40,MATCH(30,'Ma wish list'!$I$4:$I$40,0))&"","") | E33: =IFERROR(INDEX('Ma wish list'!$G$4:$G$40,MATCH(30,'Ma wish list'!$I$4:$I$40,0))&"","")
A34: ✏️ Mes idées perso

Sheet Papa
A1: 🎁 Idées cadeaux – Papa
A2: Lignes jaunes = automatiques depuis « Ma wish list » (statut et notes se modifient là-bas). Lignes blanches = tes idées perso.
A3: Pour qui | B3: Idée cadeau | C3: Où l'acheter / lien | D3: Statut | E3: Notes
A4: =IFERROR(INDEX('Ma wish list'!$E$4:$E$40,MATCH(1,'Ma wish list'!$H$4:$H$40,0))&"","") | B4: =IFERROR(INDEX('Ma wish list'!$A$4:$A$40,MATCH(1,'Ma wish list'!$H$4:$H$40,0))&"","") | C4: =IFERROR(INDEX('Ma wish list'!$D$4:$D$40,MATCH(1,'Ma wish list'!$H$4:$H$40,0))&"","") | D4: =IFERROR(INDEX('Ma wish list'!$F$4:$F$40,MATCH(1,'Ma wish list'!$H$4:$H$40,0))&"","") | E4: =IFERROR(INDEX('Ma wish list'!$G$4:$G$40,MATCH(1,'Ma wish list'!$H$4:$H$40,0))&"","")
A5: =IFERROR(INDEX('Ma wish list'!$E$4:$E$40,MATCH(2,'Ma wish list'!$H$4:$H$40,0))&"","") | B5: =IFERROR(INDEX('Ma wish list'!$A$4:$A$40,MATCH(2,'Ma wish list'!$H$4:$H$40,0))&"","") | C5: =IFERROR(INDEX('Ma wish list'!$D$4:$D$40,MATCH(2,'Ma wish list'!$H$4:$H$40,0))&"","") | D5: =IFERROR(INDEX('Ma wish list'!$F$4:$F$40,MATCH(2,'Ma wish list'!$H$4:$H$40,0))&"","") | E5: =IFERROR(INDEX('Ma wish list'!$G$4:$G$40,MATCH(2,'Ma wish list'!$H$4:$H$40,0))&"","")
A6: =IFERROR(INDEX('Ma wish list'!$E$4:$E$40,MATCH(3,'Ma wish list'!$H$4:$H$40,0))&"","") | B6: =IFERROR(INDEX('Ma wish list'!$A$4:$A$40,MATCH(3,'Ma wish list'!$H$4:$H$40,0))&"","") | C6: =IFERROR(INDEX('Ma wish list'!$D$4:$D$40,MATCH(3,'Ma wish list'!$H$4:$H$40,0))&"","") | D6: =IFERROR(INDEX('Ma wish list'!$F$4:$F$40,MATCH(3,'Ma wish list'!$H$4:$H$40,0))&"","") | E6: =IFERROR(INDEX('Ma wish list'!$G$4:$G$40,MATCH(3,'Ma wish list'!$H$4:$H$40,0))&"","")
A7: =IFERROR(INDEX('Ma wish list'!$E$4:$E$40,MATCH(4,'Ma wish list'!$H$4:$H$40,0))&"","") | B7: =IFERROR(INDEX('Ma wish list'!$A$4:$A$40,MATCH(4,'Ma wish list'!$H$4:$H$40,0))&"","") | C7: =IFERROR(INDEX('Ma wish list'!$D$4:$D$40,MATCH(4,'Ma wish list'!$H$4:$H$40,0))&"","") | D7: =IFERROR(INDEX('Ma wish list'!$F$4:$F$40,MATCH(4,'Ma wish list'!$H$4:$H$40,0))&"","") | E7: =IFERROR(INDEX('Ma wish list'!$G$4:$G$40,MATCH(4,'Ma wish list'!$H$4:$H$40,0))&"","")
A8: =IFERROR(INDEX('Ma wish list'!$E$4:$E$40,MATCH(5,'Ma wish list'!$H$4:$H$40,0))&"","") | B8: =IFERROR(INDEX('Ma wish list'!$A$4:$A$40,MATCH(5,'Ma wish list'!$H$4:$H$40,0))&"","") | C8: =IFERROR(INDEX('Ma wish list'!$D$4:$D$40,MATCH(5,'Ma wish list'!$H$4:$H$40,0))&"","") | D8: =IFERROR(INDEX('Ma wish list'!$F$4:$F$40,MATCH(5,'Ma wish list'!$H$4:$H$40,0))&"","") | E8: =IFERROR(INDEX('Ma wish list'!$G$4:$G$40,MATCH(5,'Ma wish list'!$H$4:$H$40,0))&"","")
A9: =IFERROR(INDEX('Ma wish list'!$E$4:$E$40,MATCH(6,'Ma wish list'!$H$4:$H$40,0))&"","") | B9: =IFERROR(INDEX('Ma wish list'!$A$4:$A$40,MATCH(6,'Ma wish list'!$H$4:$H$40,0))&"","") | C9: =IFERROR(INDEX('Ma wish list'!$D$4:$D$40,MATCH(6,'Ma wish list'!$H$4:$H$40,0))&"","") | D9: =IFERROR(INDEX('Ma wish list'!$F$4:$F$40,MATCH(6,'Ma wish list'!$H$4:$H$40,0))&"","") | E9: =IFERROR(INDEX('Ma wish list'!$G$4:$G$40,MATCH(6,'Ma wish list'!$H$4:$H$40,0))&"","")
A10: =IFERROR(INDEX('Ma wish list'!$E$4:$E$40,MATCH(7,'Ma wish list'!$H$4:$H$40,0))&"","") | B10: =IFERROR(INDEX('Ma wish list'!$A$4:$A$40,MATCH(7,'Ma wish list'!$H$4:$H$40,0))&"","") | C10: =IFERROR(INDEX('Ma wish list'!$D$4:$D$40,MATCH(7,'Ma wish list'!$H$4:$H$40,0))&"","") | D10: =IFERROR(INDEX('Ma wish list'!$F$4:$F$40,MATCH(7,'Ma wish list'!$H$4:$H$40,0))&"","") | E10: =IFERROR(INDEX('Ma wish list'!$G$4:$G$40,MATCH(7,'Ma wish list'!$H$4:$H$40,0))&"","")
A11: =IFERROR(INDEX('Ma wish list'!$E$4:$E$40,MATCH(8,'Ma wish list'!$H$4:$H$40,0))&"","") | B11: =IFERROR(INDEX('Ma wish list'!$A$4:$A$40,MATCH(8,'Ma wish list'!$H$4:$H$40,0))&"","") | C11: =IFERROR(INDEX('Ma wish list'!$D$4:$D$40,MATCH(8,'Ma wish list'!$H$4:$H$40,0))&"","") | D11: =IFERROR(INDEX('Ma wish list'!$F$4:$F$40,MATCH(8,'Ma wish list'!$H$4:$H$40,0))&"","") | E11: =IFERROR(INDEX('Ma wish list'!$G$4:$G$40,MATCH(8,'Ma wish list'!$H$4:$H$40,0))&"","")
A12: =IFERROR(INDEX('Ma wish list'!$E$4:$E$40,MATCH(9,'Ma wish list'!$H$4:$H$40,0))&"","") | B12: =IFERROR(INDEX('Ma wish list'!$A$4:$A$40,MATCH(9,'Ma wish list'!$H$4:$H$40,0))&"","") | C12: =IFERROR(INDEX('Ma wish list'!$D$4:$D$40,MATCH(9,'Ma wish list'!$H$4:$H$40,0))&"","") | D12: =IFERROR(INDEX('Ma wish list'!$F$4:$F$40,MATCH(9,'Ma wish list'!$H$4:$H$40,0))&"","") | E12: =IFERROR(INDEX('Ma wish list'!$G$4:$G$40,MATCH(9,'Ma wish list'!$H$4:$H$40,0))&"","")
A13: =IFERROR(INDEX('Ma wish list'!$E$4:$E$40,MATCH(10,'Ma wish list'!$H$4:$H$40,0))&"","") | B13: =IFERROR(INDEX('Ma wish list'!$A$4:$A$40,MATCH(10,'Ma wish list'!$H$4:$H$40,0))&"","") | C13: =IFERROR(INDEX('Ma wish list'!$D$4:$D$40,MATCH(10,'Ma wish list'!$H$4:$H$40,0))&"","") | D13: =IFERROR(INDEX('Ma wish list'!$F$4:$F$40,MATCH(10,'Ma wish list'!$H$4:$H$40,0))&"","") | E13: =IFERROR(INDEX('Ma wish list'!$G$4:$G$40,MATCH(10,'Ma wish list'!$H$4:$H$40,0))&"","")
A14: =IFERROR(INDEX('Ma wish list'!$E$4:$E$40,MATCH(11,'Ma wish list'!$H$4:$H$40,0))&"","") | B14: =IFERROR(INDEX('Ma wish list'!$A$4:$A$40,MATCH(11,'Ma wish list'!$H$4:$H$40,0))&"","") | C14: =IFERROR(INDEX('Ma wish list'!$D$4:$D$40,MATCH(11,'Ma wish list'!$H$4:$H$40,0))&"","") | D14: =IFERROR(INDEX('Ma wish list'!$F$4:$F$40,MATCH(11,'Ma wish list'!$H$4:$H$40,0))&"","") | E14: =IFERROR(INDEX('Ma wish list'!$G$4:$G$40,MATCH(11,'Ma wish list'!$H$4:$H$40,0))&"","")
A15: =IFERROR(INDEX('Ma wish list'!$E$4:$E$40,MATCH(12,'Ma wish list'!$H$4:$H$40,0))&"","") | B15: =IFERROR(INDEX('Ma wish list'!$A$4:$A$40,MATCH(12,'Ma wish list'!$H$4:$H$40,0))&"","") | C15: =IFERROR(INDEX('Ma wish list'!$D$4:$D$40,MATCH(12,'Ma wish list'!$H$4:$H$40,0))&"","") | D15: =IFERROR(INDEX('Ma wish list'!$F$4:$F$40,MATCH(12,'Ma wish list'!$H$4:$H$40,0))&"","") | E15: =IFERROR(INDEX('Ma wish list'!$G$4:$G$40,MATCH(12,'Ma wish list'!$H$4:$H$40,0))&"","")
A16: =IFERROR(INDEX('Ma wish list'!$E$4:$E$40,MATCH(13,'Ma wish list'!$H$4:$H$40,0))&"","") | B16: =IFERROR(INDEX('Ma wish list'!$A$4:$A$40,MATCH(13,'Ma wish list'!$H$4:$H$40,0))&"","") | C16: =IFERROR(INDEX('Ma wish list'!$D$4:$D$40,MATCH(13,'Ma wish list'!$H$4:$H$40,0))&"","") | D16: =IFERROR(INDEX('Ma wish list'!$F$4:$F$40,MATCH(13,'Ma wish list'!$H$4:$H$40,0))&"","") | E16: =IFERROR(INDEX('Ma wish list'!$G$4:$G$40,MATCH(13,'Ma wish list'!$H$4:$H$40,0))&"","")
A17: =IFERROR(INDEX('Ma wish list'!$E$4:$E$40,MATCH(14,'Ma wish list'!$H$4:$H$40,0))&"","") | B17: =IFERROR(INDEX('Ma wish list'!$A$4:$A$40,MATCH(14,'Ma wish list'!$H$4:$H$40,0))&"","") | C17: =IFERROR(INDEX('Ma wish list'!$D$4:$D$40,MATCH(14,'Ma wish list'!$H$4:$H$40,0))&"","") | D17: =IFERROR(INDEX('Ma wish list'!$F$4:$F$40,MATCH(14,'Ma wish list'!$H$4:$H$40,0))&"","") | E17: =IFERROR(INDEX('Ma wish list'!$G$4:$G$40,MATCH(14,'Ma wish list'!$H$4:$H$40,0))&"","")
A18: =IFERROR(INDEX('Ma wish list'!$E$4:$E$40,MATCH(15,'Ma wish list'!$H$4:$H$40,0))&"","") | B18: =IFERROR(INDEX('Ma wish list'!$A$4:$A$40,MATCH(15,'Ma wish list'!$H$4:$H$40,0))&"","") | C18: =IFERROR(INDEX('Ma wish list'!$D$4:$D$40,MATCH(15,'Ma wish list'!$H$4:$H$40,0))&"","") | D18: =IFERROR(INDEX('Ma wish list'!$F$4:$F$40,MATCH(15,'Ma wish list'!$H$4:$H$40,0))&"","") | E18: =IFERROR(INDEX('Ma wish list'!$G$4:$G$40,MATCH(15,'Ma wish list'!$H$4:$H$40,0))&"","")
A19: =IFERROR(INDEX('Ma wish list'!$E$4:$E$40,MATCH(16,'Ma wish list'!$H$4:$H$40,0))&"","") | B19: =IFERROR(INDEX('Ma wish list'!$A$4:$A$40,MATCH(16,'Ma wish list'!$H$4:$H$40,0))&"","") | C19: =IFERROR(INDEX('Ma wish list'!$D$4:$D$40,MATCH(16,'Ma wish list'!$H$4:$H$40,0))&"","") | D19: =IFERROR(INDEX('Ma wish list'!$F$4:$F$40,MATCH(16,'Ma wish list'!$H$4:$H$40,0))&"","") | E19: =IFERROR(INDEX('Ma wish list'!$G$4:$G$40,MATCH(16,'Ma wish list'!$H$4:$H$40,0))&"","")
A20: =IFERROR(INDEX('Ma wish list'!$E$4:$E$40,MATCH(17,'Ma wish list'!$H$4:$H$40,0))&"","") | B20: =IFERROR(INDEX('Ma wish list'!$A$4:$A$40,MATCH(17,'Ma wish list'!$H$4:$H$40,0))&"","") | C20: =IFERROR(INDEX('Ma wish list'!$D$4:$D$40,MATCH(17,'Ma wish list'!$H$4:$H$40,0))&"","") | D20: =IFERROR(INDEX('Ma wish list'!$F$4:$F$40,MATCH(17,'Ma wish list'!$H$4:$H$40,0))&"","") | E20: =IFERROR(INDEX('Ma wish list'!$G$4:$G$40,MATCH(17,'Ma wish list'!$H$4:$H$40,0))&"","")
A21: =IFERROR(INDEX('Ma wish list'!$E$4:$E$40,MATCH(18,'Ma wish list'!$H$4:$H$40,0))&"","") | B21: =IFERROR(INDEX('Ma wish list'!$A$4:$A$40,MATCH(18,'Ma wish list'!$H$4:$H$40,0))&"","") | C21: =IFERROR(INDEX('Ma wish list'!$D$4:$D$40,MATCH(18,'Ma wish list'!$H$4:$H$40,0))&"","") | D21: =IFERROR(INDEX('Ma wish list'!$F$4:$F$40,MATCH(18,'Ma wish list'!$H$4:$H$40,0))&"","") | E21: =IFERROR(INDEX('Ma wish list'!$G$4:$G$40,MATCH(18,'Ma wish list'!$H$4:$H$40,0))&"","")
A22: =IFERROR(INDEX('Ma wish list'!$E$4:$E$40,MATCH(19,'Ma wish list'!$H$4:$H$40,0))&"","") | B22: =IFERROR(INDEX('Ma wish list'!$A$4:$A$40,MATCH(19,'Ma wish list'!$H$4:$H$40,0))&"","") | C22: =IFERROR(INDEX('Ma wish list'!$D$4:$D$40,MATCH(19,'Ma wish list'!$H$4:$H$40,0))&"","") | D22: =IFERROR(INDEX('Ma wish list'!$F$4:$F$40,MATCH(19,'Ma wish list'!$H$4:$H$40,0))&"","") | E22: =IFERROR(INDEX('Ma wish list'!$G$4:$G$40,MATCH(19,'Ma wish list'!$H$4:$H$40,0))&"","")
A23: =IFERROR(INDEX('Ma wish list'!$E$4:$E$40,MATCH(20,'Ma wish list'!$H$4:$H$40,0))&"","") | B23: =IFERROR(INDEX('Ma wish list'!$A$4:$A$40,MATCH(20,'Ma wish list'!$H$4:$H$40,0))&"","") | C23: =IFERROR(INDEX('Ma wish list'!$D$4:$D$40,MATCH(20,'Ma wish list'!$H$4:$H$40,0))&"","") | D23: =IFERROR(INDEX('Ma wish list'!$F$4:$F$40,MATCH(20,'Ma wish list'!$H$4:$H$40,0))&"","") | E23: =IFERROR(INDEX('Ma wish list'!$G$4:$G$40,MATCH(20,'Ma wish list'!$H$4:$H$40,0))&"","")
A24: =IFERROR(INDEX('Ma wish list'!$E$4:$E$40,MATCH(21,'Ma wish list'!$H$4:$H$40,0))&"","") | B24: =IFERROR(INDEX('Ma wish list'!$A$4:$A$40,MATCH(21,'Ma wish list'!$H$4:$H$40,0))&"","") | C24: =IFERROR(INDEX('Ma wish list'!$D$4:$D$40,MATCH(21,'Ma wish list'!$H$4:$H$40,0))&"","") | D24: =IFERROR(INDEX('Ma wish list'!$F$4:$F$40,MATCH(21,'Ma wish list'!$H$4:$H$40,0))&"","") | E24: =IFERROR(INDEX('Ma wish list'!$G$4:$G$40,MATCH(21,'Ma wish list'!$H$4:$H$40,0))&"","")
A25: =IFERROR(INDEX('Ma wish list'!$E$4:$E$40,MATCH(22,'Ma wish list'!$H$4:$H$40,0))&"","") | B25: =IFERROR(INDEX('Ma wish list'!$A$4:$A$40,MATCH(22,'Ma wish list'!$H$4:$H$40,0))&"","") | C25: =IFERROR(INDEX('Ma wish list'!$D$4:$D$40,MATCH(22,'Ma wish list'!$H$4:$H$40,0))&"","") | D25: =IFERROR(INDEX('Ma wish list'!$F$4:$F$40,MATCH(22,'Ma wish list'!$H$4:$H$40,0))&"","") | E25: =IFERROR(INDEX('Ma wish list'!$G$4:$G$40,MATCH(22,'Ma wish list'!$H$4:$H$40,0))&"","")
A26: =IFERROR(INDEX('Ma wish list'!$E$4:$E$40,MATCH(23,'Ma wish list'!$H$4:$H$40,0))&"","") | B26: =IFERROR(INDEX('Ma wish list'!$A$4:$A$40,MATCH(23,'Ma wish list'!$H$4:$H$40,0))&"","") | C26: =IFERROR(INDEX('Ma wish list'!$D$4:$D$40,MATCH(23,'Ma wish list'!$H$4:$H$40,0))&"","") | D26: =IFERROR(INDEX('Ma wish list'!$F$4:$F$40,MATCH(23,'Ma wish list'!$H$4:$H$40,0))&"","") | E26: =IFERROR(INDEX('Ma wish list'!$G$4:$G$40,MATCH(23,'Ma wish list'!$H$4:$H$40,0))&"","")
A27: =IFERROR(INDEX('Ma wish list'!$E$4:$E$40,MATCH(24,'Ma wish list'!$H$4:$H$40,0))&"","") | B27: =IFERROR(INDEX('Ma wish list'!$A$4:$A$40,MATCH(24,'Ma wish list'!$H$4:$H$40,0))&"","") | C27: =IFERROR(INDEX('Ma wish list'!$D$4:$D$40,MATCH(24,'Ma wish list'!$H$4:$H$40,0))&"","") | D27: =IFERROR(INDEX('Ma wish list'!$F$4:$F$40,MATCH(24,'Ma wish list'!$H$4:$H$40,0))&"","") | E27: =IFERROR(INDEX('Ma wish list'!$G$4:$G$40,MATCH(24,'Ma wish list'!$H$4:$H$40,0))&"","")
A28: =IFERROR(INDEX('Ma wish list'!$E$4:$E$40,MATCH(25,'Ma wish list'!$H$4:$H$40,0))&"","") | B28: =IFERROR(INDEX('Ma wish list'!$A$4:$A$40,MATCH(25,'Ma wish list'!$H$4:$H$40,0))&"","") | C28: =IFERROR(INDEX('Ma wish list'!$D$4:$D$40,MATCH(25,'Ma wish list'!$H$4:$H$40,0))&"","") | D28: =IFERROR(INDEX('Ma wish list'!$F$4:$F$40,MATCH(25,'Ma wish list'!$H$4:$H$40,0))&"","") | E28: =IFERROR(INDEX('Ma wish list'!$G$4:$G$40,MATCH(25,'Ma wish list'!$H$4:$H$40,0))&"","")
A29: =IFERROR(INDEX('Ma wish list'!$E$4:$E$40,MATCH(26,'Ma wish list'!$H$4:$H$40,0))&"","") | B29: =IFERROR(INDEX('Ma wish list'!$A$4:$A$40,MATCH(26,'Ma wish list'!$H$4:$H$40,0))&"","") | C29: =IFERROR(INDEX('Ma wish list'!$D$4:$D$40,MATCH(26,'Ma wish list'!$H$4:$H$40,0))&"","") | D29: =IFERROR(INDEX('Ma wish list'!$F$4:$F$40,MATCH(26,'Ma wish list'!$H$4:$H$40,0))&"","") | E29: =IFERROR(INDEX('Ma wish list'!$G$4:$G$40,MATCH(26,'Ma wish list'!$H$4:$H$40,0))&"","")
A30: =IFERROR(INDEX('Ma wish list'!$E$4:$E$40,MATCH(27,'Ma wish list'!$H$4:$H$40,0))&"","") | B30: =IFERROR(INDEX('Ma wish list'!$A$4:$A$40,MATCH(27,'Ma wish list'!$H$4:$H$40,0))&"","") | C30: =IFERROR(INDEX('Ma wish list'!$D$4:$D$40,MATCH(27,'Ma wish list'!$H$4:$H$40,0))&"","") | D30: =IFERROR(INDEX('Ma wish list'!$F$4:$F$40,MATCH(27,'Ma wish list'!$H$4:$H$40,0))&"","") | E30: =IFERROR(INDEX('Ma wish list'!$G$4:$G$40,MATCH(27,'Ma wish list'!$H$4:$H$40,0))&"","")
A31: =IFERROR(INDEX('Ma wish list'!$E$4:$E$40,MATCH(28,'Ma wish list'!$H$4:$H$40,0))&"","") | B31: =IFERROR(INDEX('Ma wish list'!$A$4:$A$40,MATCH(28,'Ma wish list'!$H$4:$H$40,0))&"","") | C31: =IFERROR(INDEX('Ma wish list'!$D$4:$D$40,MATCH(28,'Ma wish list'!$H$4:$H$40,0))&"","") | D31: =IFERROR(INDEX('Ma wish list'!$F$4:$F$40,MATCH(28,'Ma wish list'!$H$4:$H$40,0))&"","") | E31: =IFERROR(INDEX('Ma wish list'!$G$4:$G$40,MATCH(28,'Ma wish list'!$H$4:$H$40,0))&"","")
A32: =IFERROR(INDEX('Ma wish list'!$E$4:$E$40,MATCH(29,'Ma wish list'!$H$4:$H$40,0))&"","") | B32: =IFERROR(INDEX('Ma wish list'!$A$4:$A$40,MATCH(29,'Ma wish list'!$H$4:$H$40,0))&"","") | C32: =IFERROR(INDEX('Ma wish list'!$D$4:$D$40,MATCH(29,'Ma wish list'!$H$4:$H$40,0))&"","") | D32: =IFERROR(INDEX('Ma wish list'!$F$4:$F$40,MATCH(29,'Ma wish list'!$H$4:$H$40,0))&"","") | E32: =IFERROR(INDEX('Ma wish list'!$G$4:$G$40,MATCH(29,'Ma wish list'!$H$4:$H$40,0))&"","")
A33: =IFERROR(INDEX('Ma wish list'!$E$4:$E$40,MATCH(30,'Ma wish list'!$H$4:$H$40,0))&"","") | B33: =IFERROR(INDEX('Ma wish list'!$A$4:$A$40,MATCH(30,'Ma wish list'!$H$4:$H$40,0))&"","") | C33: =IFERROR(INDEX('Ma wish list'!$D$4:$D$40,MATCH(30,'Ma wish list'!$H$4:$H$40,0))&"","") | D33: =IFERROR(INDEX('Ma wish list'!$F$4:$F$40,MATCH(30,'Ma wish list'!$H$4:$H$40,0))&"","") | E33: =IFERROR(INDEX('Ma wish list'!$G$4:$G$40,MATCH(30,'Ma wish list'!$H$4:$H$40,0))&"","")
A34: ✏️ Mes idées perso

Sheet Ma wish list
A1: ⭐ Ma wish list – choisis « Offert par » pour l'envoyer dans le bon onglet
A3: Article | B3: Catégorie | C3: Priorité | D3: Lien | E3: Offert par | F3: Statut | G3: Notes | H3: n° Papa | I3: n° autres
A4: Glacière transport repas midi | B4: Divers | H4: =IF($E4="Papa",COUNTIF($E$4:$E4,"Papa"),"") | I4: =IF(OR($E4="",$E4="Papa",$E4="Autre"),"",COUNTIFS($E$4:$E4,"<>Papa",$E$4:$E4,"<>Autre",$E$4:$E4,"<>"))
A5: Compressport R2V2 | B5: Course / Trail | H5: =IF($E5="Papa",COUNTIF($E$4:$E5,"Papa"),"") | I5: =IF(OR($E5="",$E5="Papa",$E5="Autre"),"",COUNTIFS($E$4:$E5,"<>Papa",$E$4:$E5,"<>Autre",$E$4:$E5,"<>"))
A6: Gel Meltonic | B6: Course / Trail | H6: =IF($E6="Papa",COUNTIF($E$4:$E6,"Papa"),"") | I6: =IF(OR($E6="",$E6="Papa",$E6="Autre"),"",COUNTIFS($E$4:$E6,"<>Papa",$E$4:$E6,"<>Autre",$E$4:$E6,"<>"))
A7: Débardeur course | B7: Course / Trail | H7: =IF($E7="Papa",COUNTIF($E$4:$E7,"Papa"),"") | I7: =IF(OR($E7="",$E7="Papa",$E7="Autre"),"",COUNTIFS($E$4:$E7,"<>Papa",$E$4:$E7,"<>Autre",$E$4:$E7,"<>"))
A8: Écouteurs | B8: Tech | H8: =IF($E8="Papa",COUNTIF($E$4:$E8,"Papa"),"") | I8: =IF(OR($E8="",$E8="Papa",$E8="Autre"),"",COUNTIFS($E$4:$E8,"<>Papa",$E$4:$E8,"<>Autre",$E$4:$E8,"<>"))
A9: Garmin HRM Pro Plus | B9: Tech | H9: =IF($E9="Papa",COUNTIF($E$4:$E9,"Papa"),"") | I9: =IF(OR($E9="",$E9="Papa",$E9="Autre"),"",COUNTIFS($E$4:$E9,"<>Papa",$E$4:$E9,"<>Autre",$E$4:$E9,"<>"))
A10: Chaussettes trail | B10: Course / Trail | H10: =IF($E10="Papa",COUNTIF($E$4:$E10,"Papa"),"") | I10: =IF(OR($E10="",$E10="Papa",$E10="Autre"),"",COUNTIFS($E$4:$E10,"<>Papa",$E$4:$E10,"<>Autre",$E$4:$E10,"<>"))
A11: Vêtements course à pied | B11: Course / Trail | H11: =IF($E11="Papa",COUNTIF($E$4:$E11,"Papa"),"") | I11: =IF(OR($E11="",$E11="Papa",$E11="Autre"),"",COUNTIFS($E$4:$E11,"<>Papa",$E$4:$E11,"<>Autre",$E$4:$E11,"<>"))
A12: Casquette | B12: Course / Trail | H12: =IF($E12="Papa",COUNTIF($E$4:$E12,"Papa"),"") | I12: =IF(OR($E12="",$E12="Papa",$E12="Autre"),"",COUNTIFS($E$4:$E12,"<>Papa",$E$4:$E12,"<>Autre",$E$4:$E12,"<>"))
A13: Bâtons de trail | B13: Course / Trail | H13: =IF($E13="Papa",COUNTIF($E$4:$E13,"Papa"),"") | I13: =IF(OR($E13="",$E13="Papa",$E13="Autre"),"",COUNTIFS($E$4:$E13,"<>Papa",$E$4:$E13,"<>Autre",$E$4:$E13,"<>"))
A14: Sac de sport grand under | B14: Sport | H14: =IF($E14="Papa",COUNTIF($E$4:$E14,"Papa"),"") | I14: =IF(OR($E14="",$E14="Papa",$E14="Autre"),"",COUNTIFS($E$4:$E14,"<>Papa",$E$4:$E14,"<>Autre",$E$4:$E14,"<>"))
A15: PS5 + Madden | B15: Tech | H15: =IF($E15="Papa",COUNTIF($E$4:$E15,"Papa"),"") | I15: =IF(OR($E15="",$E15="Papa",$E15="Autre"),"",COUNTIFS($E$4:$E15,"<>Papa",$E$4:$E15,"<>Autre",$E$4:$E15,"<>"))
... A18: Raquette padel | B18: Sport | H18: =IF($E18="Papa",COUNTIF($E$4:$E18,"Papa"),"") | I18: =IF(OR($E18="",$E18="Papa",$E18="Autre"),"",COUNTIFS($E$4:$E18,"<>Papa",$E$4:$E18,"<>Autre",$E$4:$E18,"<>"))
A19: Montre (style terrain / rétro) | B19: Tech | D19: https://timex.eu/products/expedition-sierra-40mm-fabric-strap-watch-tw2v22800 https://charlie-paris.com/products/grx-mecaquartz-chronographe-evo-iii?variant=50144588857670 | G19: Timex Expedition Sierra 40 mm (119 €) / Charlie GRX mecaquartz chrono (395 €) | H19: =IF($E19="Papa",COUNTIF($E$4:$E19,"Papa"),"") | I19: =IF(OR($E19="",$E19="Papa",$E19="Autre"),"",COUNTIFS($E$4:$E19,"<>Papa",$E$4:$E19,"<>Autre",$E$4:$E19,"<>"))
A20: Box U2 | B20: Divers | H20: =IF($E20="Papa",COUNTIF($E$4:$E20,"Papa"),"") | I20: =IF(OR($E20="",$E20="Papa",$E20="Autre"),"",COUNTIFS($E$4:$E20,"<>Papa",$E$4:$E20,"<>Autre",$E$4:$E20,"<>"))
A21: Chaussures On | B21: Course / Trail | H21: =IF($E21="Papa",COUNTIF($E$4:$E21,"Papa"),"") | I21: =IF(OR($E21="",$E21="Papa",$E21="Autre"),"",COUNTIFS($E$4:$E21,"<>Papa",$E$4:$E21,"<>Autre",$E$4:$E21,"<>"))
A22: Coque téléphone | B22: Tech | H22: =IF($E22="Papa",COUNTIF($E$4:$E22,"Papa"),"") | I22: =IF(OR($E22="",$E22="Papa",$E22="Autre"),"",COUNTIFS($E$4:$E22,"<>Papa",$E$4:$E22,"<>Autre",$E$4:$E22,"<>"))
A23: Montre – Timex Expedition North Field Post Solar 41 mm | B23: Tech | D23: https://ablogtowatch.com/watch-review-timex-expedition-north-field-post-solar-41mm | G23: Quartz solaire, 100 m. Lien = test. Env. 170-180 $ (prix à vérifier en €) | H23: =IF($E23="Papa",COUNTIF($E$4:$E23,"Papa"),"") | I23: =IF(OR($E23="",$E23="Papa",$E23="Autre"),"",COUNTIFS($E$4:$E23,"<>Papa",$E$4:$E23,"<>Autre",$E$4:$E23,"<>"))
A24: Montre – Citizen Eco-Drive Garrison BM8180 | B24: Tech | D24: https://longislandwatch.com/products/citizen-eco-drive-garrison-watch-with-black-dial-and-green-strap-bm8180-03e | G24: Solaire, 37 mm, 100 m. Prix très variable, à vérifier en France | H24: =IF($E24="Papa",COUNTIF($E$4:$E24,"Papa"),"") | I24: =IF(OR($E24="",$E24="Papa",$E24="Autre"),"",COUNTIFS($E$4:$E24,"<>Papa",$E$4:$E24,"<>Autre",$E$4:$E24,"<>"))
A25: Montre – Seiko 5 SNK809 | B25: Tech | D25: https://www.ebay.de/p/24050466267 | G25: Automatique, classique de terrain. Env. 218 € sur une annonce eBay.de, à comparer | H25: =IF($E25="Papa",COUNTIF($E$4:$E25,"Papa"),"") | I25: =IF(OR($E25="",$E25="Papa",$E25="Autre"),"",COUNTIFS($E$4:$E25,"<>Papa",$E$4:$E25,"<>Autre",$E$4:$E25,"<>"))
A26: Montre – Hamilton Khaki Field Quartz 40 mm | B26: Tech | D26: https://www.thewatchpages.com/watches/hamilton-khaki-field-quartz-40-h68551933 | G26: Référence du genre, prix catalogue env. 575-595 $ (haut de gamme) | H26: =IF($E26="Papa",COUNTIF($E$4:$E26,"Papa"),"") | I26: =IF(OR($E26="",$E26="Papa",$E26="Autre"),"",COUNTIFS($E$4:$E26,"<>Papa",$E$4:$E26,"<>Autre",$E$4:$E26,"<>"))
A27: Montre – Yema Rallygraf (chrono mecaquartz) | B27: Tech | D27: https://jamaisvulgaire.com/conseil-montre-homme/meilleure-montre-chronographe-homme-moins-de-500-euros/ | G27: Piste pour un chrono mecaquartz < 500 €. Lien = guide, modèle à vérifier | H27: =IF($E27="Papa",COUNTIF($E$4:$E27,"Papa"),"") | I27: =IF(OR($E27="",$E27="Papa",$E27="Autre"),"",COUNTIFS($E$4:$E27,"<>Papa",$E$4:$E27,"<>Autre",$E$4:$E27,"<>"))
H28: =IF($E28="Papa",COUNTIF($E$4:$E28,"Papa"),"") | I28: =IF(OR($E28="",$E28="Papa",$E28="Autre"),"",COUNTIFS($E$4:$E28,"<>Papa",$E$4:$E28,"<>Autre",$E$4:$E28,"<>"))
H29: =IF($E29="Papa",COUNTIF($E$4:$E29,"Papa"),"") | I29: =IF(OR($E29="",$E29="Papa",$E29="Autre"),"",COUNTIFS($E$4:$E29,"<>Papa",$E$4:$E29,"<>Autre",$E$4:$E29,"<>"))
H30: =IF($E30="Papa",COUNTIF($E$4:$E30,"Papa"),"") | I30: =IF(OR($E30="",$E30="Papa",$E30="Autre"),"",COUNTIFS($E$4:$E30,"<>Papa",$E$4:$E30,"<>Autre",$E$4:$E30,"<>"))
H31: =IF($E31="Papa",COUNTIF($E$4:$E31,"Papa"),"") | I31: =IF(OR($E31="",$E31="Papa",$E31="Autre"),"",COUNTIFS($E$4:$E31,"<>Papa",$E$4:$E31,"<>Autre",$E$4:$E31,"<>"))
H32: =IF($E32="Papa",COUNTIF($E$4:$E32,"Papa"),"") | I32: =IF(OR($E32="",$E32="Papa",$E32="Autre"),"",COUNTIFS($E$4:$E32,"<>Papa",$E$4:$E32,"<>Autre",$E$4:$E32,"<>"))
H33: =IF($E33="Papa",COUNTIF($E$4:$E33,"Papa"),"") | I33: =IF(OR($E33="",$E33="Papa",$E33="Autre"),"",COUNTIFS($E$4:$E33,"<>Papa",$E$4:$E33,"<>Autre",$E$4:$E33,"<>"))
H34: =IF($E34="Papa",COUNTIF($E$4:$E34,"Papa"),"") | I34: =IF(OR($E34="",$E34="Papa",$E34="Autre"),"",COUNTIFS($E$4:$E34,"<>Papa",$E$4:$E34,"<>Autre",$E$4:$E34,"<>"))
H35: =IF($E35="Papa",COUNTIF($E$4:$E35,"Papa"),"") | I35: =IF(OR($E35="",$E35="Papa",$E35="Autre"),"",COUNTIFS($E$4:$E35,"<>Papa",$E$4:$E35,"<>Autre",$E$4:$E35,"<>"))
H36: =IF($E36="Papa",COUNTIF($E$4:$E36,"Papa"),"") | I36: =IF(OR($E36="",$E36="Papa",$E36="Autre"),"",COUNTIFS($E$4:$E36,"<>Papa",$E$4:$E36,"<>Autre",$E$4:$E36,"<>"))
H37: =IF($E37="Papa",COUNTIF($E$4:$E37,"Papa"),"") | I37: =IF(OR($E37="",$E37="Papa",$E37="Autre"),"",COUNTIFS($E$4:$E37,"<>Papa",$E$4:$E37,"<>Autre",$E$4:$E37,"<>"))
H38: =IF($E38="Papa",COUNTIF($E$4:$E38,"Papa"),"") | I38: =IF(OR($E38="",$E38="Papa",$E38="Autre"),"",COUNTIFS($E$4:$E38,"<>Papa",$E$4:$E38,"<>Autre",$E$4:$E38,"<>"))
H39: =IF($E39="Papa",COUNTIF($E$4:$E39,"Papa"),"") | I39: =IF(OR($E39="",$E39="Papa",$E39="Autre"),"",COUNTIFS($E$4:$E39,"<>Papa",$E$4:$E39,"<>Autre",$E$4:$E39,"<>"))
H40: =IF($E40="Papa",COUNTIF($E$4:$E40,"Papa"),"") | I40: =IF(OR($E40="",$E40="Papa",$E40="Autre"),"",COUNTIFS($E$4:$E40,"<>Papa",$E$4:$E40,"<>Autre",$E$4:$E40,"<>"))

Sheet Récap
A1: 📊 Récap
A3: Onglet | B3: Nb idées | C3: Nb achetés | D3: Nb offerts
A4: Maman-Frère-Copine & famille | B4: =COUNTIF('Maman-Frère-Copine & famille'!B4:B59,"?*")-COUNTIF('Maman-Frère-Copine & famille'!B34,"?*") | C4: =COUNTIF('Maman-Frère-Copine & famille'!D4:D59,"🛒 Acheté")+COUNTIF('Maman-Frère-Copine & famille'!D4:D59,"🎁 Emballé") | D4: =COUNTIF('Maman-Frère-Copine & famille'!D4:D59,"✅ Offert")
A5: Papa | B5: =COUNTIF('Papa'!B4:B59,"?*")-COUNTIF('Papa'!B34,"?*") | C5: =COUNTIF('Papa'!D4:D59,"🛒 Acheté")+COUNTIF('Papa'!D4:D59,"🎁 Emballé") | D5: =COUNTIF('Papa'!D4:D59,"✅ Offert")
A6: TOTAL | B6: =SUM(B4:B5) | C6: =SUM(C4:C5) | D6: =SUM(D4:D5)

Sheet Si je gagne - Début
A1: 🎰 Si je gagne – les premiers pas (hypothétique)
A2: Informations générales, pas un conseil. Chiffres et règles à revérifier avec un notaire / conseiller indépendant.
A3: Étape | B3: À faire | C3: Quand | D3: Fait ?
A4: 1. Ticket | B4: Signer le ticket, en faire des photos, le ranger en lieu sûr | C4: Jour J
A5: 2. Discrétion | B5: Ne rien dire à personne (ni réseaux sociaux) tant que rien n'est décidé | C5: Jour J
A6: 3. Décider le nom | B6: Voir le tableau « Ticket : à ton nom ou aux deux ? » plus bas, idéalement AVANT de signer | C6: Jour J
A7: 4. FDJ | B7: Contacter la FDJ pour la réclamation et l'accompagnement des gros gagnants | C7: Jours 1-3
A8: 5. Équipe | B8: Choisir un notaire, un conseiller en gestion de patrimoine indépendant (honoraires), un expert-comptable | C8: Semaine 1
A9: 6. Banque | B9: Verser sur un compte, répartir sur plusieurs banques (dépôts garantis à 100 000 € par banque) | C9: Semaine 1-2
A10: 7. Pause | B10: Ne rien dépenser de gros pendant 1 à 3 mois | C10: Mois 1-3
A11: 8. Budget plaisir | B11: Fixer une enveloppe cadeaux / achats plaisir (voir onglet Placements) | C11: Mois 1
A12: 9. Famille | B12: Définir qui reçoit quoi, puis faire des dons encadrés par le notaire | C12: Mois 1-3
A13: 10. Protection | B13: Faire le point sur PACS / mariage, testament, assurance-vie avec bénéficiaire | C13: Mois 1-3
A14: 11. Placements | B14: Investir progressivement selon l'onglet Placements | C14: Mois 3+
A16: Ticket : à ton nom ou aux deux ?
A17: Option | B17: Avantages | C17: Risques / limites | D17: À vérifier
A18: À ton nom seul | B18: Le gain est à toi. Tu gardes la main et tu choisis ensuite à qui donner, de façon encadrée. | C18: Ta copine n'est pas héritière sans mariage ni testament. Des dons à une personne non mariée ou non pacsée sont taxés lourdement. | D18: Droits de donation / succession entre non-mariés
A19: Aux deux noms (copine) | B19: Le gain est partagé dès le départ. | C19: Co-propriété : en cas de séparation, c'est compliqué. Aussi une donation indirecte possible. Ça ne règle pas la transmission. | D19: Notaire AVANT de signer
A20: À ton nom + PACS ou mariage | B20: Le conjoint ou partenaire pacsé est exonéré de droits de succession. Le mariage protège davantage. | C20: Engagement juridique, régime matrimonial à choisir. | D20: Contrat de mariage, testament
A21: À ton nom + assurance-vie | B21: Tu désignes qui reçoit, hors succession classique, avec un abattement par bénéficiaire (152 500 € dans le cas général, à vérifier). | C21: Clause bénéficiaire à rédiger précisément. Fiscalité selon l'âge des versements. | D21: Clause bénéficiaire avec le notaire

Sheet Si je gagne - Placements
A1: 💶 Si je gagne – répartition et placements (hypothétique)
A3: Montant gagné (€) | B3: 79000000
A4: Mets les % dans la colonne C. Les montants se calculent seuls.
A6: Poste | B6: Quoi | C6: % du gain | D6: Montant (€) | E6: Plafond / limite | F6: Fiscalité (à vérifier) | G6: Remarques
A7: Sécurité – comptes | B7: Plusieurs banques, livrets | C7: 0.1 | D7: =$B$3*C7 | E7: Garantie 100 000 € par banque. Livret A 22 950 €, LDDS 12 000 € | F7: Intérêts du Livret A et LDDS exonérés d'impôt | G7: Réserve de précaution, disponible tout de suite
A8: Assurance-vie | B8: Fonds euros + unités de compte | C8: 0.25 | D8: =$B$3*C8 | E8: Pas de plafond. Plusieurs contrats possibles | F8: Gains imposés après 8 ans avec abattement 4 600 € (9 200 € couple), puis 7,5 % ou 12,8 % + prélèvements sociaux (~17,2 %, taux à vérifier) | G8: Bon pour la transmission (abattement par bénéficiaire). Répartir les risques
A9: PEA (actions) | B9: Actions européennes, ETF | C9: 0.05 | D9: =$B$3*C9 | E9: Plafond de versements 150 000 € | F9: Après 5 ans, plus d'impôt sur les gains (prélèvements sociaux restent) | G9: Placement long terme, risque de perte
A10: Compte-titres | B10: Actions, ETF, obligations | C10: 0.15 | D10: =$B$3*C10 | E10: Pas de plafond | F10: Flat tax 30 % (12,8 % + 17,2 %), taux à vérifier | G10: Souple, mais plus taxé
A11: Contrat de capitalisation | B11: Support proche de l'assurance-vie | C11: 0.1 | D11: =$B$3*C11 | E11: Pas de plafond | F11: Fiscalité proche de l'assurance-vie | G11: Utile pour donner / transmettre
A12: Immobilier | B12: Résidence principale, locatif | C12: 0.2 | D12: =$B$3*C12 | E12: IFI au-delà de 1,3 M € de patrimoine immobilier net | F12: Revenus fonciers imposés. Résidence principale exonérée de plus-value à la revente | G12: Demande un notaire, évite l'endettement
A13: Famille – dons | B13: Parents, frère, copine et sa famille | C13: 0.08 | D13: =$B$3*C13 | E13: Abattement parent-enfant 100 000 € tous les 15 ans. Don d'argent exonéré 31 865 € (donateur < 80 ans, bénéficiaire majeur : enfants, petits-enfants, neveux/nièces, PAS les parents). Frère/sœur 15 932 € | F13: Au-delà : droits de donation selon le lien de parenté | G13: Dons encadrés par le notaire, répartis dans le temps
A14: Plaisir | B14: Voyages, montres, PS5, etc. | C14: 0.05 | D14: =$B$3*C14 | E14: – | F14: Pas d'impôt sur la dépense | G14: Fixe-le à l'avance pour ne pas déraper
A15: Associations / dons | B15: Dons à des causes qui comptent | C15: 0.01 | D15: =$B$3*C15 | E15: Plafond 20 % du revenu imposable | F15: Réduction d'impôt de 66 % (cas général) | G15: Optionnel
A16: Imprévus / à décider | B16: Réserve pour décider plus tard | C16: 0.01 | D16: =$B$3*C16 | E16: – | F16: – | G16: Garde une marge
A17: TOTAL | C17: =SUM(C7:C16) | D17: =SUM(D7:D16) | E17: =IF(ROUND(C17,4)=1,"✅ 100 %","⚠️ Le total doit faire 100 %")
A19: Aide pour payer moins d'impôt légalement : enveloppes avantageuses (assurance-vie, PEA, capitalisation), dons échelonnés, bon notaire. Pas d'optimisation agressive.
