Workbook

Sheet 1 Bon de livraison
C1: BON DE LIVRAISON · DELIVERY TICKET
C2: ="N° "&A6
A4: ENEDRIL SAS · 3 Avenue des Lacs · 64140 Lons (France) · +33 (0)5 59 04 50 45 · SIRET 79464246200020 · TVA FR11794642462
A5: N° DU BL · DELIVERY TICKET N° | C5: DATE | D5: N° DE DOSSIER (DEVIS) · JOB NUMBER
A6: BL-26-0123 | C6: 46335 | D6: 26-82-FR
A7: CLIENT · CUSTOMER | C7: PUITS / CHANTIER · WELL | D7: PO CLIENT · PURCHASE ORDER
A8: Geopetrol | C8: Puits Lacq-12 · CLU108 | D8: PO-4500123
A9: TRANSPORTEUR · TRANSPORT COMPANY | C9: PO TRANSPORT · TRANSPORT PO N° | D9: DÉLAI · EXPECTED TIME OF ARRIVAL (ETA)
A10: Transports Durand | C10: TPO-778 | D10: 48 h après chargement
A11: ADRESSE DE CHARGEMENT · LOADING ADDRESS | D11: ADRESSE DE LIVRAISON · DELIVERY ADDRESS
A12: Enedril · 3 Avenue des Lacs · 64140 Lons (France) | D12: Geopetrol · Base de Lacq · 64170 Lacq
A13: =IF(SUBTOTAL(103,C15:C54)<SUM(I15:I54),"⚠ Appuyer sur Ctrl + Alt + L pour afficher toutes les lignes du BL.","") | M13: Infos catalogue (non imprimées)
A14: N° Item | B14: N° de série Serial number | C14: Description | D14: Qté Qty | E14: Origine Origin | F14: Poids net kg / unité | G14: Valeur de remplacement € / unité | I14: actif | M14: Réf catalogue | N14: Code SH | O14: OD | P14: Lg
A15: =IF(OR(J15=0,K15=1),"",COUNTIF(K$15:K15,0)-COUNTIF(J$15:J15,0)) | C15: =IF(J15=0,"",IF(K15=1,UPPER(INDEX('2 Import devis'!$B$6:$B$29,J15)),IF(L15>0,TRIM(SUBSTITUTE(INDEX('3 Catalogue outils'!$A$6:$AC$5005,L15,2),CHAR(10)," ")),INDEX('2 Import devis'!$B$6:$B$29,J15)))) | D15: =IF(OR(J15=0,K15=1),"",1) | E15: =IF(OR(J15=0,K15=1),"",IF(L15>0,IF(N(INDEX('3 Catalogue outils'!$A$6:$AC$5005,L15,22))=0,IF(ISTEXT(INDEX('3 Catalogue outils'!$A$6:$AC$5005,L15,22)),INDEX('3 Catalogue outils'!$A$6:$AC$5005,L15,22),"FR"),"FR"),"FR")) | F15: =IF(L15>0,IF(N(INDEX('3 Catalogue outils'!$A$6:$AC$5005,L15,3))=0,"",ROUND(INDEX('3 Catalogue outils'!$A$6:$AC$5005,L15,3),1)),"") | G15: =IF(OR(D15="",INDEX('2 Import devis'!$G$6:$G$29,J15)=""),"",INDEX('2 Import devis'!$G$6:$G$29,J15)) | I15: =IF(J15=0,0,1) | J15: =IF(1>MAX('2 Import devis'!$L$6:$L$29),0,COUNTIF('2 Import devis'!$L$6:$L$29,"<"&1)+1) | K15: =IF(J15=0,0,IF(N(INDEX('2 Import devis'!$C$6:$C$29,J15))=0,1,0)) | L15: =IF(OR(J15=0,K15=1,B15=""),0,IFERROR(MATCH(B15,'3 Catalogue outils'!$A$6:$A$5005,0),0)) | M15: =IF(L15>0,IF(INDEX('3 Catalogue outils'!$A$6:$AC$5005,L15,20)=0,"",INDEX('3 Catalogue outils'!$A$6:$AC$5005,L15,20)),"") | N15: =IF(L15>0,IF(INDEX('3 Catalogue outils'!$A$6:$AC$5005,L15,23)=0,"",INDEX('3 Catalogue outils'!$A$6:$AC$5005,L15,23)),"") | O15: =IF(L15>0,IF(INDEX('3 Catalogue outils'!$A$6:$AC$5005,L15,4)=0,"",INDEX('3 Catalogue outils'!$A$6:$AC$5005,L15,4)),"") | P15: =IF(L15>0,IF(INDEX('3 Catalogue outils'!$A$6:$AC$5005,L15,5)=0,"",INDEX('3 Catalogue outils'!$A$6:$AC$5005,L15,5)),"")
A16: =IF(OR(J16=0,K16=1),"",COUNTIF(K$15:K16,0)-COUNTIF(J$15:J16,0)) | B16: 8020008 | C16: =IF(J16=0,"",IF(K16=1,UPPER(INDEX('2 Import devis'!$B$6:$B$29,J16)),IF(L16>0,TRIM(SUBSTITUTE(INDEX('3 Catalogue outils'!$A$6:$AC$5005,L16,2),CHAR(10)," ")),INDEX('2 Import devis'!$B$6:$B$29,J16)))) | D16: =IF(OR(J16=0,K16=1),"",1) | E16: =IF(OR(J16=0,K16=1),"",IF(L16>0,IF(N(INDEX('3 Catalogue outils'!$A$6:$AC$5005,L16,22))=0,IF(ISTEXT(INDEX('3 Catalogue outils'!$A$6:$AC$5005,L16,22)),INDEX('3 Catalogue outils'!$A$6:$AC$5005,L16,22),"FR"),"FR"),"FR")) | F16: =IF(L16>0,IF(N(INDEX('3 Catalogue outils'!$A$6:$AC$5005,L16,3))=0,"",ROUND(INDEX('3 Catalogue outils'!$A$6:$AC$5005,L16,3),1)),"") | G16: =IF(OR(D16="",INDEX('2 Import devis'!$G$6:$G$29,J16)=""),"",INDEX('2 Import devis'!$G$6:$G$29,J16)) | I16: =IF(J16=0,0,1) | J16: =IF(2>MAX('2 Import devis'!$L$6:$L$29),0,COUNTIF('2 Import devis'!$L$6:$L$29,"<"&2)+1) | K16: =IF(J16=0,0,IF(N(INDEX('2 Import devis'!$C$6:$C$29,J16))=0,1,0)) | L16: =IF(OR(J16=0,K16=1,B16=""),0,IFERROR(MATCH(B16,'3 Catalogue outils'!$A$6:$A$5005,0),0)) | M16: =IF(L16>0,IF(INDEX('3 Catalogue outils'!$A$6:$AC$5005,L16,20)=0,"",INDEX('3 Catalogue outils'!$A$6:$AC$5005,L16,20)),"") | N16: =IF(L16>0,IF(INDEX('3 Catalogue outils'!$A$6:$AC$5005,L16,23)=0,"",INDEX('3 Catalogue outils'!$A$6:$AC$5005,L16,23)),"") | O16: =IF(L16>0,IF(INDEX('3 Catalogue outils'!$A$6:$AC$5005,L16,4)=0,"",INDEX('3 Catalogue outils'!$A$6:$AC$5005,L16,4)),"") | P16: =IF(L16>0,IF(INDEX('3 Catalogue outils'!$A$6:$AC$5005,L16,5)=0,"",INDEX('3 Catalogue outils'!$A$6:$AC$5005,L16,5)),"")
A17: =IF(OR(J17=0,K17=1),"",COUNTIF(K$15:K17,0)-COUNTIF(J$15:J17,0)) | B17: 7050712 | C17: =IF(J17=0,"",IF(K17=1,UPPER(INDEX('2 Import devis'!$B$6:$B$29,J17)),IF(L17>0,TRIM(SUBSTITUTE(INDEX('3 Catalogue outils'!$A$6:$AC$5005,L17,2),CHAR(10)," ")),INDEX('2 Import devis'!$B$6:$B$29,J17)))) | D17: =IF(OR(J17=0,K17=1),"",1) | E17: =IF(OR(J17=0,K17=1),"",IF(L17>0,IF(N(INDEX('3 Catalogue outils'!$A$6:$AC$5005,L17,22))=0,IF(ISTEXT(INDEX('3 Catalogue outils'!$A$6:$AC$5005,L17,22)),INDEX('3 Catalogue outils'!$A$6:$AC$5005,L17,22),"FR"),"FR"),"FR")) | F17: =IF(L17>0,IF(N(INDEX('3 Catalogue outils'!$A$6:$AC$5005,L17,3))=0,"",ROUND(INDEX('3 Catalogue outils'!$A$6:$AC$5005,L17,3),1)),"") | G17: =IF(OR(D17="",INDEX('2 Import devis'!$G$6:$G$29,J17)=""),"",INDEX('2 Import devis'!$G$6:$G$29,J17)) | I17: =IF(J17=0,0,1) | J17: =IF(3>MAX('2 Import devis'!$L$6:$L$29),0,COUNTIF('2 Import devis'!$L$6:$L$29,"<"&3)+1) | K17: =IF(J17=0,0,IF(N(INDEX('2 Import devis'!$C$6:$C$29,J17))=0,1,0)) | L17: =IF(OR(J17=0,K17=1,B17=""),0,IFERROR(MATCH(B17,'3 Catalogue outils'!$A$6:$A$5005,0),0)) | M17: =IF(L17>0,IF(INDEX('3 Catalogue outils'!$A$6:$AC$5005,L17,20)=0,"",INDEX('3 Catalogue outils'!$A$6:$AC$5005,L17,20)),"") | N17: =IF(L17>0,IF(INDEX('3 Catalogue outils'!$A$6:$AC$5005,L17,23)=0,"",INDEX('3 Catalogue outils'!$A$6:$AC$5005,L17,23)),"") | O17: =IF(L17>0,IF(INDEX('3 Catalogue outils'!$A$6:$AC$5005,L17,4)=0,"",INDEX('3 Catalogue outils'!$A$6:$AC$5005,L17,4)),"") | P17: =IF(L17>0,IF(INDEX('3 Catalogue outils'!$A$6:$AC$5005,L17,5)=0,"",INDEX('3 Catalogue outils'!$A$6:$AC$5005,L17,5)),"")
A18: =IF(OR(J18=0,K18=1),"",COUNTIF(K$15:K18,0)-COUNTIF(J$15:J18,0)) | B18: 7050715 | C18: =IF(J18=0,"",IF(K18=1,UPPER(INDEX('2 Import devis'!$B$6:$B$29,J18)),IF(L18>0,TRIM(SUBSTITUTE(INDEX('3 Catalogue outils'!$A$6:$AC$5005,L18,2),CHAR(10)," ")),INDEX('2 Import devis'!$B$6:$B$29,J18)))) | D18: =IF(OR(J18=0,K18=1),"",1) | E18: =IF(OR(J18=0,K18=1),"",IF(L18>0,IF(N(INDEX('3 Catalogue outils'!$A$6:$AC$5005,L18,22))=0,IF(ISTEXT(INDEX('3 Catalogue outils'!$A$6:$AC$5005,L18,22)),INDEX('3 Catalogue outils'!$A$6:$AC$5005,L18,22),"FR"),"FR"),"FR")) | F18: =IF(L18>0,IF(N(INDEX('3 Catalogue outils'!$A$6:$AC$5005,L18,3))=0,"",ROUND(INDEX('3 Catalogue outils'!$A$6:$AC$5005,L18,3),1)),"") | G18: =IF(OR(D18="",INDEX('2 Import devis'!$G$6:$G$29,J18)=""),"",INDEX('2 Import devis'!$G$6:$G$29,J18)) | I18: =IF(J18=0,0,1) | J18: =IF(4>MAX('2 Import devis'!$L$6:$L$29),0,COUNTIF('2 Import devis'!$L$6:$L$29,"<"&4)+1) | K18: =IF(J18=0,0,IF(N(INDEX('2 Import devis'!$C$6:$C$29,J18))=0,1,0)) | L18: =IF(OR(J18=0,K18=1,B18=""),0,IFERROR(MATCH(B18,'3 Catalogue outils'!$A$6:$A$5005,0),0)) | M18: =IF(L18>0,IF(INDEX('3 Catalogue outils'!$A$6:$AC$5005,L18,20)=0,"",INDEX('3 Catalogue outils'!$A$6:$AC$5005,L18,20)),"") | N18: =IF(L18>0,IF(INDEX('3 Catalogue outils'!$A$6:$AC$5005,L18,23)=0,"",INDEX('3 Catalogue outils'!$A$6:$AC$5005,L18,23)),"") | O18: =IF(L18>0,IF(INDEX('3 Catalogue outils'!$A$6:$AC$5005,L18,4)=0,"",INDEX('3 Catalogue outils'!$A$6:$AC$5005,L18,4)),"") | P18: =IF(L18>0,IF(INDEX('3 Catalogue outils'!$A$6:$AC$5005,L18,5)=0,"",INDEX('3 Catalogue outils'!$A$6:$AC$5005,L18,5)),"")
A19: =IF(OR(J19=0,K19=1),"",COUNTIF(K$15:K19,0)-COUNTIF(J$15:J19,0)) | B19: 7050715 | C19: =IF(J19=0,"",IF(K19=1,UPPER(INDEX('2 Import devis'!$B$6:$B$29,J19)),IF(L19>0,TRIM(SUBSTITUTE(INDEX('3 Catalogue outils'!$A$6:$AC$5005,L19,2),CHAR(10)," ")),INDEX('2 Import devis'!$B$6:$B$29,J19)))) | D19: =IF(OR(J19=0,K19=1),"",1) | E19: =IF(OR(J19=0,K19=1),"",IF(L19>0,IF(N(INDEX('3 Catalogue outils'!$A$6:$AC$5005,L19,22))=0,IF(ISTEXT(INDEX('3 Catalogue outils'!$A$6:$AC$5005,L19,22)),INDEX('3 Catalogue outils'!$A$6:$AC$5005,L19,22),"FR"),"FR"),"FR")) | F19: =IF(L19>0,IF(N(INDEX('3 Catalogue outils'!$A$6:$AC$5005,L19,3))=0,"",ROUND(INDEX('3 Catalogue outils'!$A$6:$AC$5005,L19,3),1)),"") | G19: =IF(OR(D19="",INDEX('2 Import devis'!$G$6:$G$29,J19)=""),"",INDEX('2 Import devis'!$G$6:$G$29,J19)) | I19: =IF(J19=0,0,1) | J19: =IF(5>MAX('2 Import devis'!$L$6:$L$29),0,COUNTIF('2 Import devis'!$L$6:$L$29,"<"&5)+1) | K19: =IF(J19=0,0,IF(N(INDEX('2 Import devis'!$C$6:$C$29,J19))=0,1,0)) | L19: =IF(OR(J19=0,K19=1,B19=""),0,IFERROR(MATCH(B19,'3 Catalogue outils'!$A$6:$A$5005,0),0)) | M19: =IF(L19>0,IF(INDEX('3 Catalogue outils'!$A$6:$AC$5005,L19,20)=0,"",INDEX('3 Catalogue outils'!$A$6:$AC$5005,L19,20)),"") | N19: =IF(L19>0,IF(INDEX('3 Catalogue outils'!$A$6:$AC$5005,L19,23)=0,"",INDEX('3 Catalogue outils'!$A$6:$AC$5005,L19,23)),"") | O19: =IF(L19>0,IF(INDEX('3 Catalogue outils'!$A$6:$AC$5005,L19,4)=0,"",INDEX('3 Catalogue outils'!$A$6:$AC$5005,L19,4)),"") | P19: =IF(L19>0,IF(INDEX('3 Catalogue outils'!$A$6:$AC$5005,L19,5)=0,"",INDEX('3 Catalogue outils'!$A$6:$AC$5005,L19,5)),"")
A20: =IF(OR(J20=0,K20=1),"",COUNTIF(K$15:K20,0)-COUNTIF(J$15:J20,0)) | C20: =IF(J20=0,"",IF(K20=1,UPPER(INDEX('2 Import devis'!$B$6:$B$29,J20)),IF(L20>0,TRIM(SUBSTITUTE(INDEX('3 Catalogue outils'!$A$6:$AC$5005,L20,2),CHAR(10)," ")),INDEX('2 Import devis'!$B$6:$B$29,J20)))) | D20: =IF(OR(J20=0,K20=1),"",1) | E20: =IF(OR(J20=0,K20=1),"",IF(L20>0,IF(N(INDEX('3 Catalogue outils'!$A$6:$AC$5005,L20,22))=0,IF(ISTEXT(INDEX('3 Catalogue outils'!$A$6:$AC$5005,L20,22)),INDEX('3 Catalogue outils'!$A$6:$AC$5005,L20,22),"FR"),"FR"),"FR")) | F20: =IF(L20>0,IF(N(INDEX('3 Catalogue outils'!$A$6:$AC$5005,L20,3))=0,"",ROUND(INDEX('3 Catalogue outils'!$A$6:$AC$5005,L20,3),1)),"") | G20: =IF(OR(D20="",INDEX('2 Import devis'!$G$6:$G$29,J20)=""),"",INDEX('2 Import devis'!$G$6:$G$29,J20)) | I20: =IF(J20=0,0,1) | J20: =IF(6>MAX('2 Import devis'!$L$6:$L$29),0,COUNTIF('2 Import devis'!$L$6:$L$29,"<"&6)+1) | K20: =IF(J20=0,0,IF(N(INDEX('2 Import devis'!$C$6:$C$29,J20))=0,1,0)) | L20: =IF(OR(J20=0,K20=1,B20=""),0,IFERROR(MATCH(B20,'3 Catalogue outils'!$A$6:$A$5005,0),0)) | M20: =IF(L20>0,IF(INDEX('3 Catalogue outils'!$A$6:$AC$5005,L20,20)=0,"",INDEX('3 Catalogue outils'!$A$6:$AC$5005,L20,20)),"") | N20: =IF(L20>0,IF(INDEX('3 Catalogue outils'!$A$6:$AC$5005,L20,23)=0,"",INDEX('3 Catalogue outils'!$A$6:$AC$5005,L20,23)),"") | O20: =IF(L20>0,IF(INDEX('3 Catalogue outils'!$A$6:$AC$5005,L20,4)=0,"",INDEX('3 Catalogue outils'!$A$6:$AC$5005,L20,4)),"") | P20: =IF(L20>0,IF(INDEX('3 Catalogue outils'!$A$6:$AC$5005,L20,5)=0,"",INDEX('3 Catalogue outils'!$A$6:$AC$5005,L20,5)),"")
A21: =IF(OR(J21=0,K21=1),"",COUNTIF(K$15:K21,0)-COUNTIF(J$15:J21,0)) | C21: =IF(J21=0,"",IF(K21=1,UPPER(INDEX('2 Import devis'!$B$6:$B$29,J21)),IF(L21>0,TRIM(SUBSTITUTE(INDEX('3 Catalogue outils'!$A$6:$AC$5005,L21,2),CHAR(10)," ")),INDEX('2 Import devis'!$B$6:$B$29,J21)))) | D21: =IF(OR(J21=0,K21=1),"",1) | E21: =IF(OR(J21=0,K21=1),"",IF(L21>0,IF(N(INDEX('3 Catalogue outils'!$A$6:$AC$5005,L21,22))=0,IF(ISTEXT(INDEX('3 Catalogue outils'!$A$6:$AC$5005,L21,22)),INDEX('3 Catalogue outils'!$A$6:$AC$5005,L21,22),"FR"),"FR"),"FR")) | F21: =IF(L21>0,IF(N(INDEX('3 Catalogue outils'!$A$6:$AC$5005,L21,3))=0,"",ROUND(INDEX('3 Catalogue outils'!$A$6:$AC$5005,L21,3),1)),"") | G21: =IF(OR(D21="",INDEX('2 Import devis'!$G$6:$G$29,J21)=""),"",INDEX('2 Import devis'!$G$6:$G$29,J21)) | I21: =IF(J21=0,0,1) | J21: =IF(7>MAX('2 Import devis'!$L$6:$L$29),0,COUNTIF('2 Import devis'!$L$6:$L$29,"<"&7)+1) | K21: =IF(J21=0,0,IF(N(INDEX('2 Import devis'!$C$6:$C$29,J21))=0,1,0)) | L21: =IF(OR(J21=0,K21=1,B21=""),0,IFERROR(MATCH(B21,'3 Catalogue outils'!$A$6:$A$5005,0),0)) | M21: =IF(L21>0,IF(INDEX('3 Catalogue outils'!$A$6:$AC$5005,L21,20)=0,"",INDEX('3 Catalogue outils'!$A$6:$AC$5005,L21,20)),"") | N21: =IF(L21>0,IF(INDEX('3 Catalogue outils'!$A$6:$AC$5005,L21,23)=0,"",INDEX('3 Catalogue outils'!$A$6:$AC$5005,L21,23)),"") | O21: =IF(L21>0,IF(INDEX('3 Catalogue outils'!$A$6:$AC$5005,L21,4)=0,"",INDEX('3 Catalogue outils'!$A$6:$AC$5005,L21,4)),"") | P21: =IF(L21>0,IF(INDEX('3 Catalogue outils'!$A$6:$AC$5005,L21,5)=0,"",INDEX('3 Catalogue outils'!$A$6:$AC$5005,L21,5)),"")
A22: =IF(OR(J22=0,K22=1),"",COUNTIF(K$15:K22,0)-COUNTIF(J$15:J22,0)) | C22: =IF(J22=0,"",IF(K22=1,UPPER(INDEX('2 Import devis'!$B$6:$B$29,J22)),IF(L22>0,TRIM(SUBSTITUTE(INDEX('3 Catalogue outils'!$A$6:$AC$5005,L22,2),CHAR(10)," ")),INDEX('2 Import devis'!$B$6:$B$29,J22)))) | D22: =IF(OR(J22=0,K22=1),"",1) | E22: =IF(OR(J22=0,K22=1),"",IF(L22>0,IF(N(INDEX('3 Catalogue outils'!$A$6:$AC$5005,L22,22))=0,IF(ISTEXT(INDEX('3 Catalogue outils'!$A$6:$AC$5005,L22,22)),INDEX('3 Catalogue outils'!$A$6:$AC$5005,L22,22),"FR"),"FR"),"FR")) | F22: =IF(L22>0,IF(N(INDEX('3 Catalogue outils'!$A$6:$AC$5005,L22,3))=0,"",ROUND(INDEX('3 Catalogue outils'!$A$6:$AC$5005,L22,3),1)),"") | G22: =IF(OR(D22="",INDEX('2 Import devis'!$G$6:$G$29,J22)=""),"",INDEX('2 Import devis'!$G$6:$G$29,J22)) | I22: =IF(J22=0,0,1) | J22: =IF(8>MAX('2 Import devis'!$L$6:$L$29),0,COUNTIF('2 Import devis'!$L$6:$L$29,"<"&8)+1) | K22: =IF(J22=0,0,IF(N(INDEX('2 Import devis'!$C$6:$C$29,J22))=0,1,0)) | L22: =IF(OR(J22=0,K22=1,B22=""),0,IFERROR(MATCH(B22,'3 Catalogue outils'!$A$6:$A$5005,0),0)) | M22: =IF(L22>0,IF(INDEX('3 Catalogue outils'!$A$6:$AC$5005,L22,20)=0,"",INDEX('3 Catalogue outils'!$A$6:$AC$5005,L22,20)),"") | N22: =IF(L22>0,IF(INDEX('3 Catalogue outils'!$A$6:$AC$5005,L22,23)=0,"",INDEX('3 Catalogue outils'!$A$6:$AC$5005,L22,23)),"") | O22: =IF(L22>0,IF(INDEX('3 Catalogue outils'!$A$6:$AC$5005,L22,4)=0,"",INDEX('3 Catalogue outils'!$A$6:$AC$5005,L22,4)),"") | P22: =IF(L22>0,IF(INDEX('3 Catalogue outils'!$A$6:$AC$5005,L22,5)=0,"",INDEX('3 Catalogue outils'!$A$6:$AC$5005,L22,5)),"")
A23: =IF(OR(J23=0,K23=1),"",COUNTIF(K$15:K23,0)-COUNTIF(J$15:J23,0)) | C23: =IF(J23=0,"",IF(K23=1,UPPER(INDEX('2 Import devis'!$B$6:$B$29,J23)),IF(L23>0,TRIM(SUBSTITUTE(INDEX('3 Catalogue outils'!$A$6:$AC$5005,L23,2),CHAR(10)," ")),INDEX('2 Import devis'!$B$6:$B$29,J23)))) | D23: =IF(OR(J23=0,K23=1),"",1) | E23: =IF(OR(J23=0,K23=1),"",IF(L23>0,IF(N(INDEX('3 Catalogue outils'!$A$6:$AC$5005,L23,22))=0,IF(ISTEXT(INDEX('3 Catalogue outils'!$A$6:$AC$5005,L23,22)),INDEX('3 Catalogue outils'!$A$6:$AC$5005,L23,22),"FR"),"FR"),"FR")) | F23: =IF(L23>0,IF(N(INDEX('3 Catalogue outils'!$A$6:$AC$5005,L23,3))=0,"",ROUND(INDEX('3 Catalogue outils'!$A$6:$AC$5005,L23,3),1)),"") | G23: =IF(OR(D23="",INDEX('2 Import devis'!$G$6:$G$29,J23)=""),"",INDEX('2 Import devis'!$G$6:$G$29,J23)) | I23: =IF(J23=0,0,1) | J23: =IF(9>MAX('2 Import devis'!$L$6:$L$29),0,COUNTIF('2 Import devis'!$L$6:$L$29,"<"&9)+1) | K23: =IF(J23=0,0,IF(N(INDEX('2 Import devis'!$C$6:$C$29,J23))=0,1,0)) | L23: =IF(OR(J23=0,K23=1,B23=""),0,IFERROR(MATCH(B23,'3 Catalogue outils'!$A$6:$A$5005,0),0)) | M23: =IF(L23>0,IF(INDEX('3 Catalogue outils'!$A$6:$AC$5005,L23,20)=0,"",INDEX('3 Catalogue outils'!$A$6:$AC$5005,L23,20)),"") | N23: =IF(L23>0,IF(INDEX('3 Catalogue outils'!$A$6:$AC$5005,L23,23)=0,"",INDEX('3 Catalogue outils'!$A$6:$AC$5005,L23,23)),"") | O23: =IF(L23>0,IF(INDEX('3 Catalogue outils'!$A$6:$AC$5005,L23,4)=0,"",INDEX('3 Catalogue outils'!$A$6:$AC$5005,L23,4)),"") | P23: =IF(L23>0,IF(INDEX('3 Catalogue outils'!$A$6:$AC$5005,L23,5)=0,"",INDEX('3 Catalogue outils'!$A$6:$AC$5005,L23,5)),"")
A24: =IF(OR(J24=0,K24=1),"",COUNTIF(K$15:K24,0)-COUNTIF(J$15:J24,0)) | C24: =IF(J24=0,"",IF(K24=1,UPPER(INDEX('2 Import devis'!$B$6:$B$29,J24)),IF(L24>0,TRIM(SUBSTITUTE(INDEX('3 Catalogue outils'!$A$6:$AC$5005,L24,2),CHAR(10)," ")),INDEX('2 Import devis'!$B$6:$B$29,J24)))) | D24: =IF(OR(J24=0,K24=1),"",1) | E24: =IF(OR(J24=0,K24=1),"",IF(L24>0,IF(N(INDEX('3 Catalogue outils'!$A$6:$AC$5005,L24,22))=0,IF(ISTEXT(INDEX('3 Catalogue outils'!$A$6:$AC$5005,L24,22)),INDEX('3 Catalogue outils'!$A$6:$AC$5005,L24,22),"FR"),"FR"),"FR")) | F24: =IF(L24>0,IF(N(INDEX('3 Catalogue outils'!$A$6:$AC$5005,L24,3))=0,"",ROUND(INDEX('3 Catalogue outils'!$A$6:$AC$5005,L24,3),1)),"") | G24: =IF(OR(D24="",INDEX('2 Import devis'!$G$6:$G$29,J24)=""),"",INDEX('2 Import devis'!$G$6:$G$29,J24)) | I24: =IF(J24=0,0,1) | J24: =IF(10>MAX('2 Import devis'!$L$6:$L$29),0,COUNTIF('2 Import devis'!$L$6:$L$29,"<"&10)+1) | K24: =IF(J24=0,0,IF(N(INDEX('2 Import devis'!$C$6:$C$29,J24))=0,1,0)) | L24: =IF(OR(J24=0,K24=1,B24=""),0,IFERROR(MATCH(B24,'3 Catalogue outils'!$A$6:$A$5005,0),0)) | M24: =IF(L24>0,IF(INDEX('3 Catalogue outils'!$A$6:$AC$5005,L24,20)=0,"",INDEX('3 Catalogue outils'!$A$6:$AC$5005,L24,20)),"") | N24: =IF(L24>0,IF(INDEX('3 Catalogue outils'!$A$6:$AC$5005,L24,23)=0,"",INDEX('3 Catalogue outils'!$A$6:$AC$5005,L24,23)),"") | O24: =IF(L24>0,IF(INDEX('3 Catalogue outils'!$A$6:$AC$5005,L24,4)=0,"",INDEX('3 Catalogue outils'!$A$6:$AC$5005,L24,4)),"") | P24: =IF(L24>0,IF(INDEX('3 Catalogue outils'!$A$6:$AC$5005,L24,5)=0,"",INDEX('3 Catalogue outils'!$A$6:$AC$5005,L24,5)),"")
A25: =IF(OR(J25=0,K25=1),"",COUNTIF(K$15:K25,0)-COUNTIF(J$15:J25,0)) | C25: =IF(J25=0,"",IF(K25=1,UPPER(INDEX('2 Import devis'!$B$6:$B$29,J25)),IF(L25>0,TRIM(SUBSTITUTE(INDEX('3 Catalogue outils'!$A$6:$AC$5005,L25,2),CHAR(10)," ")),INDEX('2 Import devis'!$B$6:$B$29,J25)))) | D25: =IF(OR(J25=0,K25=1),"",1) | E25: =IF(OR(J25=0,K25=1),"",IF(L25>0,IF(N(INDEX('3 Catalogue outils'!$A$6:$AC$5005,L25,22))=0,IF(ISTEXT(INDEX('3 Catalogue outils'!$A$6:$AC$5005,L25,22)),INDEX('3 Catalogue outils'!$A$6:$AC$5005,L25,22),"FR"),"FR"),"FR")) | F25: =IF(L25>0,IF(N(INDEX('3 Catalogue outils'!$A$6:$AC$5005,L25,3))=0,"",ROUND(INDEX('3 Catalogue outils'!$A$6:$AC$5005,L25,3),1)),"") | G25: =IF(OR(D25="",INDEX('2 Import devis'!$G$6:$G$29,J25)=""),"",INDEX('2 Import devis'!$G$6:$G$29,J25)) | I25: =IF(J25=0,0,1) | J25: =IF(11>MAX('2 Import devis'!$L$6:$L$29),0,COUNTIF('2 Import devis'!$L$6:$L$29,"<"&11)+1) | K25: =IF(J25=0,0,IF(N(INDEX('2 Import devis'!$C$6:$C$29,J25))=0,1,0)) | L25: =IF(OR(J25=0,K25=1,B25=""),0,IFERROR(MATCH(B25,'3 Catalogue outils'!$A$6:$A$5005,0),0)) | M25: =IF(L25>0,IF(INDEX('3 Catalogue outils'!$A$6:$AC$5005,L25,20)=0,"",INDEX('3 Catalogue outils'!$A$6:$AC$5005,L25,20)),"") | N25: =IF(L25>0,IF(INDEX('3 Catalogue outils'!$A$6:$AC$5005,L25,23)=0,"",INDEX('3 Catalogue outils'!$A$6:$AC$5005,L25,23)),"") | O25: =IF(L25>0,IF(INDEX('3 Catalogue outils'!$A$6:$AC$5005,L25,4)=0,"",INDEX('3 Catalogue outils'!$A$6:$AC$5005,L25,4)),"") | P25: =IF(L25>0,IF(INDEX('3 Catalogue outils'!$A$6:$AC$5005,L25,5)=0,"",INDEX('3 Catalogue outils'!$A$6:$AC$5005,L25,5)),"")
A26: =IF(OR(J26=0,K26=1),"",COUNTIF(K$15:K26,0)-COUNTIF(J$15:J26,0)) | C26: =IF(J26=0,"",IF(K26=1,UPPER(INDEX('2 Import devis'!$B$6:$B$29,J26)),IF(L26>0,TRIM(SUBSTITUTE(INDEX('3 Catalogue outils'!$A$6:$AC$5005,L26,2),CHAR(10)," ")),INDEX('2 Import devis'!$B$6:$B$29,J26)))) | D26: =IF(OR(J26=0,K26=1),"",1) | E26: =IF(OR(J26=0,K26=1),"",IF(L26>0,IF(N(INDEX('3 Catalogue outils'!$A$6:$AC$5005,L26,22))=0,IF(ISTEXT(INDEX('3 Catalogue outils'!$A$6:$AC$5005,L26,22)),INDEX('3 Catalogue outils'!$A$6:$AC$5005,L26,22),"FR"),"FR"),"FR")) | F26: =IF(L26>0,IF(N(INDEX('3 Catalogue outils'!$A$6:$AC$5005,L26,3))=0,"",ROUND(INDEX('3 Catalogue outils'!$A$6:$AC$5005,L26,3),1)),"") | G26: =IF(OR(D26="",INDEX('2 Import devis'!$G$6:$G$29,J26)=""),"",INDEX('2 Import devis'!$G$6:$G$29,J26)) | I26: =IF(J26=0,0,1) | J26: =IF(12>MAX('2 Import devis'!$L$6:$L$29),0,COUNTIF('2 Import devis'!$L$6:$L$29,"<"&12)+1) | K26: =IF(J26=0,0,IF(N(INDEX('2 Import devis'!$C$6:$C$29,J26))=0,1,0)) | L26: =IF(OR(J26=0,K26=1,B26=""),0,IFERROR(MATCH(B26,'3 Catalogue outils'!$A$6:$A$5005,0),0)) | M26: =IF(L26>0,IF(INDEX('3 Catalogue outils'!$A$6:$AC$5005,L26,20)=0,"",INDEX('3 Catalogue outils'!$A$6:$AC$5005,L26,20)),"") | N26: =IF(L26>0,IF(INDEX('3 Catalogue outils'!$A$6:$AC$5005,L26,23)=0,"",INDEX('3 Catalogue outils'!$A$6:$AC$5005,L26,23)),"") | O26: =IF(L26>0,IF(INDEX('3 Catalogue outils'!$A$6:$AC$5005,L26,4)=0,"",INDEX('3 Catalogue outils'!$A$6:$AC$5005,L26,4)),"") | P26: =IF(L26>0,IF(INDEX('3 Catalogue outils'!$A$6:$AC$5005,L26,5)=0,"",INDEX('3 Catalogue outils'!$A$6:$AC$5005,L26,5)),"")
A27: =IF(OR(J27=0,K27=1),"",COUNTIF(K$15:K27,0)-COUNTIF(J$15:J27,0)) | C27: =IF(J27=0,"",IF(K27=1,UPPER(INDEX('2 Import devis'!$B$6:$B$29,J27)),IF(L27>0,TRIM(SUBSTITUTE(INDEX('3 Catalogue outils'!$A$6:$AC$5005,L27,2),CHAR(10)," ")),INDEX('2 Import devis'!$B$6:$B$29,J27)))) | D27: =IF(OR(J27=0,K27=1),"",1) | E27: =IF(OR(J27=0,K27=1),"",IF(L27>0,IF(N(INDEX('3 Catalogue outils'!$A$6:$AC$5005,L27,22))=0,IF(ISTEXT(INDEX('3 Catalogue outils'!$A$6:$AC$5005,L27,22)),INDEX('3 Catalogue outils'!$A$6:$AC$5005,L27,22),"FR"),"FR"),"FR")) | F27: =IF(L27>0,IF(N(INDEX('3 Catalogue outils'!$A$6:$AC$5005,L27,3))=0,"",ROUND(INDEX('3 Catalogue outils'!$A$6:$AC$5005,L27,3),1)),"") | G27: =IF(OR(D27="",INDEX('2 Import devis'!$G$6:$G$29,J27)=""),"",INDEX('2 Import devis'!$G$6:$G$29,J27)) | I27: =IF(J27=0,0,1) | J27: =IF(13>MAX('2 Import devis'!$L$6:$L$29),0,COUNTIF('2 Import devis'!$L$6:$L$29,"<"&13)+1) | K27: =IF(J27=0,0,IF(N(INDEX('2 Import devis'!$C$6:$C$29,J27))=0,1,0)) | L27: =IF(OR(J27=0,K27=1,B27=""),0,IFERROR(MATCH(B27,'3 Catalogue outils'!$A$6:$A$5005,0),0)) | M27: =IF(L27>0,IF(INDEX('3 Catalogue outils'!$A$6:$AC$5005,L27,20)=0,"",INDEX('3 Catalogue outils'!$A$6:$AC$5005,L27,20)),"") | N27: =IF(L27>0,IF(INDEX('3 Catalogue outils'!$A$6:$AC$5005,L27,23)=0,"",INDEX('3 Catalogue outils'!$A$6:$AC$5005,L27,23)),"") | O27: =IF(L27>0,IF(INDEX('3 Catalogue outils'!$A$6:$AC$5005,L27,4)=0,"",INDEX('3 Catalogue outils'!$A$6:$AC$5005,L27,4)),"") | P27: =IF(L27>0,IF(INDEX('3 Catalogue outils'!$A$6:$AC$5005,L27,5)=0,"",INDEX('3 Catalogue outils'!$A$6:$AC$5005,L27,5)),"")
A28: =IF(OR(J28=0,K28=1),"",COUNTIF(K$15:K28,0)-COUNTIF(J$15:J28,0)) | C28: =IF(J28=0,"",IF(K28=1,UPPER(INDEX('2 Import devis'!$B$6:$B$29,J28)),IF(L28>0,TRIM(SUBSTITUTE(INDEX('3 Catalogue outils'!$A$6:$AC$5005,L28,2),CHAR(10)," ")),INDEX('2 Import devis'!$B$6:$B$29,J28)))) | D28: =IF(OR(J28=0,K28=1),"",1) | E28: =IF(OR(J28=0,K28=1),"",IF(L28>0,IF(N(INDEX('3 Catalogue outils'!$A$6:$AC$5005,L28,22))=0,IF(ISTEXT(INDEX('3 Catalogue outils'!$A$6:$AC$5005,L28,22)),INDEX('3 Catalogue outils'!$A$6:$AC$5005,L28,22),"FR"),"FR"),"FR")) | F28: =IF(L28>0,IF(N(INDEX('3 Catalogue outils'!$A$6:$AC$5005,L28,3))=0,"",ROUND(INDEX('3 Catalogue outils'!$A$6:$AC$5005,L28,3),1)),"") | G28: =IF(OR(D28="",INDEX('2 Import devis'!$G$6:$G$29,J28)=""),"",INDEX('2 Import devis'!$G$6:$G$29,J28)) | I28: =IF(J28=0,0,1) | J28: =IF(14>MAX('2 Import devis'!$L$6:$L$29),0,COUNTIF('2 Import devis'!$L$6:$L$29,"<"&14)+1) | K28: =IF(J28=0,0,IF(N(INDEX('2 Import devis'!$C$6:$C$29,J28))=0,1,0)) | L28: =IF(OR(J28=0,K28=1,B28=""),0,IFERROR(MATCH(B28,'3 Catalogue outils'!$A$6:$A$5005,0),0)) | M28: =IF(L28>0,IF(INDEX('3 Catalogue outils'!$A$6:$AC$5005,L28,20)=0,"",INDEX('3 Catalogue outils'!$A$6:$AC$5005,L28,20)),"") | N28: =IF(L28>0,IF(INDEX('3 Catalogue outils'!$A$6:$AC$5005,L28,23)=0,"",INDEX('3 Catalogue outils'!$A$6:$AC$5005,L28,23)),"") | O28: =IF(L28>0,IF(INDEX('3 Catalogue outils'!$A$6:$AC$5005,L28,4)=0,"",INDEX('3 Catalogue outils'!$A$6:$AC$5005,L28,4)),"") | P28: =IF(L28>0,IF(INDEX('3 Catalogue outils'!$A$6:$AC$5005,L28,5)=0,"",INDEX('3 Catalogue outils'!$A$6:$AC$5005,L28,5)),"")
A29: =IF(OR(J29=0,K29=1),"",COUNTIF(K$15:K29,0)-COUNTIF(J$15:J29,0)) | C29: =IF(J29=0,"",IF(K29=1,UPPER(INDEX('2 Import devis'!$B$6:$B$29,J29)),IF(L29>0,TRIM(SUBSTITUTE(INDEX('3 Catalogue outils'!$A$6:$AC$5005,L29,2),CHAR(10)," ")),INDEX('2 Import devis'!$B$6:$B$29,J29)))) | D29: =IF(OR(J29=0,K29=1),"",1) | E29: =IF(OR(J29=0,K29=1),"",IF(L29>0,IF(N(INDEX('3 Catalogue outils'!$A$6:$AC$5005,L29,22))=0,IF(ISTEXT(INDEX('3 Catalogue outils'!$A$6:$AC$5005,L29,22)),INDEX('3 Catalogue outils'!$A$6:$AC$5005,L29,22),"FR"),"FR"),"FR")) | F29: =IF(L29>0,IF(N(INDEX('3 Catalogue outils'!$A$6:$AC$5005,L29,3))=0,"",ROUND(INDEX('3 Catalogue outils'!$A$6:$AC$5005,L29,3),1)),"") | G29: =IF(OR(D29="",INDEX('2 Import devis'!$G$6:$G$29,J29)=""),"",INDEX('2 Import devis'!$G$6:$G$29,J29)) | I29: =IF(J29=0,0,1) | J29: =IF(15>MAX('2 Import devis'!$L$6:$L$29),0,COUNTIF('2 Import devis'!$L$6:$L$29,"<"&15)+1) | K29: =IF(J29=0,0,IF(N(INDEX('2 Import devis'!$C$6:$C$29,J29))=0,1,0)) | L29: =IF(OR(J29=0,K29=1,B29=""),0,IFERROR(MATCH(B29,'3 Catalogue outils'!$A$6:$A$5005,0),0)) | M29: =IF(L29>0,IF(INDEX('3 Catalogue outils'!$A$6:$AC$5005,L29,20)=0,"",INDEX('3 Catalogue outils'!$A$6:$AC$5005,L29,20)),"") | N29: =IF(L29>0,IF(INDEX('3 Catalogue outils'!$A$6:$AC$5005,L29,23)=0,"",INDEX('3 Catalogue outils'!$A$6:$AC$5005,L29,23)),"") | O29: =IF(L29>0,IF(INDEX('3 Catalogue outils'!$A$6:$AC$5005,L29,4)=0,"",INDEX('3 Catalogue outils'!$A$6:$AC$5005,L29,4)),"") | P29: =IF(L29>0,IF(INDEX('3 Catalogue outils'!$A$6:$AC$5005,L29,5)=0,"",INDEX('3 Catalogue outils'!$A$6:$AC$5005,L29,5)),"")
A30: =IF(OR(J30=0,K30=1),"",COUNTIF(K$15:K30,0)-COUNTIF(J$15:J30,0)) | C30: =IF(J30=0,"",IF(K30=1,UPPER(INDEX('2 Import devis'!$B$6:$B$29,J30)),IF(L30>0,TRIM(SUBSTITUTE(INDEX('3 Catalogue outils'!$A$6:$AC$5005,L30,2),CHAR(10)," ")),INDEX('2 Import devis'!$B$6:$B$29,J30)))) | D30: =IF(OR(J30=0,K30=1),"",1) | E30: =IF(OR(J30=0,K30=1),"",IF(L30>0,IF(N(INDEX('3 Catalogue outils'!$A$6:$AC$5005,L30,22))=0,IF(ISTEXT(INDEX('3 Catalogue outils'!$A$6:$AC$5005,L30,22)),INDEX('3 Catalogue outils'!$A$6:$AC$5005,L30,22),"FR"),"FR"),"FR")) | F30: =IF(L30>0,IF(N(INDEX('3 Catalogue outils'!$A$6:$AC$5005,L30,3))=0,"",ROUND(INDEX('3 Catalogue outils'!$A$6:$AC$5005,L30,3),1)),"") | G30: =IF(OR(D30="",INDEX('2 Import devis'!$G$6:$G$29,J30)=""),"",INDEX('2 Import devis'!$G$6:$G$29,J30)) | I30: =IF(J30=0,0,1) | J30: =IF(16>MAX('2 Import devis'!$L$6:$L$29),0,COUNTIF('2 Import devis'!$L$6:$L$29,"<"&16)+1) | K30: =IF(J30=0,0,IF(N(INDEX('2 Import devis'!$C$6:$C$29,J30))=0,1,0)) | L30: =IF(OR(J30=0,K30=1,B30=""),0,IFERROR(MATCH(B30,'3 Catalogue outils'!$A$6:$A$5005,0),0)) | M30: =IF(L30>0,IF(INDEX('3 Catalogue outils'!$A$6:$AC$5005,L30,20)=0,"",INDEX('3 Catalogue outils'!$A$6:$AC$5005,L30,20)),"") | N30: =IF(L30>0,IF(INDEX('3 Catalogue outils'!$A$6:$AC$5005,L30,23)=0,"",INDEX('3 Catalogue outils'!$A$6:$AC$5005,L30,23)),"") | O30: =IF(L30>0,IF(INDEX('3 Catalogue outils'!$A$6:$AC$5005,L30,4)=0,"",INDEX('3 Catalogue outils'!$A$6:$AC$5005,L30,4)),"") | P30: =IF(L30>0,IF(INDEX('3 Catalogue outils'!$A$6:$AC$5005,L30,5)=0,"",INDEX('3 Catalogue outils'!$A$6:$AC$5005,L30,5)),"")
A31: =IF(OR(J31=0,K31=1),"",COUNTIF(K$15:K31,0)-COUNTIF(J$15:J31,0)) | C31: =IF(J31=0,"",IF(K31=1,UPPER(INDEX('2 Import devis'!$B$6:$B$29,J31)),IF(L31>0,TRIM(SUBSTITUTE(INDEX('3 Catalogue outils'!$A$6:$AC$5005,L31,2),CHAR(10)," ")),INDEX('2 Import devis'!$B$6:$B$29,J31)))) | D31: =IF(OR(J31=0,K31=1),"",1) | E31: =IF(OR(J31=0,K31=1),"",IF(L31>0,IF(N(INDEX('3 Catalogue outils'!$A$6:$AC$5005,L31,22))=0,IF(ISTEXT(INDEX('3 Catalogue outils'!$A$6:$AC$5005,L31,22)),INDEX('3 Catalogue outils'!$A$6:$AC$5005,L31,22),"FR"),"FR"),"FR")) | F31: =IF(L31>0,IF(N(INDEX('3 Catalogue outils'!$A$6:$AC$5005,L31,3))=0,"",ROUND(INDEX('3 Catalogue outils'!$A$6:$AC$5005,L31,3),1)),"") | G31: =IF(OR(D31="",INDEX('2 Import devis'!$G$6:$G$29,J31)=""),"",INDEX('2 Import devis'!$G$6:$G$29,J31)) | I31: =IF(J31=0,0,1) | J31: =IF(17>MAX('2 Import devis'!$L$6:$L$29),0,COUNTIF('2 Import devis'!$L$6:$L$29,"<"&17)+1) | K31: =IF(J31=0,0,IF(N(INDEX('2 Import devis'!$C$6:$C$29,J31))=0,1,0)) | L31: =IF(OR(J31=0,K31=1,B31=""),0,IFERROR(MATCH(B31,'3 Catalogue outils'!$A$6:$A$5005,0),0)) | M31: =IF(L31>0,IF(INDEX('3 Catalogue outils'!$A$6:$AC$5005,L31,20)=0,"",INDEX('3 Catalogue outils'!$A$6:$AC$5005,L31,20)),"") | N31: =IF(L31>0,IF(INDEX('3 Catalogue outils'!$A$6:$AC$5005,L31,23)=0,"",INDEX('3 Catalogue outils'!$A$6:$AC$5005,L31,23)),"") | O31: =IF(L31>0,IF(INDEX('3 Catalogue outils'!$A$6:$AC$5005,L31,4)=0,"",INDEX('3 Catalogue outils'!$A$6:$AC$5005,L31,4)),"") | P31: =IF(L31>0,IF(INDEX('3 Catalogue outils'!$A$6:$AC$5005,L31,5)=0,"",INDEX('3 Catalogue outils'!$A$6:$AC$5005,L31,5)),"")
A32: =IF(OR(J32=0,K32=1),"",COUNTIF(K$15:K32,0)-COUNTIF(J$15:J32,0)) | C32: =IF(J32=0,"",IF(K32=1,UPPER(INDEX('2 Import devis'!$B$6:$B$29,J32)),IF(L32>0,TRIM(SUBSTITUTE(INDEX('3 Catalogue outils'!$A$6:$AC$5005,L32,2),CHAR(10)," ")),INDEX('2 Import devis'!$B$6:$B$29,J32)))) | D32: =IF(OR(J32=0,K32=1),"",1) | E32: =IF(OR(J32=0,K32=1),"",IF(L32>0,IF(N(INDEX('3 Catalogue outils'!$A$6:$AC$5005,L32,22))=0,IF(ISTEXT(INDEX('3 Catalogue outils'!$A$6:$AC$5005,L32,22)),INDEX('3 Catalogue outils'!$A$6:$AC$5005,L32,22),"FR"),"FR"),"FR")) | F32: =IF(L32>0,IF(N(INDEX('3 Catalogue outils'!$A$6:$AC$5005,L32,3))=0,"",ROUND(INDEX('3 Catalogue outils'!$A$6:$AC$5005,L32,3),1)),"") | G32: =IF(OR(D32="",INDEX('2 Import devis'!$G$6:$G$29,J32)=""),"",INDEX('2 Import devis'!$G$6:$G$29,J32)) | I32: =IF(J32=0,0,1) | J32: =IF(18>MAX('2 Import devis'!$L$6:$L$29),0,COUNTIF('2 Import devis'!$L$6:$L$29,"<"&18)+1) | K32: =IF(J32=0,0,IF(N(INDEX('2 Import devis'!$C$6:$C$29,J32))=0,1,0)) | L32: =IF(OR(J32=0,K32=1,B32=""),0,IFERROR(MATCH(B32,'3 Catalogue outils'!$A$6:$A$5005,0),0)) | M32: =IF(L32>0,IF(INDEX('3 Catalogue outils'!$A$6:$AC$5005,L32,20)=0,"",INDEX('3 Catalogue outils'!$A$6:$AC$5005,L32,20)),"") | N32: =IF(L32>0,IF(INDEX('3 Catalogue outils'!$A$6:$AC$5005,L32,23)=0,"",INDEX('3 Catalogue outils'!$A$6:$AC$5005,L32,23)),"") | O32: =IF(L32>0,IF(INDEX('3 Catalogue outils'!$A$6:$AC$5005,L32,4)=0,"",INDEX('3 Catalogue outils'!$A$6:$AC$5005,L32,4)),"") | P32: =IF(L32>0,IF(INDEX('3 Catalogue outils'!$A$6:$AC$5005,L32,5)=0,"",INDEX('3 Catalogue outils'!$A$6:$AC$5005,L32,5)),"")
A33: =IF(OR(J33=0,K33=1),"",COUNTIF(K$15:K33,0)-COUNTIF(J$15:J33,0)) | C33: =IF(J33=0,"",IF(K33=1,UPPER(INDEX('2 Import devis'!$B$6:$B$29,J33)),IF(L33>0,TRIM(SUBSTITUTE(INDEX('3 Catalogue outils'!$A$6:$AC$5005,L33,2),CHAR(10)," ")),INDEX('2 Import devis'!$B$6:$B$29,J33)))) | D33: =IF(OR(J33=0,K33=1),"",1) | E33: =IF(OR(J33=0,K33=1),"",IF(L33>0,IF(N(INDEX('3 Catalogue outils'!$A$6:$AC$5005,L33,22))=0,IF(ISTEXT(INDEX('3 Catalogue outils'!$A$6:$AC$5005,L33,22)),INDEX('3 Catalogue outils'!$A$6:$AC$5005,L33,22),"FR"),"FR"),"FR")) | F33: =IF(L33>0,IF(N(INDEX('3 Catalogue outils'!$A$6:$AC$5005,L33,3))=0,"",ROUND(INDEX('3 Catalogue outils'!$A$6:$AC$5005,L33,3),1)),"") | G33: =IF(OR(D33="",INDEX('2 Import devis'!$G$6:$G$29,J33)=""),"",INDEX('2 Import devis'!$G$6:$G$29,J33)) | I33: =IF(J33=0,0,1) | J33: =IF(19>MAX('2 Import devis'!$L$6:$L$29),0,COUNTIF('2 Import devis'!$L$6:$L$29,"<"&19)+1) | K33: =IF(J33=0,0,IF(N(INDEX('2 Import devis'!$C$6:$C$29,J33))=0,1,0)) | L33: =IF(OR(J33=0,K33=1,B33=""),0,IFERROR(MATCH(B33,'3 Catalogue outils'!$A$6:$A$5005,0),0)) | M33: =IF(L33>0,IF(INDEX('3 Catalogue outils'!$A$6:$AC$5005,L33,20)=0,"",INDEX('3 Catalogue outils'!$A$6:$AC$5005,L33,20)),"") | N33: =IF(L33>0,IF(INDEX('3 Catalogue outils'!$A$6:$AC$5005,L33,23)=0,"",INDEX('3 Catalogue outils'!$A$6:$AC$5005,L33,23)),"") | O33: =IF(L33>0,IF(INDEX('3 Catalogue outils'!$A$6:$AC$5005,L33,4)=0,"",INDEX('3 Catalogue outils'!$A$6:$AC$5005,L33,4)),"") | P33: =IF(L33>0,IF(INDEX('3 Catalogue outils'!$A$6:$AC$5005,L33,5)=0,"",INDEX('3 Catalogue outils'!$A$6:$AC$5005,L33,5)),"")
A34: =IF(OR(J34=0,K34=1),"",COUNTIF(K$15:K34,0)-COUNTIF(J$15:J34,0)) | C34: =IF(J34=0,"",IF(K34=1,UPPER(INDEX('2 Import devis'!$B$6:$B$29,J34)),IF(L34>0,TRIM(SUBSTITUTE(INDEX('3 Catalogue outils'!$A$6:$AC$5005,L34,2),CHAR(10)," ")),INDEX('2 Import devis'!$B$6:$B$29,J34)))) | D34: =IF(OR(J34=0,K34=1),"",1) | E34: =IF(OR(J34=0,K34=1),"",IF(L34>0,IF(N(INDEX('3 Catalogue outils'!$A$6:$AC$5005,L34,22))=0,IF(ISTEXT(INDEX('3 Catalogue outils'!$A$6:$AC$5005,L34,22)),INDEX('3 Catalogue outils'!$A$6:$AC$5005,L34,22),"FR"),"FR"),"FR")) | F34: =IF(L34>0,IF(N(INDEX('3 Catalogue outils'!$A$6:$AC$5005,L34,3))=0,"",ROUND(INDEX('3 Catalogue outils'!$A$6:$AC$5005,L34,3),1)),"") | G34: =IF(OR(D34="",INDEX('2 Import devis'!$G$6:$G$29,J34)=""),"",INDEX('2 Import devis'!$G$6:$G$29,J34)) | I34: =IF(J34=0,0,1) | J34: =IF(20>MAX('2 Import devis'!$L$6:$L$29),0,COUNTIF('2 Import devis'!$L$6:$L$29,"<"&20)+1) | K34: =IF(J34=0,0,IF(N(INDEX('2 Import devis'!$C$6:$C$29,J34))=0,1,0)) | L34: =IF(OR(J34=0,K34=1,B34=""),0,IFERROR(MATCH(B34,'3 Catalogue outils'!$A$6:$A$5005,0),0)) | M34: =IF(L34>0,IF(INDEX('3 Catalogue outils'!$A$6:$AC$5005,L34,20)=0,"",INDEX('3 Catalogue outils'!$A$6:$AC$5005,L34,20)),"") | N34: =IF(L34>0,IF(INDEX('3 Catalogue outils'!$A$6:$AC$5005,L34,23)=0,"",INDEX('3 Catalogue outils'!$A$6:$AC$5005,L34,23)),"") | O34: =IF(L34>0,IF(INDEX('3 Catalogue outils'!$A$6:$AC$5005,L34,4)=0,"",INDEX('3 Catalogue outils'!$A$6:$AC$5005,L34,4)),"") | P34: =IF(L34>0,IF(INDEX('3 Catalogue outils'!$A$6:$AC$5005,L34,5)=0,"",INDEX('3 Catalogue outils'!$A$6:$AC$5005,L34,5)),"")
A35: =IF(OR(J35=0,K35=1),"",COUNTIF(K$15:K35,0)-COUNTIF(J$15:J35,0)) | C35: =IF(J35=0,"",IF(K35=1,UPPER(INDEX('2 Import devis'!$B$6:$B$29,J35)),IF(L35>0,TRIM(SUBSTITUTE(INDEX('3 Catalogue outils'!$A$6:$AC$5005,L35,2),CHAR(10)," ")),INDEX('2 Import devis'!$B$6:$B$29,J35)))) | D35: =IF(OR(J35=0,K35=1),"",1) | E35: =IF(OR(J35=0,K35=1),"",IF(L35>0,IF(N(INDEX('3 Catalogue outils'!$A$6:$AC$5005,L35,22))=0,IF(ISTEXT(INDEX('3 Catalogue outils'!$A$6:$AC$5005,L35,22)),INDEX('3 Catalogue outils'!$A$6:$AC$5005,L35,22),"FR"),"FR"),"FR")) | F35: =IF(L35>0,IF(N(INDEX('3 Catalogue outils'!$A$6:$AC$5005,L35,3))=0,"",ROUND(INDEX('3 Catalogue outils'!$A$6:$AC$5005,L35,3),1)),"") | G35: =IF(OR(D35="",INDEX('2 Import devis'!$G$6:$G$29,J35)=""),"",INDEX('2 Import devis'!$G$6:$G$29,J35)) | I35: =IF(J35=0,0,1) | J35: =IF(21>MAX('2 Import devis'!$L$6:$L$29),0,COUNTIF('2 Import devis'!$L$6:$L$29,"<"&21)+1) | K35: =IF(J35=0,0,IF(N(INDEX('2 Import devis'!$C$6:$C$29,J35))=0,1,0)) | L35: =IF(OR(J35=0,K35=1,B35=""),0,IFERROR(MATCH(B35,'3 Catalogue outils'!$A$6:$A$5005,0),0)) | M35: =IF(L35>0,IF(INDEX('3 Catalogue outils'!$A$6:$AC$5005,L35,20)=0,"",INDEX('3 Catalogue outils'!$A$6:$AC$5005,L35,20)),"") | N35: =IF(L35>0,IF(INDEX('3 Catalogue outils'!$A$6:$AC$5005,L35,23)=0,"",INDEX('3 Catalogue outils'!$A$6:$AC$5005,L35,23)),"") | O35: =IF(L35>0,IF(INDEX('3 Catalogue outils'!$A$6:$AC$5005,L35,4)=0,"",INDEX('3 Catalogue outils'!$A$6:$AC$5005,L35,4)),"") | P35: =IF(L35>0,IF(INDEX('3 Catalogue outils'!$A$6:$AC$5005,L35,5)=0,"",INDEX('3 Catalogue outils'!$A$6:$AC$5005,L35,5)),"")
A36: =IF(OR(J36=0,K36=1),"",COUNTIF(K$15:K36,0)-COUNTIF(J$15:J36,0)) | C36: =IF(J36=0,"",IF(K36=1,UPPER(INDEX('2 Import devis'!$B$6:$B$29,J36)),IF(L36>0,TRIM(SUBSTITUTE(INDEX('3 Catalogue outils'!$A$6:$AC$5005,L36,2),CHAR(10)," ")),INDEX('2 Import devis'!$B$6:$B$29,J36)))) | D36: =IF(OR(J36=0,K36=1),"",1) | E36: =IF(OR(J36=0,K36=1),"",IF(L36>0,IF(N(INDEX('3 Catalogue outils'!$A$6:$AC$5005,L36,22))=0,IF(ISTEXT(INDEX('3 Catalogue outils'!$A$6:$AC$5005,L36,22)),INDEX('3 Catalogue outils'!$A$6:$AC$5005,L36,22),"FR"),"FR"),"FR")) | F36: =IF(L36>0,IF(N(INDEX('3 Catalogue outils'!$A$6:$AC$5005,L36,3))=0,"",ROUND(INDEX('3 Catalogue outils'!$A$6:$AC$5005,L36,3),1)),"") | G36: =IF(OR(D36="",INDEX('2 Import devis'!$G$6:$G$29,J36)=""),"",INDEX('2 Import devis'!$G$6:$G$29,J36)) | I36: =IF(J36=0,0,1) | J36: =IF(22>MAX('2 Import devis'!$L$6:$L$29),0,COUNTIF('2 Import devis'!$L$6:$L$29,"<"&22)+1) | K36: =IF(J36=0,0,IF(N(INDEX('2 Import devis'!$C$6:$C$29,J36))=0,1,0)) | L36: =IF(OR(J36=0,K36=1,B36=""),0,IFERROR(MATCH(B36,'3 Catalogue outils'!$A$6:$A$5005,0),0)) | M36: =IF(L36>0,IF(INDEX('3 Catalogue outils'!$A$6:$AC$5005,L36,20)=0,"",INDEX('3 Catalogue outils'!$A$6:$AC$5005,L36,20)),"") | N36: =IF(L36>0,IF(INDEX('3 Catalogue outils'!$A$6:$AC$5005,L36,23)=0,"",INDEX('3 Catalogue outils'!$A$6:$AC$5005,L36,23)),"") | O36: =IF(L36>0,IF(INDEX('3 Catalogue outils'!$A$6:$AC$5005,L36,4)=0,"",INDEX('3 Catalogue outils'!$A$6:$AC$5005,L36,4)),"") | P36: =IF(L36>0,IF(INDEX('3 Catalogue outils'!$A$6:$AC$5005,L36,5)=0,"",INDEX('3 Catalogue outils'!$A$6:$AC$5005,L36,5)),"")
A37: =IF(OR(J37=0,K37=1),"",COUNTIF(K$15:K37,0)-COUNTIF(J$15:J37,0)) | C37: =IF(J37=0,"",IF(K37=1,UPPER(INDEX('2 Import devis'!$B$6:$B$29,J37)),IF(L37>0,TRIM(SUBSTITUTE(INDEX('3 Catalogue outils'!$A$6:$AC$5005,L37,2),CHAR(10)," ")),INDEX('2 Import devis'!$B$6:$B$29,J37)))) | D37: =IF(OR(J37=0,K37=1),"",1) | E37: =IF(OR(J37=0,K37=1),"",IF(L37>0,IF(N(INDEX('3 Catalogue outils'!$A$6:$AC$5005,L37,22))=0,IF(ISTEXT(INDEX('3 Catalogue outils'!$A$6:$AC$5005,L37,22)),INDEX('3 Catalogue outils'!$A$6:$AC$5005,L37,22),"FR"),"FR"),"FR")) | F37: =IF(L37>0,IF(N(INDEX('3 Catalogue outils'!$A$6:$AC$5005,L37,3))=0,"",ROUND(INDEX('3 Catalogue outils'!$A$6:$AC$5005,L37,3),1)),"") | G37: =IF(OR(D37="",INDEX('2 Import devis'!$G$6:$G$29,J37)=""),"",INDEX('2 Import devis'!$G$6:$G$29,J37)) | I37: =IF(J37=0,0,1) | J37: =IF(23>MAX('2 Import devis'!$L$6:$L$29),0,COUNTIF('2 Import devis'!$L$6:$L$29,"<"&23)+1) | K37: =IF(J37=0,0,IF(N(INDEX('2 Import devis'!$C$6:$C$29,J37))=0,1,0)) | L37: =IF(OR(J37=0,K37=1,B37=""),0,IFERROR(MATCH(B37,'3 Catalogue outils'!$A$6:$A$5005,0),0)) | M37: =IF(L37>0,IF(INDEX('3 Catalogue outils'!$A$6:$AC$5005,L37,20)=0,"",INDEX('3 Catalogue outils'!$A$6:$AC$5005,L37,20)),"") | N37: =IF(L37>0,IF(INDEX('3 Catalogue outils'!$A$6:$AC$5005,L37,23)=0,"",INDEX('3 Catalogue outils'!$A$6:$AC$5005,L37,23)),"") | O37: =IF(L37>0,IF(INDEX('3 Catalogue outils'!$A$6:$AC$5005,L37,4)=0,"",INDEX('3 Catalogue outils'!$A$6:$AC$5005,L37,4)),"") | P37: =IF(L37>0,IF(INDEX('3 Catalogue outils'!$A$6:$AC$5005,L37,5)=0,"",INDEX('3 Catalogue outils'!$A$6:$AC$5005,L37,5)),"")
A38: =IF(OR(J38=0,K38=1),"",COUNTIF(K$15:K38,0)-COUNTIF(J$15:J38,0)) | C38: =IF(J38=0,"",IF(K38=1,UPPER(INDEX('2 Import devis'!$B$6:$B$29,J38)),IF(L38>0,TRIM(SUBSTITUTE(INDEX('3 Catalogue outils'!$A$6:$AC$5005,L38,2),CHAR(10)," ")),INDEX('2 Import devis'!$B$6:$B$29,J38)))) | D38: =IF(OR(J38=0,K38=1),"",1) | E38: =IF(OR(J38=0,K38=1),"",IF(L38>0,IF(N(INDEX('3 Catalogue outils'!$A$6:$AC$5005,L38,22))=0,IF(ISTEXT(INDEX('3 Catalogue outils'!$A$6:$AC$5005,L38,22)),INDEX('3 Catalogue outils'!$A$6:$AC$5005,L38,22),"FR"),"FR"),"FR")) | F38: =IF(L38>0,IF(N(INDEX('3 Catalogue outils'!$A$6:$AC$5005,L38,3))=0,"",ROUND(INDEX('3 Catalogue outils'!$A$6:$AC$5005,L38,3),1)),"") | G38: =IF(OR(D38="",INDEX('2 Import devis'!$G$6:$G$29,J38)=""),"",INDEX('2 Import devis'!$G$6:$G$29,J38)) | I38: =IF(J38=0,0,1) | J38: =IF(24>MAX('2 Import devis'!$L$6:$L$29),0,COUNTIF('2 Import devis'!$L$6:$L$29,"<"&24)+1) | K38: =IF(J38=0,0,IF(N(INDEX('2 Import devis'!$C$6:$C$29,J38))=0,1,0)) | L38: =IF(OR(J38=0,K38=1,B38=""),0,IFERROR(MATCH(B38,'3 Catalogue outils'!$A$6:$A$5005,0),0)) | M38: =IF(L38>0,IF(INDEX('3 Catalogue outils'!$A$6:$AC$5005,L38,20)=0,"",INDEX('3 Catalogue outils'!$A$6:$AC$5005,L38,20)),"") | N38: =IF(L38>0,IF(INDEX('3 Catalogue outils'!$A$6:$AC$5005,L38,23)=0,"",INDEX('3 Catalogue outils'!$A$6:$AC$5005,L38,23)),"") | O38: =IF(L38>0,IF(INDEX('3 Catalogue outils'!$A$6:$AC$5005,L38,4)=0,"",INDEX('3 Catalogue outils'!$A$6:$AC$5005,L38,4)),"") | P38: =IF(L38>0,IF(INDEX('3 Catalogue outils'!$A$6:$AC$5005,L38,5)=0,"",INDEX('3 Catalogue outils'!$A$6:$AC$5005,L38,5)),"")
A39: =IF(OR(J39=0,K39=1),"",COUNTIF(K$15:K39,0)-COUNTIF(J$15:J39,0)) | C39: =IF(J39=0,"",IF(K39=1,UPPER(INDEX('2 Import devis'!$B$6:$B$29,J39)),IF(L39>0,TRIM(SUBSTITUTE(INDEX('3 Catalogue outils'!$A$6:$AC$5005,L39,2),CHAR(10)," ")),INDEX('2 Import devis'!$B$6:$B$29,J39)))) | D39: =IF(OR(J39=0,K39=1),"",1) | E39: =IF(OR(J39=0,K39=1),"",IF(L39>0,IF(N(INDEX('3 Catalogue outils'!$A$6:$AC$5005,L39,22))=0,IF(ISTEXT(INDEX('3 Catalogue outils'!$A$6:$AC$5005,L39,22)),INDEX('3 Catalogue outils'!$A$6:$AC$5005,L39,22),"FR"),"FR"),"FR")) | F39: =IF(L39>0,IF(N(INDEX('3 Catalogue outils'!$A$6:$AC$5005,L39,3))=0,"",ROUND(INDEX('3 Catalogue outils'!$A$6:$AC$5005,L39,3),1)),"") | G39: =IF(OR(D39="",INDEX('2 Import devis'!$G$6:$G$29,J39)=""),"",INDEX('2 Import devis'!$G$6:$G$29,J39)) | I39: =IF(J39=0,0,1) | J39: =IF(25>MAX('2 Import devis'!$L$6:$L$29),0,COUNTIF('2 Import devis'!$L$6:$L$29,"<"&25)+1) | K39: =IF(J39=0,0,IF(N(INDEX('2 Import devis'!$C$6:$C$29,J39))=0,1,0)) | L39: =IF(OR(J39=0,K39=1,B39=""),0,IFERROR(MATCH(B39,'3 Catalogue outils'!$A$6:$A$5005,0),0)) | M39: =IF(L39>0,IF(INDEX('3 Catalogue outils'!$A$6:$AC$5005,L39,20)=0,"",INDEX('3 Catalogue outils'!$A$6:$AC$5005,L39,20)),"") | N39: =IF(L39>0,IF(INDEX('3 Catalogue outils'!$A$6:$AC$5005,L39,23)=0,"",INDEX('3 Catalogue outils'!$A$6:$AC$5005,L39,23)),"") | O39: =IF(L39>0,IF(INDEX('3 Catalogue outils'!$A$6:$AC$5005,L39,4)=0,"",INDEX('3 Catalogue outils'!$A$6:$AC$5005,L39,4)),"") | P39: =IF(L39>0,IF(INDEX('3 Catalogue outils'!$A$6:$AC$5005,L39,5)=0,"",INDEX('3 Catalogue outils'!$A$6:$AC$5005,L39,5)),"")
A40: =IF(OR(J40=0,K40=1),"",COUNTIF(K$15:K40,0)-COUNTIF(J$15:J40,0)) | C40: =IF(J40=0,"",IF(K40=1,UPPER(INDEX('2 Import devis'!$B$6:$B$29,J40)),IF(L40>0,TRIM(SUBSTITUTE(INDEX('3 Catalogue outils'!$A$6:$AC$5005,L40,2),CHAR(10)," ")),INDEX('2 Import devis'!$B$6:$B$29,J40)))) | D40: =IF(OR(J40=0,K40=1),"",1) | E40: =IF(OR(J40=0,K40=1),"",IF(L40>0,IF(N(INDEX('3 Catalogue outils'!$A$6:$AC$5005,L40,22))=0,IF(ISTEXT(INDEX('3 Catalogue outils'!$A$6:$AC$5005,L40,22)),INDEX('3 Catalogue outils'!$A$6:$AC$5005,L40,22),"FR"),"FR"),"FR")) | F40: =IF(L40>0,IF(N(INDEX('3 Catalogue outils'!$A$6:$AC$5005,L40,3))=0,"",ROUND(INDEX('3 Catalogue outils'!$A$6:$AC$5005,L40,3),1)),"") | G40: =IF(OR(D40="",INDEX('2 Import devis'!$G$6:$G$29,J40)=""),"",INDEX('2 Import devis'!$G$6:$G$29,J40)) | I40: =IF(J40=0,0,1) | J40: =IF(26>MAX('2 Import devis'!$L$6:$L$29),0,COUNTIF('2 Import devis'!$L$6:$L$29,"<"&26)+1) | K40: =IF(J40=0,0,IF(N(INDEX('2 Import devis'!$C$6:$C$29,J40))=0,1,0)) | L40: =IF(OR(J40=0,K40=1,B40=""),0,IFERROR(MATCH(B40,'3 Catalogue outils'!$A$6:$A$5005,0),0)) | M40: =IF(L40>0,IF(INDEX('3 Catalogue outils'!$A$6:$AC$5005,L40,20)=0,"",INDEX('3 Catalogue outils'!$A$6:$AC$5005,L40,20)),"") | N40: =IF(L40>0,IF(INDEX('3 Catalogue outils'!$A$6:$AC$5005,L40,23)=0,"",INDEX('3 Catalogue outils'!$A$6:$AC$5005,L40,23)),"") | O40: =IF(L40>0,IF(INDEX('3 Catalogue outils'!$A$6:$AC$5005,L40,4)=0,"",INDEX('3 Catalogue outils'!$A$6:$AC$5005,L40,4)),"") | P40: =IF(L40>0,IF(INDEX('3 Catalogue outils'!$A$6:$AC$5005,L40,5)=0,"",INDEX('3 Catalogue outils'!$A$6:$AC$5005,L40,5)),"")
A41: =IF(OR(J41=0,K41=1),"",COUNTIF(K$15:K41,0)-COUNTIF(J$15:J41,0)) | C41: =IF(J41=0,"",IF(K41=1,UPPER(INDEX('2 Import devis'!$B$6:$B$29,J41)),IF(L41>0,TRIM(SUBSTITUTE(INDEX('3 Catalogue outils'!$A$6:$AC$5005,L41,2),CHAR(10)," ")),INDEX('2 Import devis'!$B$6:$B$29,J41)))) | D41: =IF(OR(J41=0,K41=1),"",1) | E41: =IF(OR(J41=0,K41=1),"",IF(L41>0,IF(N(INDEX('3 Catalogue outils'!$A$6:$AC$5005,L41,22))=0,IF(ISTEXT(INDEX('3 Catalogue outils'!$A$6:$AC$5005,L41,22)),INDEX('3 Catalogue outils'!$A$6:$AC$5005,L41,22),"FR"),"FR"),"FR")) | F41: =IF(L41>0,IF(N(INDEX('3 Catalogue outils'!$A$6:$AC$5005,L41,3))=0,"",ROUND(INDEX('3 Catalogue outils'!$A$6:$AC$5005,L41,3),1)),"") | G41: =IF(OR(D41="",INDEX('2 Import devis'!$G$6:$G$29,J41)=""),"",INDEX('2 Import devis'!$G$6:$G$29,J41)) | I41: =IF(J41=0,0,1) | J41: =IF(27>MAX('2 Import devis'!$L$6:$L$29),0,COUNTIF('2 Import devis'!$L$6:$L$29,"<"&27)+1) | K41: =IF(J41=0,0,IF(N(INDEX('2 Import devis'!$C$6:$C$29,J41))=0,1,0)) | L41: =IF(OR(J41=0,K41=1,B41=""),0,IFERROR(MATCH(B41,'3 Catalogue outils'!$A$6:$A$5005,0),0)) | M41: =IF(L41>0,IF(INDEX('3 Catalogue outils'!$A$6:$AC$5005,L41,20)=0,"",INDEX('3 Catalogue outils'!$A$6:$AC$5005,L41,20)),"") | N41: =IF(L41>0,IF(INDEX('3 Catalogue outils'!$A$6:$AC$5005,L41,23)=0,"",INDEX('3 Catalogue outils'!$A$6:$AC$5005,L41,23)),"") | O41: =IF(L41>0,IF(INDEX('3 Catalogue outils'!$A$6:$AC$5005,L41,4)=0,"",INDEX('3 Catalogue outils'!$A$6:$AC$5005,L41,4)),"") | P41: =IF(L41>0,IF(INDEX('3 Catalogue outils'!$A$6:$AC$5005,L41,5)=0,"",INDEX('3 Catalogue outils'!$A$6:$AC$5005,L41,5)),"")
A42: =IF(OR(J42=0,K42=1),"",COUNTIF(K$15:K42,0)-COUNTIF(J$15:J42,0)) | C42: =IF(J42=0,"",IF(K42=1,UPPER(INDEX('2 Import devis'!$B$6:$B$29,J42)),IF(L42>0,TRIM(SUBSTITUTE(INDEX('3 Catalogue outils'!$A$6:$AC$5005,L42,2),CHAR(10)," ")),INDEX('2 Import devis'!$B$6:$B$29,J42)))) | D42: =IF(OR(J42=0,K42=1),"",1) | E42: =IF(OR(J42=0,K42=1),"",IF(L42>0,IF(N(INDEX('3 Catalogue outils'!$A$6:$AC$5005,L42,22))=0,IF(ISTEXT(INDEX('3 Catalogue outils'!$A$6:$AC$5005,L42,22)),INDEX('3 Catalogue outils'!$A$6:$AC$5005,L42,22),"FR"),"FR"),"FR")) | F42: =IF(L42>0,IF(N(INDEX('3 Catalogue outils'!$A$6:$AC$5005,L42,3))=0,"",ROUND(INDEX('3 Catalogue outils'!$A$6:$AC$5005,L42,3),1)),"") | G42: =IF(OR(D42="",INDEX('2 Import devis'!$G$6:$G$29,J42)=""),"",INDEX('2 Import devis'!$G$6:$G$29,J42)) | I42: =IF(J42=0,0,1) | J42: =IF(28>MAX('2 Import devis'!$L$6:$L$29),0,COUNTIF('2 Import devis'!$L$6:$L$29,"<"&28)+1) | K42: =IF(J42=0,0,IF(N(INDEX('2 Import devis'!$C$6:$C$29,J42))=0,1,0)) | L42: =IF(OR(J42=0,K42=1,B42=""),0,IFERROR(MATCH(B42,'3 Catalogue outils'!$A$6:$A$5005,0),0)) | M42: =IF(L42>0,IF(INDEX('3 Catalogue outils'!$A$6:$AC$5005,L42,20)=0,"",INDEX('3 Catalogue outils'!$A$6:$AC$5005,L42,20)),"") | N42: =IF(L42>0,IF(INDEX('3 Catalogue outils'!$A$6:$AC$5005,L42,23)=0,"",INDEX('3 Catalogue outils'!$A$6:$AC$5005,L42,23)),"") | O42: =IF(L42>0,IF(INDEX('3 Catalogue outils'!$A$6:$AC$5005,L42,4)=0,"",INDEX('3 Catalogue outils'!$A$6:$AC$5005,L42,4)),"") | P42: =IF(L42>0,IF(INDEX('3 Catalogue outils'!$A$6:$AC$5005,L42,5)=0,"",INDEX('3 Catalogue outils'!$A$6:$AC$5005,L42,5)),"")
A43: =IF(OR(J43=0,K43=1),"",COUNTIF(K$15:K43,0)-COUNTIF(J$15:J43,0)) | C43: =IF(J43=0,"",IF(K43=1,UPPER(INDEX('2 Import devis'!$B$6:$B$29,J43)),IF(L43>0,TRIM(SUBSTITUTE(INDEX('3 Catalogue outils'!$A$6:$AC$5005,L43,2),CHAR(10)," ")),INDEX('2 Import devis'!$B$6:$B$29,J43)))) | D43: =IF(OR(J43=0,K43=1),"",1) | E43: =IF(OR(J43=0,K43=1),"",IF(L43>0,IF(N(INDEX('3 Catalogue outils'!$A$6:$AC$5005,L43,22))=0,IF(ISTEXT(INDEX('3 Catalogue outils'!$A$6:$AC$5005,L43,22)),INDEX('3 Catalogue outils'!$A$6:$AC$5005,L43,22),"FR"),"FR"),"FR")) | F43: =IF(L43>0,IF(N(INDEX('3 Catalogue outils'!$A$6:$AC$5005,L43,3))=0,"",ROUND(INDEX('3 Catalogue outils'!$A$6:$AC$5005,L43,3),1)),"") | G43: =IF(OR(D43="",INDEX('2 Import devis'!$G$6:$G$29,J43)=""),"",INDEX('2 Import devis'!$G$6:$G$29,J43)) | I43: =IF(J43=0,0,1) | J43: =IF(29>MAX('2 Import devis'!$L$6:$L$29),0,COUNTIF('2 Import devis'!$L$6:$L$29,"<"&29)+1) | K43: =IF(J43=0,0,IF(N(INDEX('2 Import devis'!$C$6:$C$29,J43))=0,1,0)) | L43: =IF(OR(J43=0,K43=1,B43=""),0,IFERROR(MATCH(B43,'3 Catalogue outils'!$A$6:$A$5005,0),0)) | M43: =IF(L43>0,IF(INDEX('3 Catalogue outils'!$A$6:$AC$5005,L43,20)=0,"",INDEX('3 Catalogue outils'!$A$6:$AC$5005,L43,20)),"") | N43: =IF(L43>0,IF(INDEX('3 Catalogue outils'!$A$6:$AC$5005,L43,23)=0,"",INDEX('3 Catalogue outils'!$A$6:$AC$5005,L43,23)),"") | O43: =IF(L43>0,IF(INDEX('3 Catalogue outils'!$A$6:$AC$5005,L43,4)=0,"",INDEX('3 Catalogue outils'!$A$6:$AC$5005,L43,4)),"") | P43: =IF(L43>0,IF(INDEX('3 Catalogue outils'!$A$6:$AC$5005,L43,5)=0,"",INDEX('3 Catalogue outils'!$A$6:$AC$5005,L43,5)),"")
A44: =IF(OR(J44=0,K44=1),"",COUNTIF(K$15:K44,0)-COUNTIF(J$15:J44,0)) | C44: =IF(J44=0,"",IF(K44=1,UPPER(INDEX('2 Import devis'!$B$6:$B$29,J44)),IF(L44>0,TRIM(SUBSTITUTE(INDEX('3 Catalogue outils'!$A$6:$AC$5005,L44,2),CHAR(10)," ")),INDEX('2 Import devis'!$B$6:$B$29,J44)))) | D44: =IF(OR(J44=0,K44=1),"",1) | E44: =IF(OR(J44=0,K44=1),"",IF(L44>0,IF(N(INDEX('3 Catalogue outils'!$A$6:$AC$5005,L44,22))=0,IF(ISTEXT(INDEX('3 Catalogue outils'!$A$6:$AC$5005,L44,22)),INDEX('3 Catalogue outils'!$A$6:$AC$5005,L44,22),"FR"),"FR"),"FR")) | F44: =IF(L44>0,IF(N(INDEX('3 Catalogue outils'!$A$6:$AC$5005,L44,3))=0,"",ROUND(INDEX('3 Catalogue outils'!$A$6:$AC$5005,L44,3),1)),"") | G44: =IF(OR(D44="",INDEX('2 Import devis'!$G$6:$G$29,J44)=""),"",INDEX('2 Import devis'!$G$6:$G$29,J44)) | I44: =IF(J44=0,0,1) | J44: =IF(30>MAX('2 Import devis'!$L$6:$L$29),0,COUNTIF('2 Import devis'!$L$6:$L$29,"<"&30)+1) | K44: =IF(J44=0,0,IF(N(INDEX('2 Import devis'!$C$6:$C$29,J44))=0,1,0)) | L44: =IF(OR(J44=0,K44=1,B44=""),0,IFERROR(MATCH(B44,'3 Catalogue outils'!$A$6:$A$5005,0),0)) | M44: =IF(L44>0,IF(INDEX('3 Catalogue outils'!$A$6:$AC$5005,L44,20)=0,"",INDEX('3 Catalogue outils'!$A$6:$AC$5005,L44,20)),"") | N44: =IF(L44>0,IF(INDEX('3 Catalogue outils'!$A$6:$AC$5005,L44,23)=0,"",INDEX('3 Catalogue outils'!$A$6:$AC$5005,L44,23)),"") | O44: =IF(L44>0,IF(INDEX('3 Catalogue outils'!$A$6:$AC$5005,L44,4)=0,"",INDEX('3 Catalogue outils'!$A$6:$AC$5005,L44,4)),"") | P44: =IF(L44>0,IF(INDEX('3 Catalogue outils'!$A$6:$AC$5005,L44,5)=0,"",INDEX('3 Catalogue outils'!$A$6:$AC$5005,L44,5)),"")
A45: =IF(OR(J45=0,K45=1),"",COUNTIF(K$15:K45,0)-COUNTIF(J$15:J45,0)) | C45: =IF(J45=0,"",IF(K45=1,UPPER(INDEX('2 Import devis'!$B$6:$B$29,J45)),IF(L45>0,TRIM(SUBSTITUTE(INDEX('3 Catalogue outils'!$A$6:$AC$5005,L45,2),CHAR(10)," ")),INDEX('2 Import devis'!$B$6:$B$29,J45)))) | D45: =IF(OR(J45=0,K45=1),"",1) | E45: =IF(OR(J45=0,K45=1),"",IF(L45>0,IF(N(INDEX('3 Catalogue outils'!$A$6:$AC$5005,L45,22))=0,IF(ISTEXT(INDEX('3 Catalogue outils'!$A$6:$AC$5005,L45,22)),INDEX('3 Catalogue outils'!$A$6:$AC$5005,L45,22),"FR"),"FR"),"FR")) | F45: =IF(L45>0,IF(N(INDEX('3 Catalogue outils'!$A$6:$AC$5005,L45,3))=0,"",ROUND(INDEX('3 Catalogue outils'!$A$6:$AC$5005,L45,3),1)),"") | G45: =IF(OR(D45="",INDEX('2 Import devis'!$G$6:$G$29,J45)=""),"",INDEX('2 Import devis'!$G$6:$G$29,J45)) | I45: =IF(J45=0,0,1) | J45: =IF(31>MAX('2 Import devis'!$L$6:$L$29),0,COUNTIF('2 Import devis'!$L$6:$L$29,"<"&31)+1) | K45: =IF(J45=0,0,IF(N(INDEX('2 Import devis'!$C$6:$C$29,J45))=0,1,0)) | L45: =IF(OR(J45=0,K45=1,B45=""),0,IFERROR(MATCH(B45,'3 Catalogue outils'!$A$6:$A$5005,0),0)) | M45: =IF(L45>0,IF(INDEX('3 Catalogue outils'!$A$6:$AC$5005,L45,20)=0,"",INDEX('3 Catalogue outils'!$A$6:$AC$5005,L45,20)),"") | N45: =IF(L45>0,IF(INDEX('3 Catalogue outils'!$A$6:$AC$5005,L45,23)=0,"",INDEX('3 Catalogue outils'!$A$6:$AC$5005,L45,23)),"") | O45: =IF(L45>0,IF(INDEX('3 Catalogue outils'!$A$6:$AC$5005,L45,4)=0,"",INDEX('3 Catalogue outils'!$A$6:$AC$5005,L45,4)),"") | P45: =IF(L45>0,IF(INDEX('3 Catalogue outils'!$A$6:$AC$5005,L45,5)=0,"",INDEX('3 Catalogue outils'!$A$6:$AC$5005,L45,5)),"")
A46: =IF(OR(J46=0,K46=1),"",COUNTIF(K$15:K46,0)-COUNTIF(J$15:J46,0)) | C46: =IF(J46=0,"",IF(K46=1,UPPER(INDEX('2 Import devis'!$B$6:$B$29,J46)),IF(L46>0,TRIM(SUBSTITUTE(INDEX('3 Catalogue outils'!$A$6:$AC$5005,L46,2),CHAR(10)," ")),INDEX('2 Import devis'!$B$6:$B$29,J46)))) | D46: =IF(OR(J46=0,K46=1),"",1) | E46: =IF(OR(J46=0,K46=1),"",IF(L46>0,IF(N(INDEX('3 Catalogue outils'!$A$6:$AC$5005,L46,22))=0,IF(ISTEXT(INDEX('3 Catalogue outils'!$A$6:$AC$5005,L46,22)),INDEX('3 Catalogue outils'!$A$6:$AC$5005,L46,22),"FR"),"FR"),"FR")) | F46: =IF(L46>0,IF(N(INDEX('3 Catalogue outils'!$A$6:$AC$5005,L46,3))=0,"",ROUND(INDEX('3 Catalogue outils'!$A$6:$AC$5005,L46,3),1)),"") | G46: =IF(OR(D46="",INDEX('2 Import devis'!$G$6:$G$29,J46)=""),"",INDEX('2 Import devis'!$G$6:$G$29,J46)) | I46: =IF(J46=0,0,1) | J46: =IF(32>MAX('2 Import devis'!$L$6:$L$29),0,COUNTIF('2 Import devis'!$L$6:$L$29,"<"&32)+1) | K46: =IF(J46=0,0,IF(N(INDEX('2 Import devis'!$C$6:$C$29,J46))=0,1,0)) | L46: =IF(OR(J46=0,K46=1,B46=""),0,IFERROR(MATCH(B46,'3 Catalogue outils'!$A$6:$A$5005,0),0)) | M46: =IF(L46>0,IF(INDEX('3 Catalogue outils'!$A$6:$AC$5005,L46,20)=0,"",INDEX('3 Catalogue outils'!$A$6:$AC$5005,L46,20)),"") | N46: =IF(L46>0,IF(INDEX('3 Catalogue outils'!$A$6:$AC$5005,L46,23)=0,"",INDEX('3 Catalogue outils'!$A$6:$AC$5005,L46,23)),"") | O46: =IF(L46>0,IF(INDEX('3 Catalogue outils'!$A$6:$AC$5005,L46,4)=0,"",INDEX('3 Catalogue outils'!$A$6:$AC$5005,L46,4)),"") | P46: =IF(L46>0,IF(INDEX('3 Catalogue outils'!$A$6:$AC$5005,L46,5)=0,"",INDEX('3 Catalogue outils'!$A$6:$AC$5005,L46,5)),"")
A47: =IF(OR(J47=0,K47=1),"",COUNTIF(K$15:K47,0)-COUNTIF(J$15:J47,0)) | C47: =IF(J47=0,"",IF(K47=1,UPPER(INDEX('2 Import devis'!$B$6:$B$29,J47)),IF(L47>0,TRIM(SUBSTITUTE(INDEX('3 Catalogue outils'!$A$6:$AC$5005,L47,2),CHAR(10)," ")),INDEX('2 Import devis'!$B$6:$B$29,J47)))) | D47: =IF(OR(J47=0,K47=1),"",1) | E47: =IF(OR(J47=0,K47=1),"",IF(L47>0,IF(N(INDEX('3 Catalogue outils'!$A$6:$AC$5005,L47,22))=0,IF(ISTEXT(INDEX('3 Catalogue outils'!$A$6:$AC$5005,L47,22)),INDEX('3 Catalogue outils'!$A$6:$AC$5005,L47,22),"FR"),"FR"),"FR")) | F47: =IF(L47>0,IF(N(INDEX('3 Catalogue outils'!$A$6:$AC$5005,L47,3))=0,"",ROUND(INDEX('3 Catalogue outils'!$A$6:$AC$5005,L47,3),1)),"") | G47: =IF(OR(D47="",INDEX('2 Import devis'!$G$6:$G$29,J47)=""),"",INDEX('2 Import devis'!$G$6:$G$29,J47)) | I47: =IF(J47=0,0,1) | J47: =IF(33>MAX('2 Import devis'!$L$6:$L$29),0,COUNTIF('2 Import devis'!$L$6:$L$29,"<"&33)+1) | K47: =IF(J47=0,0,IF(N(INDEX('2 Import devis'!$C$6:$C$29,J47))=0,1,0)) | L47: =IF(OR(J47=0,K47=1,B47=""),0,IFERROR(MATCH(B47,'3 Catalogue outils'!$A$6:$A$5005,0),0)) | M47: =IF(L47>0,IF(INDEX('3 Catalogue outils'!$A$6:$AC$5005,L47,20)=0,"",INDEX('3 Catalogue outils'!$A$6:$AC$5005,L47,20)),"") | N47: =IF(L47>0,IF(INDEX('3 Catalogue outils'!$A$6:$AC$5005,L47,23)=0,"",INDEX('3 Catalogue outils'!$A$6:$AC$5005,L47,23)),"") | O47: =IF(L47>0,IF(INDEX('3 Catalogue outils'!$A$6:$AC$5005,L47,4)=0,"",INDEX('3 Catalogue outils'!$A$6:$AC$5005,L47,4)),"") | P47: =IF(L47>0,IF(INDEX('3 Catalogue outils'!$A$6:$AC$5005,L47,5)=0,"",INDEX('3 Catalogue outils'!$A$6:$AC$5005,L47,5)),"")
A48: =IF(OR(J48=0,K48=1),"",COUNTIF(K$15:K48,0)-COUNTIF(J$15:J48,0)) | C48: =IF(J48=0,"",IF(K48=1,UPPER(INDEX('2 Import devis'!$B$6:$B$29,J48)),IF(L48>0,TRIM(SUBSTITUTE(INDEX('3 Catalogue outils'!$A$6:$AC$5005,L48,2),CHAR(10)," ")),INDEX('2 Import devis'!$B$6:$B$29,J48)))) | D48: =IF(OR(J48=0,K48=1),"",1) | E48: =IF(OR(J48=0,K48=1),"",IF(L48>0,IF(N(INDEX('3 Catalogue outils'!$A$6:$AC$5005,L48,22))=0,IF(ISTEXT(INDEX('3 Catalogue outils'!$A$6:$AC$5005,L48,22)),INDEX('3 Catalogue outils'!$A$6:$AC$5005,L48,22),"FR"),"FR"),"FR")) | F48: =IF(L48>0,IF(N(INDEX('3 Catalogue outils'!$A$6:$AC$5005,L48,3))=0,"",ROUND(INDEX('3 Catalogue outils'!$A$6:$AC$5005,L48,3),1)),"") | G48: =IF(OR(D48="",INDEX('2 Import devis'!$G$6:$G$29,J48)=""),"",INDEX('2 Import devis'!$G$6:$G$29,J48)) | I48: =IF(J48=0,0,1) | J48: =IF(34>MAX('2 Import devis'!$L$6:$L$29),0,COUNTIF('2 Import devis'!$L$6:$L$29,"<"&34)+1) | K48: =IF(J48=0,0,IF(N(INDEX('2 Import devis'!$C$6:$C$29,J48))=0,1,0)) | L48: =IF(OR(J48=0,K48=1,B48=""),0,IFERROR(MATCH(B48,'3 Catalogue outils'!$A$6:$A$5005,0),0)) | M48: =IF(L48>0,IF(INDEX('3 Catalogue outils'!$A$6:$AC$5005,L48,20)=0,"",INDEX('3 Catalogue outils'!$A$6:$AC$5005,L48,20)),"") | N48: =IF(L48>0,IF(INDEX('3 Catalogue outils'!$A$6:$AC$5005,L48,23)=0,"",INDEX('3 Catalogue outils'!$A$6:$AC$5005,L48,23)),"") | O48: =IF(L48>0,IF(INDEX('3 Catalogue outils'!$A$6:$AC$5005,L48,4)=0,"",INDEX('3 Catalogue outils'!$A$6:$AC$5005,L48,4)),"") | P48: =IF(L48>0,IF(INDEX('3 Catalogue outils'!$A$6:$AC$5005,L48,5)=0,"",INDEX('3 Catalogue outils'!$A$6:$AC$5005,L48,5)),"")
A49: =IF(OR(J49=0,K49=1),"",COUNTIF(K$15:K49,0)-COUNTIF(J$15:J49,0)) | C49: =IF(J49=0,"",IF(K49=1,UPPER(INDEX('2 Import devis'!$B$6:$B$29,J49)),IF(L49>0,TRIM(SUBSTITUTE(INDEX('3 Catalogue outils'!$A$6:$AC$5005,L49,2),CHAR(10)," ")),INDEX('2 Import devis'!$B$6:$B$29,J49)))) | D49: =IF(OR(J49=0,K49=1),"",1) | E49: =IF(OR(J49=0,K49=1),"",IF(L49>0,IF(N(INDEX('3 Catalogue outils'!$A$6:$AC$5005,L49,22))=0,IF(ISTEXT(INDEX('3 Catalogue outils'!$A$6:$AC$5005,L49,22)),INDEX('3 Catalogue outils'!$A$6:$AC$5005,L49,22),"FR"),"FR"),"FR")) | F49: =IF(L49>0,IF(N(INDEX('3 Catalogue outils'!$A$6:$AC$5005,L49,3))=0,"",ROUND(INDEX('3 Catalogue outils'!$A$6:$AC$5005,L49,3),1)),"") | G49: =IF(OR(D49="",INDEX('2 Import devis'!$G$6:$G$29,J49)=""),"",INDEX('2 Import devis'!$G$6:$G$29,J49)) | I49: =IF(J49=0,0,1) | J49: =IF(35>MAX('2 Import devis'!$L$6:$L$29),0,COUNTIF('2 Import devis'!$L$6:$L$29,"<"&35)+1) | K49: =IF(J49=0,0,IF(N(INDEX('2 Import devis'!$C$6:$C$29,J49))=0,1,0)) | L49: =IF(OR(J49=0,K49=1,B49=""),0,IFERROR(MATCH(B49,'3 Catalogue outils'!$A$6:$A$5005,0),0)) | M49: =IF(L49>0,IF(INDEX('3 Catalogue outils'!$A$6:$AC$5005,L49,20)=0,"",INDEX('3 Catalogue outils'!$A$6:$AC$5005,L49,20)),"") | N49: =IF(L49>0,IF(INDEX('3 Catalogue outils'!$A$6:$AC$5005,L49,23)=0,"",INDEX('3 Catalogue outils'!$A$6:$AC$5005,L49,23)),"") | O49: =IF(L49>0,IF(INDEX('3 Catalogue outils'!$A$6:$AC$5005,L49,4)=0,"",INDEX('3 Catalogue outils'!$A$6:$AC$5005,L49,4)),"") | P49: =IF(L49>0,IF(INDEX('3 Catalogue outils'!$A$6:$AC$5005,L49,5)=0,"",INDEX('3 Catalogue outils'!$A$6:$AC$5005,L49,5)),"")
A50: =IF(OR(J50=0,K50=1),"",COUNTIF(K$15:K50,0)-COUNTIF(J$15:J50,0)) | C50: =IF(J50=0,"",IF(K50=1,UPPER(INDEX('2 Import devis'!$B$6:$B$29,J50)),IF(L50>0,TRIM(SUBSTITUTE(INDEX('3 Catalogue outils'!$A$6:$AC$5005,L50,2),CHAR(10)," ")),INDEX('2 Import devis'!$B$6:$B$29,J50)))) | D50: =IF(OR(J50=0,K50=1),"",1) | E50: =IF(OR(J50=0,K50=1),"",IF(L50>0,IF(N(INDEX('3 Catalogue outils'!$A$6:$AC$5005,L50,22))=0,IF(ISTEXT(INDEX('3 Catalogue outils'!$A$6:$AC$5005,L50,22)),INDEX('3 Catalogue outils'!$A$6:$AC$5005,L50,22),"FR"),"FR"),"FR")) | F50: =IF(L50>0,IF(N(INDEX('3 Catalogue outils'!$A$6:$AC$5005,L50,3))=0,"",ROUND(INDEX('3 Catalogue outils'!$A$6:$AC$5005,L50,3),1)),"") | G50: =IF(OR(D50="",INDEX('2 Import devis'!$G$6:$G$29,J50)=""),"",INDEX('2 Import devis'!$G$6:$G$29,J50)) | I50: =IF(J50=0,0,1) | J50: =IF(36>MAX('2 Import devis'!$L$6:$L$29),0,COUNTIF('2 Import devis'!$L$6:$L$29,"<"&36)+1) | K50: =IF(J50=0,0,IF(N(INDEX('2 Import devis'!$C$6:$C$29,J50))=0,1,0)) | L50: =IF(OR(J50=0,K50=1,B50=""),0,IFERROR(MATCH(B50,'3 Catalogue outils'!$A$6:$A$5005,0),0)) | M50: =IF(L50>0,IF(INDEX('3 Catalogue outils'!$A$6:$AC$5005,L50,20)=0,"",INDEX('3 Catalogue outils'!$A$6:$AC$5005,L50,20)),"") | N50: =IF(L50>0,IF(INDEX('3 Catalogue outils'!$A$6:$AC$5005,L50,23)=0,"",INDEX('3 Catalogue outils'!$A$6:$AC$5005,L50,23)),"") | O50: =IF(L50>0,IF(INDEX('3 Catalogue outils'!$A$6:$AC$5005,L50,4)=0,"",INDEX('3 Catalogue outils'!$A$6:$AC$5005,L50,4)),"") | P50: =IF(L50>0,IF(INDEX('3 Catalogue outils'!$A$6:$AC$5005,L50,5)=0,"",INDEX('3 Catalogue outils'!$A$6:$AC$5005,L50,5)),"")
A51: =IF(OR(J51=0,K51=1),"",COUNTIF(K$15:K51,0)-COUNTIF(J$15:J51,0)) | C51: =IF(J51=0,"",IF(K51=1,UPPER(INDEX('2 Import devis'!$B$6:$B$29,J51)),IF(L51>0,TRIM(SUBSTITUTE(INDEX('3 Catalogue outils'!$A$6:$AC$5005,L51,2),CHAR(10)," ")),INDEX('2 Import devis'!$B$6:$B$29,J51)))) | D51: =IF(OR(J51=0,K51=1),"",1) | E51: =IF(OR(J51=0,K51=1),"",IF(L51>0,IF(N(INDEX('3 Catalogue outils'!$A$6:$AC$5005,L51,22))=0,IF(ISTEXT(INDEX('3 Catalogue outils'!$A$6:$AC$5005,L51,22)),INDEX('3 Catalogue outils'!$A$6:$AC$5005,L51,22),"FR"),"FR"),"FR")) | F51: =IF(L51>0,IF(N(INDEX('3 Catalogue outils'!$A$6:$AC$5005,L51,3))=0,"",ROUND(INDEX('3 Catalogue outils'!$A$6:$AC$5005,L51,3),1)),"") | G51: =IF(OR(D51="",INDEX('2 Import devis'!$G$6:$G$29,J51)=""),"",INDEX('2 Import devis'!$G$6:$G$29,J51)) | I51: =IF(J51=0,0,1) | J51: =IF(37>MAX('2 Import devis'!$L$6:$L$29),0,COUNTIF('2 Import devis'!$L$6:$L$29,"<"&37)+1) | K51: =IF(J51=0,0,IF(N(INDEX('2 Import devis'!$C$6:$C$29,J51))=0,1,0)) | L51: =IF(OR(J51=0,K51=1,B51=""),0,IFERROR(MATCH(B51,'3 Catalogue outils'!$A$6:$A$5005,0),0)) | M51: =IF(L51>0,IF(INDEX('3 Catalogue outils'!$A$6:$AC$5005,L51,20)=0,"",INDEX('3 Catalogue outils'!$A$6:$AC$5005,L51,20)),"") | N51: =IF(L51>0,IF(INDEX('3 Catalogue outils'!$A$6:$AC$5005,L51,23)=0,"",INDEX('3 Catalogue outils'!$A$6:$AC$5005,L51,23)),"") | O51: =IF(L51>0,IF(INDEX('3 Catalogue outils'!$A$6:$AC$5005,L51,4)=0,"",INDEX('3 Catalogue outils'!$A$6:$AC$5005,L51,4)),"") | P51: =IF(L51>0,IF(INDEX('3 Catalogue outils'!$A$6:$AC$5005,L51,5)=0,"",INDEX('3 Catalogue outils'!$A$6:$AC$5005,L51,5)),"")
A52: =IF(OR(J52=0,K52=1),"",COUNTIF(K$15:K52,0)-COUNTIF(J$15:J52,0)) | C52: =IF(J52=0,"",IF(K52=1,UPPER(INDEX('2 Import devis'!$B$6:$B$29,J52)),IF(L52>0,TRIM(SUBSTITUTE(INDEX('3 Catalogue outils'!$A$6:$AC$5005,L52,2),CHAR(10)," ")),INDEX('2 Import devis'!$B$6:$B$29,J52)))) | D52: =IF(OR(J52=0,K52=1),"",1) | E52: =IF(OR(J52=0,K52=1),"",IF(L52>0,IF(N(INDEX('3 Catalogue outils'!$A$6:$AC$5005,L52,22))=0,IF(ISTEXT(INDEX('3 Catalogue outils'!$A$6:$AC$5005,L52,22)),INDEX('3 Catalogue outils'!$A$6:$AC$5005,L52,22),"FR"),"FR"),"FR")) | F52: =IF(L52>0,IF(N(INDEX('3 Catalogue outils'!$A$6:$AC$5005,L52,3))=0,"",ROUND(INDEX('3 Catalogue outils'!$A$6:$AC$5005,L52,3),1)),"") | G52: =IF(OR(D52="",INDEX('2 Import devis'!$G$6:$G$29,J52)=""),"",INDEX('2 Import devis'!$G$6:$G$29,J52)) | I52: =IF(J52=0,0,1) | J52: =IF(38>MAX('2 Import devis'!$L$6:$L$29),0,COUNTIF('2 Import devis'!$L$6:$L$29,"<"&38)+1) | K52: =IF(J52=0,0,IF(N(INDEX('2 Import devis'!$C$6:$C$29,J52))=0,1,0)) | L52: =IF(OR(J52=0,K52=1,B52=""),0,IFERROR(MATCH(B52,'3 Catalogue outils'!$A$6:$A$5005,0),0)) | M52: =IF(L52>0,IF(INDEX('3 Catalogue outils'!$A$6:$AC$5005,L52,20)=0,"",INDEX('3 Catalogue outils'!$A$6:$AC$5005,L52,20)),"") | N52: =IF(L52>0,IF(INDEX('3 Catalogue outils'!$A$6:$AC$5005,L52,23)=0,"",INDEX('3 Catalogue outils'!$A$6:$AC$5005,L52,23)),"") | O52: =IF(L52>0,IF(INDEX('3 Catalogue outils'!$A$6:$AC$5005,L52,4)=0,"",INDEX('3 Catalogue outils'!$A$6:$AC$5005,L52,4)),"") | P52: =IF(L52>0,IF(INDEX('3 Catalogue outils'!$A$6:$AC$5005,L52,5)=0,"",INDEX('3 Catalogue outils'!$A$6:$AC$5005,L52,5)),"")
A53: =IF(OR(J53=0,K53=1),"",COUNTIF(K$15:K53,0)-COUNTIF(J$15:J53,0)) | C53: =IF(J53=0,"",IF(K53=1,UPPER(INDEX('2 Import devis'!$B$6:$B$29,J53)),IF(L53>0,TRIM(SUBSTITUTE(INDEX('3 Catalogue outils'!$A$6:$AC$5005,L53,2),CHAR(10)," ")),INDEX('2 Import devis'!$B$6:$B$29,J53)))) | D53: =IF(OR(J53=0,K53=1),"",1) | E53: =IF(OR(J53=0,K53=1),"",IF(L53>0,IF(N(INDEX('3 Catalogue outils'!$A$6:$AC$5005,L53,22))=0,IF(ISTEXT(INDEX('3 Catalogue outils'!$A$6:$AC$5005,L53,22)),INDEX('3 Catalogue outils'!$A$6:$AC$5005,L53,22),"FR"),"FR"),"FR")) | F53: =IF(L53>0,IF(N(INDEX('3 Catalogue outils'!$A$6:$AC$5005,L53,3))=0,"",ROUND(INDEX('3 Catalogue outils'!$A$6:$AC$5005,L53,3),1)),"") | G53: =IF(OR(D53="",INDEX('2 Import devis'!$G$6:$G$29,J53)=""),"",INDEX('2 Import devis'!$G$6:$G$29,J53)) | I53: =IF(J53=0,0,1) | J53: =IF(39>MAX('2 Import devis'!$L$6:$L$29),0,COUNTIF('2 Import devis'!$L$6:$L$29,"<"&39)+1) | K53: =IF(J53=0,0,IF(N(INDEX('2 Import devis'!$C$6:$C$29,J53))=0,1,0)) | L53: =IF(OR(J53=0,K53=1,B53=""),0,IFERROR(MATCH(B53,'3 Catalogue outils'!$A$6:$A$5005,0),0)) | M53: =IF(L53>0,IF(INDEX('3 Catalogue outils'!$A$6:$AC$5005,L53,20)=0,"",INDEX('3 Catalogue outils'!$A$6:$AC$5005,L53,20)),"") | N53: =IF(L53>0,IF(INDEX('3 Catalogue outils'!$A$6:$AC$5005,L53,23)=0,"",INDEX('3 Catalogue outils'!$A$6:$AC$5005,L53,23)),"") | O53: =IF(L53>0,IF(INDEX('3 Catalogue outils'!$A$6:$AC$5005,L53,4)=0,"",INDEX('3 Catalogue outils'!$A$6:$AC$5005,L53,4)),"") | P53: =IF(L53>0,IF(INDEX('3 Catalogue outils'!$A$6:$AC$5005,L53,5)=0,"",INDEX('3 Catalogue outils'!$A$6:$AC$5005,L53,5)),"")
A54: =IF(OR(J54=0,K54=1),"",COUNTIF(K$15:K54,0)-COUNTIF(J$15:J54,0)) | C54: =IF(J54=0,"",IF(K54=1,UPPER(INDEX('2 Import devis'!$B$6:$B$29,J54)),IF(L54>0,TRIM(SUBSTITUTE(INDEX('3 Catalogue outils'!$A$6:$AC$5005,L54,2),CHAR(10)," ")),INDEX('2 Import devis'!$B$6:$B$29,J54)))) | D54: =IF(OR(J54=0,K54=1),"",1) | E54: =IF(OR(J54=0,K54=1),"",IF(L54>0,IF(N(INDEX('3 Catalogue outils'!$A$6:$AC$5005,L54,22))=0,IF(ISTEXT(INDEX('3 Catalogue outils'!$A$6:$AC$5005,L54,22)),INDEX('3 Catalogue outils'!$A$6:$AC$5005,L54,22),"FR"),"FR"),"FR")) | F54: =IF(L54>0,IF(N(INDEX('3 Catalogue outils'!$A$6:$AC$5005,L54,3))=0,"",ROUND(INDEX('3 Catalogue outils'!$A$6:$AC$5005,L54,3),1)),"") | G54: =IF(OR(D54="",INDEX('2 Import devis'!$G$6:$G$29,J54)=""),"",INDEX('2 Import devis'!$G$6:$G$29,J54)) | I54: =IF(J54=0,0,1) | J54: =IF(40>MAX('2 Import devis'!$L$6:$L$29),0,COUNTIF('2 Import devis'!$L$6:$L$29,"<"&40)+1) | K54: =IF(J54=0,0,IF(N(INDEX('2 Import devis'!$C$6:$C$29,J54))=0,1,0)) | L54: =IF(OR(J54=0,K54=1,B54=""),0,IFERROR(MATCH(B54,'3 Catalogue outils'!$A$6:$A$5005,0),0)) | M54: =IF(L54>0,IF(INDEX('3 Catalogue outils'!$A$6:$AC$5005,L54,20)=0,"",INDEX('3 Catalogue outils'!$A$6:$AC$5005,L54,20)),"") | N54: =IF(L54>0,IF(INDEX('3 Catalogue outils'!$A$6:$AC$5005,L54,23)=0,"",INDEX('3 Catalogue outils'!$A$6:$AC$5005,L54,23)),"") | O54: =IF(L54>0,IF(INDEX('3 Catalogue outils'!$A$6:$AC$5005,L54,4)=0,"",INDEX('3 Catalogue outils'!$A$6:$AC$5005,L54,4)),"") | P54: =IF(L54>0,IF(INDEX('3 Catalogue outils'!$A$6:$AC$5005,L54,5)=0,"",INDEX('3 Catalogue outils'!$A$6:$AC$5005,L54,5)),"")
A55: TOTAL | D55: =SUM(D15:D54) | F55: =SUMPRODUCT(IF(ISNUMBER(D15:D54),D15:D54,0)*IF(ISNUMBER(F15:F54),F15:F54,0)) | G55: =SUMPRODUCT(IF(ISNUMBER(D15:D54),D15:D54,0)*IF(ISNUMBER(G15:G54),G15:G54,0))
A58: COLISAGE · PACKING (ensemble des articles)
A59: Colis · Package | B59: Type de colisage · Type | C59: Dimensions L × l × h (cm) | F59: Poids brut kg | G59: Volume m³
A60: Colis 1 | B60: Fishing basket | C60: 120 × 80 × 60 | F60: 145 | G60: 0.576
A61: Colis 2
A62: Colis 3
A63: ="TOTAL · "&COUNTA(B60:B62)&" colis" | F63: =SUM(F60:F62) | G63: =SUM(G60:G62)
A65: Marchandises reçues en bon état, à retourner à Enedril à la fin de la location · Goods received in good condition, to be returned to Enedril at the end of the rental
A66: EXPÉDITEUR · ENEDRIL Nom, date, signature | C66: TRANSPORTEUR Nom, date, signature | D66: RÉCEPTION CLIENT · RECEIVED BY Nom, date, signature, cachet

Sheet 2 Import devis
B1: IMPORT DU DEVIS
B2: Dans le classeur Devis, onglet « 2 Matériel » : copier les colonnes C à J (lignes 6 à 29) et les coller ici en B6. Seuls la description, la quantité et la valeur de remplacement passent sur le BL.
B5: Description | C5: Qté | D5: Stand-by | E5: Opér. | F5: UC | G5: Valeur remplac. (LIH / DBR) | H5: Inspection | I5: Restocking | K5: lignes BL | L5: cumul
B6: BHA #1 | K6: =IF(B6="",0,IF(N(C6)=0,1,MAX(1,INT(C6)))) | L6: =SUM(K$6:K6)
B7: Bit Sub 3-1/2" IF Box x 3-1/2" REG Box BF | C7: 1 | D7: 85 | E7: 120 | F7: 40 | G7: 4200 | H7: 150 | I7: 600 | K7: =IF(B7="",0,IF(N(C7)=0,1,MAX(1,INT(C7)))) | L7: =SUM(K$6:K7)
B8: Extension 11-3/4" FS | C8: 1 | D8: 20 | E8: 30 | F8: 10 | G8: 900 | H8: 60 | I8: 150 | K8: =IF(B8="",0,IF(N(C8)=0,1,MAX(1,INT(C8)))) | L8: =SUM(K$6:K8)
B9: Extension 3-7/8" SH | C9: 2 | D9: 20 | E9: 30 | F9: 10 | G9: 900 | H9: 60 | I9: 150 | K9: =IF(B9="",0,IF(N(C9)=0,1,MAX(1,INT(C9)))) | L9: =SUM(K$6:K9)
K10: =IF(B10="",0,IF(N(C10)=0,1,MAX(1,INT(C10)))) | L10: =SUM(K$6:K10)
K11: =IF(B11="",0,IF(N(C11)=0,1,MAX(1,INT(C11)))) | L11: =SUM(K$6:K11)
K12: =IF(B12="",0,IF(N(C12)=0,1,MAX(1,INT(C12)))) | L12: =SUM(K$6:K12)
K13: =IF(B13="",0,IF(N(C13)=0,1,MAX(1,INT(C13)))) | L13: =SUM(K$6:K13)
K14: =IF(B14="",0,IF(N(C14)=0,1,MAX(1,INT(C14)))) | L14: =SUM(K$6:K14)
K15: =IF(B15="",0,IF(N(C15)=0,1,MAX(1,INT(C15)))) | L15: =SUM(K$6:K15)
K16: =IF(B16="",0,IF(N(C16)=0,1,MAX(1,INT(C16)))) | L16: =SUM(K$6:K16)
K17: =IF(B17="",0,IF(N(C17)=0,1,MAX(1,INT(C17)))) | L17: =SUM(K$6:K17)
K18: =IF(B18="",0,IF(N(C18)=0,1,MAX(1,INT(C18)))) | L18: =SUM(K$6:K18)
K19: =IF(B19="",0,IF(N(C19)=0,1,MAX(1,INT(C19)))) | L19: =SUM(K$6:K19)
K20: =IF(B20="",0,IF(N(C20)=0,1,MAX(1,INT(C20)))) | L20: =SUM(K$6:K20)
K21: =IF(B21="",0,IF(N(C21)=0,1,MAX(1,INT(C21)))) | L21: =SUM(K$6:K21)
... K29: =IF(B29="",0,IF(N(C29)=0,1,MAX(1,INT(C29)))) | L29: =SUM(K$6:K29)
B31: Colonnes grises : tarifs, non repris sur le BL (le BL peut être envoyé au transporteur et au client sans les prix de location).

Sheet 3 Catalogue outils
A1: CATALOGUE OUTILS
A2: Dans le registre « Fabrication - Achat - 2014 et + » : copier les colonnes Z à BB (à partir de la ligne 2) et les coller ici en A6. Le BL cherche le N° de série (colonne A) et reprend désignation, poids, référence, origine, code SH, OD et longueur.
A4: Registre repris du lien de l'ancien BL : 2955 N° de série (dernière mise à jour connue). À remplacer par un nouveau copier-coller Z:BB quand le registre évolue.
A5: N° de série | B5: Désignation | C5: Poids net (kg) | D5: OD | E5: Longueur (mm) | F5: col. 6 | G5: col. 7 | H5: col. 8 | I5: col. 9 | J5: col. 10 | K5: col. 11 | L5: col. 12 | M5: col. 13 | N5: col. 14 | O5: col. 15 | P5: col. 16 | Q5: col. 17 | R5: col. 18 | S5: col. 19 | T5: Référence | U5: col. 21 | V5: Origine | W5: Code SH (HS) | X5: col. 24 | Y5: col. 25 | Z5: col. 26 | AA5: col. 27 | AB5: col. 28 | AC5: col. 29
A6: 2030001
A7: 2030002
A8: 10 | B8: Loading Basket 4200mm x 1200mm L | C8: 780 | D8: 1200 | E8: 4200 | T8: 5 | V8: FR | W8: 86090090
A9: 11 | B9: Loading Basket 4200mm x 1200mm L | C9: 780 | D9: 1200 | E9: 4200 | T9: 6 | V9: FR | W9: 86090090
A10: 12 | B10: Loading Basket 3200mm x 1200mm M | C10: 500 | D10: 1200 | E10: 3200 | T10: 11 | V10: FR | W10: 86090090
A11: 13 | B11: Loading Basket 3200mm x 1200mm M | C11: 500 | D11: 1200 | E11: 3200 | T11: 12 | V11: FR | W11: 86090090
A12: 14 | B12: Loading Basket 2200mm x 1200mm S | C12: 400 | D12: 1200 | E12: 2200 | T12: 13 | V12: FR | W12: 86090090
A13: 15 | B13: Loading Basket 2200mm x 1200mm S | C13: 400 | D13: 1200 | E13: 2200 | T13: 14 | V13: FR | W13: 86090090
A14: "1" | B14: Bac à boue | V14: FR
A15: "2" | B15: Bac à boue | V15: FR
A16: 1013-02237 | B16: Wachs Machine to cut form 7" to 9-5/8" csg
A17: 3020003 | B17: DTU 8200 4-1/2" REG Pin up x 4-1/2" REG Box down | C17: 308 | D17: 8200 | E17: 1880 | T17: 8 | V17: FR
A18: 2050004 | B18: Section Mill 5500 3-1/2" REG Pin up | C18: 170 | D18: 5500 | E18: 1280 | T18: 8 | V18: FR
A19: 2050005 | B19: Section Mill 5500 3-1/2" REG Pin up | C19: 170 | D19: 5500 | E19: 1955 | T19: 9 | V19: FR
A20: 2050006 | B20: Section Mill 8200 4-1/2" REG Pin up | C20: 426 | D20: 8200 | E20: 2380 | T20: 10 | V20: FR
A21: 8020007 | B21: Bit Sub 4-1/2" IF Box x 4-1/2" REG Box BF | C21: 88.141396 | D21: 6.5 | E21: 600 | T21: 50 | V21: FR
A22: 8020008 | B22: Bit Sub 3-1/2" IF Box x 3-1/2" REG Box BF | C22: 34.664011 | D22: 4.75 | E22: 450 | T22: 36 | V22: FR
A23: 8020009 | B23: Bit Sub 2-3/8" IF Box x 2-3/8" REG Box BF | C23: 17.776416 | D23: 3.5 | E23: 400 | T23: 73
A24: 8130010 | B24: XO 3-1/2" EU Pin x 3-1/2" IF Box | C24: 23.841384 | D24: 4.75 | E24: 445 | T24: 100 | V24: FR
A25: 8130011 | B25: XO 2-7/8" EU Pin x 2-3/8" REG Box | C25: 10.094288 | D25: 3.125 | E25: 340 | T25: 68 | V25: FR
A26: 8130012 | B26: XO 2-7/8" EU Pin x 3-1/2" IF Box | C26: 31.108728 | D26: 4.75 | E26: 450 | T26: 76 | V26: FR
A27: 8130013 | B27: XO 2-3/8" EU Pin x 2-3/8" REG Box | C27: 12.702731 | D27: 3.5 | E27: 350 | T27: 14 | V27: FR
A28: 8130014 | B28: XO 2-3/8" EU Pin x 2-7/8" IF Box | C28: 19.291732 | D28: 4.125 | E28: 350 | T28: 15 | V28: FR
A29: 8130015
A30: 8130016 | B30: XO 6-5/8" REG Pin x 7-5/8" REG Box | C30: 101.6811 | D30: 9.5 | E30: 330 | T30: 215 | V30: FR
A31: 8130017 | B31: XO 2-3/8" REG Pin x 2-7/8" EU Box | C31: 17.776416 | D31: 3.5 | E31: 400 | T31: 50 | V31: FR
A32: 8135406 | B32: XO 3-1/2" REG Pin x 3-1/2" REG Pin | C32: 17.776416 | D32: 4.5 | E32: 250 | T32: 135 | V32: FR
A33: 8130019 | B33: XO 2-3/8" REG Pin x 2-3/8" IF Box BF | C33: 16.418495 | D33: 3.375 | E33: 400 | T33: 46 | V33: FR
A34: 8130020 | B34: XO 2-3/8" REG Pin x 2-3/8" REG Pin | C34: 17.776416 | D34: 3.5 | E34: 400 | T34: 49 | V34: FR
A35: 8080021 | B35: Float Sub 6-1/2" Lg 585 mm 4-1/2" IF Pin x 4-1/2" IF Box BF (4R) | C35: 78 | D35: 6.5 | E35: 585 | T35: 16 | V35: FR
A36: 8130022 | B36: XO 3-1/2" IF Pin x 3-1/2" REG Pin | C36: 35.930581 | D36: 4.75 | E36: 490 | T36: 120 | V36: FR
A37: 8130023 | B37: XO 3-1/2" IF Pin x 3-1/2" IF Pin | C37: 32.219754 | D37: 4.75 | E37: 500 | T37: 114 | V37: FR
A38: 8130024 | B38: XO 2-3/8" IF Pin x 2-3/8" REG Pin | C38: 17.776416 | D38: 3.5 | E38: 400 | T38: 26 | V38: FR
A39: 8130025
A40: 8130026 | B40: XO 2-3/8" IF Pin x 2-3/8" IF Pin | C40: 15.801259 | D40: 3.5 | E40: 400 | T40: 19 | V40: FR
A41: 8130027
A42: 1060028 | B42: Impression block 4 1/2" OD 2-3/8" REG Box | C42: 28 | D42: 4.5 | E42: 530 | T42: 8 | V42: FR
A43: 8130029 | B43: XO 3-1/2" IF Pin x 3-1/2" REG Pin | C43: 36.910753 | D43: 4.75 | E43: 460 | T43: 118 | V43: FR
A44: 5170030 | B44: WO Junk Catcher w/ saver sub 4-1/2" FJWP Pin x Box | C44: 26 | D44: 4.625 | E44: 500 | T44: 5 | V44: FR
A45: 5120031 | B45: WO Top Sub 2-7/8" EU Box x 4-1/2" FJWP Pin | C45: 16 | D45: 4.5 | E45: 420 | T45: 18 | V45: FR
A46: 5120032 | B46: WO Top Sub 3-1/2" IF Box x 5-3/8" BRS Pin | C46: 52 | D46: 5.375 | E46: 580 | T46: 19
A47: 5120033 | B47: WO Top Sub 2-7/8" EU Box x 4-1/2" FJWP Pin
A48: 8130034 | B48: XO 2-7/8" EU Pin x 2-7/8" IF Box | C48: 16 | D48: 4.0625 | E48: 445 | T48: 74 | V48: FR
A49: 8130035 | B49: XO 2-7/8" IF Pin x 2-7/8" EU Box | C49: 38.515568 | D49: 4.75 | E49: 480 | T49: 81 | V49: FR
A50: 8020036 | B50: Bit Sub 2-3/8" IF Box x 3-1/2" REG Box | C50: 18 | D50: 4.125 | E50: 500 | T50: 11 | V50: FR
A51: 8130037 | B51: XO 2-7/8" REG Pin x 2-3/8" REG Box | C51: 20 | D51: 3.75 | E51: 500 | T51: 90 | V51: FR
A52: 8130038 | B52: XO 2-3/8" REG Pin x 2-7/8" REG Box | C52: 22 | D52: 3.75 | E52: 515 | T52: 53 | V52: FR
A53: 8020039 | B53: Bit Sub 2-3/8" REG Box x 2-3/8" REG Box | C53: 11.875634 | D53: 3.125 | E53: 400 | T53: 13 | V53: FR
A54: 8130040 | B54: XO 2-7/8" EU Pin x 2-3/8" REG Box | C54: 10.242734 | D54: 3.125 | E54: 345 | T54: 67
A55: 5120041
A56: 5100042 | B56: WO Pipe 4-1/2" FJWP Pin x Box | C56: 0 | D56: 4.5 | E56: 0 | T56: 22 | V56: n° réattribué
A57: 5100043 | B57: WO Pipe 4-1/2" FJWP Pin x Box | C57: 0 | D57: 4.5 | E57: 0 | T57: 23 | V57: n° réattribué
A58: 5100044 | B58: WO Pipe 4-1/2" FJWP Pin x Box | C58: 0 | D58: 4.5 | E58: 0 | T58: 24 | V58: n° réattribué
A59: 5100045 | B59: WO Pipe 4-1/2" FJWP Pin x Box | C59: 0 | D59: 4.5 | E59: 0 | T59: 25 | V59: n° réattribué
A60: 5090046 | B60: WO Extension Lg 2007 mm 4-1/2" FJWP Pin x Box | C60: 64 | D60: 4.5 | E60: 2007 | T60: 34 | V60: FR
A61: 5090047 | B61: WO Extension Lg 1960 mm 4-1/2" FJWP Pin x Box | C61: 47 | D61: 4.5 | E61: 1960 | T61: 31 | V61: FR
A62: 5090048 | B62: WO Extension Lg 2000 mm 4-1/2" FJWP Pin x Box | C62: 47 | D62: 4.5 | E62: 2000 | T62: 32 | V62: FR
A63: 5170049
A64: 5110050 | B64: WO Shoe 4-1/2" FJWP Box | C64: 7.6660794 | D64: flush | E64: 600 | T64: 48 | V64: FR
A65: 5110051
A66: 5110052
A67: 5110053
A68: 5110054
A69: 5170055 | B69: WO Junk Catcher 4-1/2" FJWP Pin x Box | C69: 22 | D69: 4.5 | E69: 505 | T69: 6 | V69: FR
A70: 5150056 | B70: WO Lift Plug 4-1/2" FJWP Pin | C70: 8 | D70: 6 | T70: 6 | V70: FR
A71: 8130057 | B71: XO 2-7/8" REG Pin x 3-1/2" REG Box | C71: 20.622494 | D71: 4 | E71: 370 | T71: 95 | V71: FR
A72: 3010058 | B72: RTU 5700 3-1/2" IF Box up | C72: 156 | D72: 5700 | E72: 1870 | T72: 7 | V72: FR
A73: 8130059 | B73: XO 7-5/8" REG Pin x 6-5/8" REG Box | C73: 104.76235 | D73: 9.5 | E73: 340 | T73: 226 | V73: FR
A74: 8130060 | B74: XO 6-5/8" REG Pin x 7-5/8" REG Box | C74: 104.76235 | D74: 9.5 | E74: 340 | T74: 216 | V74: FR
A75: 8130061 | B75: XO 2-3/8" IF Pin x 2-7/8" EU Box | C75: 13.546691 | D75: 3.668 | E75: 330 | T75: 31 | V75: FR
A76: 4040062 | B76: Intensifier 6-1/2" OD 4-1/2" IF Pin x Box | C76: 460 | D76: 6.5 | E76: 3940 | T76: 12
A77: 4040063
A78: 4040064
A79: 4030065
A80: 4030066 | B80: Jar Z 6-1/4" OD 4-1/2" IF Pin down x Box up | C80: 300 | D80: 6.25 | E80: 2385 | T80: 17
A81: (4030067)
A82: 4030067 | B82: Jar Z 6-1/4" OD 4-1/2" IF Pin down x Box up | C82: 300 | D82: 6.25 | E82: 2385 | T82: 18
A83: 4030068
A84: 4030069
A85: 4030070
A86: 4030070 | B86: Jar Z 3-1/8" 2-3/8" REG Pin down x Box up | C86: 58 | D86: 3.125 | E86: 1900 | T86: 5
A87: 4030071 | B87: Jar Z 3-1/8" 2-3/8" REG Pin down x Box up | C87: 60 | D87: 3.125 | E87: 1900 | T87: 6
A88: 4020072 | B88: Bumper Sub 8" OD 6-5/8" REG Pin down x Box up | C88: 277 | D88: 7.75 | E88: 1580 | T88: 23
A89: 4020073 | B89: Bumper Sub 6-1/4" OD 4-1/2" IF Pin down x Box up | C89: 157 | D89: 6.25 | E89: 1420 | T89: 16
A90: 4020074 | B90: Bumper Sub 6-1/4" OD 4-1/2" IF Pin down x Box up | C90: 157 | D90: 6.25 | E90: 1420 | T90: 17
A91: 4020075
A92: 4020075 | B92: Bumper Sub 4-3/4" OD 3-1/2" IF Pin down x Box up | C92: 98 | D92: 4.75 | E92: 1455 | T92: 11
A93: 4020076
A94: 4020077
A95: 4020078
A96: 7040079
A97: 7120080 | B97: Releasing Spear 8-1/4" OD Mandrel CA 9281 6-5/8" REG Box | C97: 230 | D97: 8.25 | E97: CA 9281 | T97: 30
A98: 7120081 | B98: Releasing Spear 2-13/16" OD Mandrel CA 9410 2-3/8" REG Box | C98: 24 | D98: 2.8125 | E98: CA 9410 | T98: 13
A99: 7120082
A100: 7040083 | B100: 3-7/8" XSH Overshot - CA 21300 2-3/8" REG Box | C100: 18 | D100: 3-7/8" XSH | E100: 822 | T100: 13
A101: 7040084 | B101: 8-1/8" SH Overshot - CA 9217 4-1/2" IF Box | C101: 96 | D101: 8-1/8" SH | E101: 1250 | T101: 65
...

Sheet Listes
A1: Type de colisage
A2: Palette
A3: Fishing basket
A4: Caisse
A5: Vrac
