Workbook

Sheet Tableau de bord
B1: Plan marketing et communication 2026
B2: Enedril · tableau de bord LinkedIn, calendrier et salons. Tout se met à jour depuis les autres onglets.
B6: ABONNÉS LINKEDIN | E6: NOUVEAUX ABONNÉS 2026 | H6: POSTS PUBLIÉS 2026 | K6: IMPRESSIONS
B7: ='Abonnés LinkedIn'!R11 | E7: ='Abonnés LinkedIn'!R12 | H7: =COUNTIF('Posts LinkedIn'!$F$7:$F$66,"Publié") | K7: ='Posts LinkedIn'!H5
B9: =TEXT('Abonnés LinkedIn'!R17,"0%")&" de l'objectif ("&TEXT('Abonnés LinkedIn'!R15,"#,##0")&")" | E9: =IFERROR(TEXT('Abonnés LinkedIn'!R20,"+0%;-0%")&" vs même période 2025","") | H9: =COUNTIF('Posts LinkedIn'!$F$7:$F$66,"Planifié")&" planifiés · "&TEXT(COUNTIF('Posts LinkedIn'!$F$7:$F$66,"Publié")/MAX(MONTH(TODAY()),1),"0.0")&" posts / mois" | K9: =TEXT('Posts LinkedIn'!H5/MAX(COUNTIF('Posts LinkedIn'!$F$7:$F$66,"Publié"),1),"#,##0")&" par post en moyenne"
B11: ENGAGEMENTS | E11: TAUX D'ENGAGEMENT | H11: BUDGET PUBLICITAIRE | K11: PARTAGES
B12: ='Posts LinkedIn'!I5 | E12: ='Posts LinkedIn'!J5 | H12: ='Posts LinkedIn'!P5 | K12: ='Posts LinkedIn'!O5
B14: =TEXT('Posts LinkedIn'!M5,"#,##0")&" réactions · "&'Posts LinkedIn'!N5&" commentaires" | E14: =IFERROR("Taux de clics : "&TEXT('Posts LinkedIn'!L5,"0.0%"),"") | H14: =IFERROR("Coût : "&TEXT('Posts LinkedIn'!Q5,"0.00")&" € / 1000 impressions","") | K14: =TEXT('Posts LinkedIn'!K5,"#,##0")&" clics au total"
B16: MEILLEUR TAUX D'ENGAGEMENT | E16: POST LE PLUS VU | H16: SALONS RÉALISÉS | K16: À COMPLÉTER
B17: =IFERROR(INDEX('Posts LinkedIn'!$B$7:$B$66,MATCH(MAX('Posts LinkedIn'!$J$7:$J$66),'Posts LinkedIn'!$J$7:$J$66,0)),"") | E17: =IFERROR(INDEX('Posts LinkedIn'!$B$7:$B$66,MATCH(MAX('Posts LinkedIn'!$H$7:$H$66),'Posts LinkedIn'!$H$7:$H$66,0)),"") | H17: =COUNTIFS(Salons!$C$7:$C$40,"Salon",Salons!$E$7:$E$40,"Réalisé") | K17: =COUNTIFS('Posts LinkedIn'!$F$7:$F$66,"Publié",'Posts LinkedIn'!$H$7:$H$66,"")+COUNTIFS('Posts LinkedIn'!$F$7:$F$66,"Publié",'Posts LinkedIn'!$I$7:$I$66,"")
B19: =IFERROR(TEXT(MAX('Posts LinkedIn'!$J$7:$J$66),"0%")&" d'engagement","") | E19: =TEXT(MAX('Posts LinkedIn'!$H$7:$H$66),"#,##0")&" impressions" | H19: =COUNTIFS(Salons!$C$7:$C$40,"Salon",Salons!$E$7:$E$40,"Confirmé")&" salons à venir" | K19: posts publiés sans statistiques
B68: ÉVOLUTION ANNUELLE
B69: Indicateur | D69: 2024 | E69: 2025 | F69: 2026 (à date) | G69: Évol. 24→25 | H69: Évol. 25→26
B70: Posts publiés | D70: 29 | E70: 35 | F70: =COUNTIF('Posts LinkedIn'!$F$7:$F$66,"Publié") | G70: =IFERROR(E70/D70-1,"") | H70: =IFERROR(F70/E70-1,"")
B71: Impressions | D71: 187339 | E71: 648545 | F71: ='Posts LinkedIn'!H5 | G71: =IFERROR(E71/D71-1,"") | H71: =IFERROR(F71/E71-1,"")
B72: Engagements | D72: 27672 | E72: 27877 | F72: ='Posts LinkedIn'!I5 | G72: =IFERROR(E72/D72-1,"") | H72: =IFERROR(F72/E72-1,"")
B73: Taux d'engagement | D73: =D72/D71 | E73: =E72/E71 | F73: =F72/F71 | G73: =IFERROR((E73-D73)*100,"") | H73: =IFERROR((F73-E73)*100,"")
B74: Clics | D74: 17886 | E74: 20958 | F74: ='Posts LinkedIn'!K5 | G74: =IFERROR(E74/D74-1,"") | H74: =IFERROR(F74/E74-1,"")
B75: Taux de clics | D75: =D74/D71 | E75: =E74/E71 | F75: =F74/F71 | G75: =IFERROR((E75-D75)*100,"") | H75: =IFERROR((F75-E75)*100,"")
B76: Réactions | D76: 1882 | E76: 2675 | F76: ='Posts LinkedIn'!M5 | G76: =IFERROR(E76/D76-1,"") | H76: =IFERROR(F76/E76-1,"")
B77: Commentaires | D77: 96 | E77: 167 | F77: ='Posts LinkedIn'!N5 | G77: =IFERROR(E77/D77-1,"") | H77: =IFERROR(F77/E77-1,"")
B78: Partages | D78: 50 | E78: 96 | F78: ='Posts LinkedIn'!O5 | G78: =IFERROR(E78/D78-1,"") | H78: =IFERROR(F78/E78-1,"")
B79: Budget (€) | D79: 960 | E79: 2500 | F79: ='Posts LinkedIn'!P5 | G79: =IFERROR(E79/D79-1,"") | H79: =IFERROR(F79/E79-1,"")
B81: 2026 est comparé à des années complètes : les évolutions 25→26 augmenteront avec les derniers mois. Valeurs 2024 et 2025 saisies à la main (cellules bleues).

Sheet Calendrier
B1: Calendrier éditorial 2026
B2: LinkedIn, blog et événements mois par mois. Le mois en cours est surligné.
C6: Janvier | D6: Février | E6: Mars | F6: Avril | G6: Mai | H6: Juin | I6: Juillet | J6: Août | K6: Septembre | L6: Octobre | M6: Novembre | N6: Décembre
B7: Posts prévus | C7: 3 | D7: 4 | E7: 3 | F7: 3 | G7: 3 | H7: 4 | I7: 3 | J7: 3 | K7: 3 | L7: 3 | M7: 3 | N7: 4
B8: Posts publiés | C8: =COUNTIFS('Posts LinkedIn'!$D$7:$D$66,COLUMN()-2,'Posts LinkedIn'!$F$7:$F$66,"Publié") | D8: =COUNTIFS('Posts LinkedIn'!$D$7:$D$66,COLUMN()-2,'Posts LinkedIn'!$F$7:$F$66,"Publié") | E8: =COUNTIFS('Posts LinkedIn'!$D$7:$D$66,COLUMN()-2,'Posts LinkedIn'!$F$7:$F$66,"Publié") | F8: =COUNTIFS('Posts LinkedIn'!$D$7:$D$66,COLUMN()-2,'Posts LinkedIn'!$F$7:$F$66,"Publié") | G8: =COUNTIFS('Posts LinkedIn'!$D$7:$D$66,COLUMN()-2,'Posts LinkedIn'!$F$7:$F$66,"Publié") | H8: =COUNTIFS('Posts LinkedIn'!$D$7:$D$66,COLUMN()-2,'Posts LinkedIn'!$F$7:$F$66,"Publié") | I8: =COUNTIFS('Posts LinkedIn'!$D$7:$D$66,COLUMN()-2,'Posts LinkedIn'!$F$7:$F$66,"Publié") | J8: =COUNTIFS('Posts LinkedIn'!$D$7:$D$66,COLUMN()-2,'Posts LinkedIn'!$F$7:$F$66,"Publié") | ... N8: =COUNTIFS('Posts LinkedIn'!$D$7:$D$66,COLUMN()-2,'Posts LinkedIn'!$F$7:$F$66,"Publié")
B9: Écart | C9: =IF(COLUMN()-2>MONTH(TODAY()),"",C8-C7) | D9: =IF(COLUMN()-2>MONTH(TODAY()),"",D8-D7) | E9: =IF(COLUMN()-2>MONTH(TODAY()),"",E8-E7) | F9: =IF(COLUMN()-2>MONTH(TODAY()),"",F8-F7) | G9: =IF(COLUMN()-2>MONTH(TODAY()),"",G8-G7) | H9: =IF(COLUMN()-2>MONTH(TODAY()),"",H8-H7) | I9: =IF(COLUMN()-2>MONTH(TODAY()),"",I8-I7) | J9: =IF(COLUMN()-2>MONTH(TODAY()),"",J8-J7) | ... N9: =IF(COLUMN()-2>MONTH(TODAY()),"",N8-N7)
B10: Impressions | C10: =SUMIFS('Posts LinkedIn'!$H$7:$H$66,'Posts LinkedIn'!$D$7:$D$66,COLUMN()-2) | D10: =SUMIFS('Posts LinkedIn'!$H$7:$H$66,'Posts LinkedIn'!$D$7:$D$66,COLUMN()-2) | E10: =SUMIFS('Posts LinkedIn'!$H$7:$H$66,'Posts LinkedIn'!$D$7:$D$66,COLUMN()-2) | F10: =SUMIFS('Posts LinkedIn'!$H$7:$H$66,'Posts LinkedIn'!$D$7:$D$66,COLUMN()-2) | G10: =SUMIFS('Posts LinkedIn'!$H$7:$H$66,'Posts LinkedIn'!$D$7:$D$66,COLUMN()-2) | H10: =SUMIFS('Posts LinkedIn'!$H$7:$H$66,'Posts LinkedIn'!$D$7:$D$66,COLUMN()-2) | I10: =SUMIFS('Posts LinkedIn'!$H$7:$H$66,'Posts LinkedIn'!$D$7:$D$66,COLUMN()-2) | J10: =SUMIFS('Posts LinkedIn'!$H$7:$H$66,'Posts LinkedIn'!$D$7:$D$66,COLUMN()-2) | ... N10: =SUMIFS('Posts LinkedIn'!$H$7:$H$66,'Posts LinkedIn'!$D$7:$D$66,COLUMN()-2)
B11: Engagements | C11: =SUMIFS('Posts LinkedIn'!$I$7:$I$66,'Posts LinkedIn'!$D$7:$D$66,COLUMN()-2) | D11: =SUMIFS('Posts LinkedIn'!$I$7:$I$66,'Posts LinkedIn'!$D$7:$D$66,COLUMN()-2) | E11: =SUMIFS('Posts LinkedIn'!$I$7:$I$66,'Posts LinkedIn'!$D$7:$D$66,COLUMN()-2) | F11: =SUMIFS('Posts LinkedIn'!$I$7:$I$66,'Posts LinkedIn'!$D$7:$D$66,COLUMN()-2) | G11: =SUMIFS('Posts LinkedIn'!$I$7:$I$66,'Posts LinkedIn'!$D$7:$D$66,COLUMN()-2) | H11: =SUMIFS('Posts LinkedIn'!$I$7:$I$66,'Posts LinkedIn'!$D$7:$D$66,COLUMN()-2) | I11: =SUMIFS('Posts LinkedIn'!$I$7:$I$66,'Posts LinkedIn'!$D$7:$D$66,COLUMN()-2) | J11: =SUMIFS('Posts LinkedIn'!$I$7:$I$66,'Posts LinkedIn'!$D$7:$D$66,COLUMN()-2) | ... N11: =SUMIFS('Posts LinkedIn'!$I$7:$I$66,'Posts LinkedIn'!$D$7:$D$66,COLUMN()-2)
B12: Thèmes LinkedIn | C12: • Vœux 2026 • Positionnement Enedril dans l'énergie • Focus expertise : forage et intervention sur puits | D12: • Post pédagogique : rôle de la géothermie aujourd’hui • Focus compétence technique clé • Coulisses terrain / équipes • Geotherm | E12: • Journée mondiale de l’eau (22/03) • Retour d’expérience chantier • Sécurité, qualité et standards | F12: • Journée de la Terre (22/04) • Typologie de projet géothermie • Focus métiers & savoir-faire • WPC Energy Congress (World Petroleum Congress) | G12: • Expertise sous-sol / performance forage • Innovation, méthodes, amélioration continue • Vie d’entreprise (sobre) • World Hydrogen Summit & Exhibition | H12: • Bilan mi-année • Cas d’usage / retour client • Impact environnemental / RSE • Geodays | I12: • Photo terrain / chantier • 14 juillet • Équipe en action | J12: • Activité estivale / préparation projets • Post pédagogique simple • Coulisses (léger mais pro) | K12: • Reprise & projets en cours • Expertise technique approfondie • Organisation projet / coordination | L12: • Journée mondiale de l’énergie (16/10) • Focus géothermie : bénéfices concrets • Octobre rose | M12: • Vision marché & enjeux énergie • Retour terrain / expertise spécifique • Movember • ADIPEC 2026 | N12: • Rétrospective projets • Mise en avant des équipes • Clôture d’année • Organiser un goûter dans une école
B13: Blog | C13: À planifier | D13: À planifier | E13: À planifier | F13: À planifier | G13: À planifier | H13: À planifier | I13: À planifier | J13: À planifier | K13: À planifier | L13: À planifier | M13: À planifier | N13: À planifier
B14: Salons et événements | D14: • Journées de la Géothermie | E14: • Think GeoEnergy | F14: • GeoRin • WPC Energy Congress (World Petroleum Congress) | G14: • World Hydrogen Summit & Exhibition | H14: • Geodays | L14: • Journée mondiale de l’énergie (16/10) • Octobre rose | M14: • Movember • ADIPEC 2026

Sheet Posts LinkedIn
B1: Posts LinkedIn 2026
B2: Saisissez uniquement les cellules en bleu : taux, coûts et mois se calculent tout seuls.
B5: Total publiés | F5: =COUNTIF(F7:F66,"Publié")&" posts" | G5: =SUM(G7:G66) | H5: =SUM(H7:H66) | I5: =SUM(I7:I66) | J5: =IFERROR(I5/H5,"") | K5: =SUM(K7:K66) | L5: =IFERROR(K5/H5,"") | M5: =SUM(M7:M66) | N5: =SUM(N7:N66) | O5: =SUM(O7:O66) | P5: =SUM(P7:P66) | Q5: =IFERROR(P5/SUMIFS(H7:H66,P7:P66,">0")*1000,"")
A6: N° | B6: Post | C6: Date | D6: Mois | E6: Type | F6: Statut | G6: Vues vidéo | H6: Impressions | I6: Engagements | J6: Taux d'engagement | K6: Clics | L6: Taux de clics | M6: Réactions | N6: Commentaires | O6: Partages | P6: Budget (€) | Q6: Coût / 1000 impr.
A7: 1 | B7: Vœux 2026 | C7: 46028 | D7: =IF(C7="","",MONTH(C7)) | E7: Post | F7: Publié | H7: 1525 | I7: 87 | J7: =IF(AND(H7>0,I7<>""),I7/H7,"") | K7: 34 | L7: =IF(AND(H7>0,K7<>""),K7/H7,"") | M7: 52 | N7: 1 | O7: 0 | P7: 0 | Q7: =IF(AND(N(P7)>0,N(H7)>0),P7/H7*1000,"")
A8: 2 | B8: Arrivée Koen | C8: 46063 | D8: =IF(C8="","",MONTH(C8)) | E8: Post | F8: Publié | H8: 4120 | I8: 348 | J8: =IF(AND(H8>0,I8<>""),I8/H8,"") | K8: 258 | L8: =IF(AND(H8>0,K8<>""),K8/H8,"") | M8: 81 | N8: 9 | O8: 0 | P8: 0 | Q8: =IF(AND(N(P8)>0,N(H8)>0),P8/H8*1000,"")
A9: 3 | B9: Annonce présence GeoTHERM | C9: 46073 | D9: =IF(C9="","",MONTH(C9)) | E9: Post | F9: Publié | H9: 945 | I9: 114 | J9: =IF(AND(H9>0,I9<>""),I9/H9,"") | K9: 60 | L9: =IF(AND(H9>0,K9<>""),K9/H9,"") | M9: 46 | N9: 7 | O9: 1 | P9: 0 | Q9: =IF(AND(N(P9)>0,N(H9)>0),P9/H9*1000,"")
A10: 4 | B10: Enedril au GeoTHERM | C10: 46079 | D10: =IF(C10="","",MONTH(C10)) | E10: Post | F10: Publié | H10: 5339 | I10: 1211 | J10: =IF(AND(H10>0,I10<>""),I10/H10,"") | K10: 1043 | L10: =IF(AND(H10>0,K10<>""),K10/H10,"") | M10: 158 | N10: 6 | O10: 4 | P10: 0 | Q10: =IF(AND(N(P10)>0,N(H10)>0),P10/H10*1000,"")
A11: 5 | B11: DTS350 | C11: 46093 | D11: =IF(C11="","",MONTH(C11)) | E11: Vidéo | F11: Publié | G11: 3196 | H11: 6252 | I11: 642 | J11: =IF(AND(H11>0,I11<>""),I11/H11,"") | K11: 515 | L11: =IF(AND(H11>0,K11<>""),K11/H11,"") | M11: 120 | N11: 2 | P11: 0 | Q11: =IF(AND(N(P11)>0,N(H11)>0),P11/H11*1000,"")
A12: 6 | B12: Performance Kem One | C12: 46105 | D12: =IF(C12="","",MONTH(C12)) | E12: Post | F12: Publié | H12: 7985 | I12: 2196 | J12: =IF(AND(H12>0,I12<>""),I12/H12,"") | K12: 2049 | L12: =IF(AND(H12>0,K12<>""),K12/H12,"") | M12: 132 | N12: 13 | O12: 2 | P12: 0 | Q12: =IF(AND(N(P12)>0,N(H12)>0),P12/H12*1000,"")
A13: 7 | B13: Junk Mill GMX 10 | C13: 46114 | D13: =IF(C13="","",MONTH(C13)) | E13: Post | F13: Publié | H13: 2665 | I13: 955 | J13: =IF(AND(H13>0,I13<>""),I13/H13,"") | K13: 876 | L13: =IF(AND(H13>0,K13<>""),K13/H13,"") | M13: 75 | N13: 3 | O13: 1 | P13: 0 | Q13: =IF(AND(N(P13)>0,N(H13)>0),P13/H13*1000,"")
A14: 8 | B14: HIRING : Assistante comptable | C14: 46125 | D14: =IF(C14="","",MONTH(C14)) | E14: Post | F14: Publié | H14: 1338 | I14: 101 | J14: =IF(AND(H14>0,I14<>""),I14/H14,"") | K14: 75 | L14: =IF(AND(H14>0,K14<>""),K14/H14,"") | M14: 18 | N14: 0 | O14: 8 | P14: 0 | Q14: =IF(AND(N(P14)>0,N(H14)>0),P14/H14*1000,"")
A15: 9 | B15: Post 4000 abonnés | C15: 46135 | D15: =IF(C15="","",MONTH(C15)) | E15: Post | F15: Publié | H15: 22024 | I15: 168 | J15: =IF(AND(H15>0,I15<>""),I15/H15,"") | K15: 97 | L15: =IF(AND(H15>0,K15<>""),K15/H15,"") | M15: 60 | N15: 2 | O15: 6 | P15: 200 | Q15: =IF(AND(N(P15)>0,N(H15)>0),P15/H15*1000,"")
A16: 10 | B16: Cartes Jobs paris Geothermie | C16: 46163 | D16: =IF(C16="","",MONTH(C16)) | E16: Post | F16: Publié | H16: 2447 | I16: 268 | J16: =IF(AND(H16>0,I16<>""),I16/H16,"") | K16: 166 | L16: =IF(AND(H16>0,K16<>""),K16/H16,"") | M16: 93 | N16: 4 | O16: 5 | P16: 0 | Q16: =IF(AND(N(P16)>0,N(H16)>0),P16/H16*1000,"")
A17: 11 | B17: Annonce Geodays | C17: 46184 | D17: =IF(C17="","",MONTH(C17)) | E17: Post | F17: Publié | H17: 883 | I17: 42 | J17: =IF(AND(H17>0,I17<>""),I17/H17,"") | K17: 10 | L17: =IF(AND(H17>0,K17<>""),K17/H17,"") | M17: 31 | N17: 0 | O17: 1 | P17: 0 | Q17: =IF(AND(N(P17)>0,N(H17)>0),P17/H17*1000,"")
A18: 12 | B18: Retour sur Geodays | C18: 46199 | D18: =IF(C18="","",MONTH(C18)) | E18: Post | F18: Publié | H18: 1160 | I18: 154 | J18: =IF(AND(H18>0,I18<>""),I18/H18,"") | K18: 61 | L18: =IF(AND(H18>0,K18<>""),K18/H18,"") | M18: 90 | N18: 2 | O18: 1 | P18: 0 | Q18: =IF(AND(N(P18)>0,N(H18)>0),P18/H18*1000,"")
A19: 13 | B19: Soletanche | C19: 46296 | D19: =IF(C19="","",MONTH(C19)) | E19: Post | F19: Publié | H19: 1907 | I19: 333 | J19: =IF(AND(H19>0,I19<>""),I19/H19,"") | K19: 259 | L19: =IF(AND(H19>0,K19<>""),K19/H19,"") | M19: 62 | N19: 0 | O19: 3 | P19: 0 | Q19: =IF(AND(N(P19)>0,N(H19)>0),P19/H19*1000,"")
A20: 14 | B20: Teambuilding | C20: 46301 | D20: =IF(C20="","",MONTH(C20)) | E20: Post | F20: Publié | H20: 1838 | I20: 1120 | J20: =IF(AND(H20>0,I20<>""),I20/H20,"") | K20: 1071 | L20: =IF(AND(H20>0,K20<>""),K20/H20,"") | M20: 52 | N20: 0 | O20: 0 | P20: 0 | Q20: =IF(AND(N(P20)>0,N(H20)>0),P20/H20*1000,"")
A21: 15 | B21: Salon GEOFLUID | C21: 46303 | D21: =IF(C21="","",MONTH(C21)) | E21: Post | F21: Publié | H21: 763 | I21: 45 | J21: =IF(AND(H21>0,I21<>""),I21/H21,"") | K21: 17 | L21: =IF(AND(H21>0,K21<>""),K21/H21,"") | M21: 26 | N21: 0 | O21: 2 | P21: 0 | Q21: =IF(AND(N(P21)>0,N(H21)>0),P21/H21*1000,"")
A22: 16 | B22: Octobre Rose | C22: 46308 | D22: =IF(C22="","",MONTH(C22)) | E22: Post | F22: Publié | H22: 2166 | I22: 269 | J22: =IF(AND(H22>0,I22<>""),I22/H22,"") | K22: 208 | L22: =IF(AND(H22>0,K22<>""),K22/H22,"") | M22: 64 | N22: 0 | O22: 0 | P22: 0 | Q22: =IF(AND(N(P22)>0,N(H22)>0),P22/H22*1000,"")
A23: 17 | B23: Prospection foreurs | C23: 46310 | D23: =IF(C23="","",MONTH(C23)) | E23: Post | F23: Publié | H23: 47945 | I23: 508 | J23: =IF(AND(H23>0,I23<>""),I23/H23,"") | K23: 435 | L23: =IF(AND(H23>0,K23<>""),K23/H23,"") | M23: 32 | N23: 1 | O23: 1 | P23: 140 | Q23: =IF(AND(N(P23)>0,N(H23)>0),P23/H23*1000,"")
A24: 18 | B24: Réception IFP | C24: 46315 | D24: =IF(C24="","",MONTH(C24)) | E24: Post | F24: Publié | H24: 1122 | I24: 402 | J24: =IF(AND(H24>0,I24<>""),I24/H24,"") | K24: 372 | L24: =IF(AND(H24>0,K24<>""),K24/H24,"") | M24: 29 | N24: 1 | O24: 0 | P24: 0 | Q24: =IF(AND(N(P24)>0,N(H24)>0),P24/H24*1000,"")
A25: 19 | B25: Case study part 1 | D25: =IF(C25="","",MONTH(C25)) | E25: Post | F25: Planifié | J25: =IF(AND(H25>0,I25<>""),I25/H25,"") | L25: =IF(AND(H25>0,K25<>""),K25/H25,"") | Q25: =IF(AND(N(P25)>0,N(H25)>0),P25/H25*1000,"")
A26: 20 | B26: Case study part 2 | D26: =IF(C26="","",MONTH(C26)) | E26: Post | F26: Planifié | J26: =IF(AND(H26>0,I26<>""),I26/H26,"") | L26: =IF(AND(H26>0,K26<>""),K26/H26,"") | Q26: =IF(AND(N(P26)>0,N(H26)>0),P26/H26*1000,"")
A27: 21 | B27: Anti-collision KEM One | D27: =IF(C27="","",MONTH(C27)) | E27: Post | F27: Planifié | J27: =IF(AND(H27>0,I27<>""),I27/H27,"") | L27: =IF(AND(H27>0,K27<>""),K27/H27,"") | Q27: =IF(AND(N(P27)>0,N(H27)>0),P27/H27*1000,"")
A28: 22 | B28: Nouvelle Break Out | D28: =IF(C28="","",MONTH(C28)) | E28: Post | F28: Planifié | J28: =IF(AND(H28>0,I28<>""),I28/H28,"") | L28: =IF(AND(H28>0,K28<>""),K28/H28,"") | Q28: =IF(AND(N(P28)>0,N(H28)>0),P28/H28*1000,"")
A29: 23 | D29: =IF(C29="","",MONTH(C29)) | J29: =IF(AND(H29>0,I29<>""),I29/H29,"") | L29: =IF(AND(H29>0,K29<>""),K29/H29,"") | Q29: =IF(AND(N(P29)>0,N(H29)>0),P29/H29*1000,"")
A30: 24 | D30: =IF(C30="","",MONTH(C30)) | J30: =IF(AND(H30>0,I30<>""),I30/H30,"") | L30: =IF(AND(H30>0,K30<>""),K30/H30,"") | Q30: =IF(AND(N(P30)>0,N(H30)>0),P30/H30*1000,"")
A31: 25 | D31: =IF(C31="","",MONTH(C31)) | J31: =IF(AND(H31>0,I31<>""),I31/H31,"") | L31: =IF(AND(H31>0,K31<>""),K31/H31,"") | Q31: =IF(AND(N(P31)>0,N(H31)>0),P31/H31*1000,"")
A32: 26 | D32: =IF(C32="","",MONTH(C32)) | J32: =IF(AND(H32>0,I32<>""),I32/H32,"") | L32: =IF(AND(H32>0,K32<>""),K32/H32,"") | Q32: =IF(AND(N(P32)>0,N(H32)>0),P32/H32*1000,"")
A33: 27 | D33: =IF(C33="","",MONTH(C33)) | J33: =IF(AND(H33>0,I33<>""),I33/H33,"") | L33: =IF(AND(H33>0,K33<>""),K33/H33,"") | Q33: =IF(AND(N(P33)>0,N(H33)>0),P33/H33*1000,"")
A34: 28 | D34: =IF(C34="","",MONTH(C34)) | J34: =IF(AND(H34>0,I34<>""),I34/H34,"") | L34: =IF(AND(H34>0,K34<>""),K34/H34,"") | Q34: =IF(AND(N(P34)>0,N(H34)>0),P34/H34*1000,"")
A35: 29 | D35: =IF(C35="","",MONTH(C35)) | J35: =IF(AND(H35>0,I35<>""),I35/H35,"") | L35: =IF(AND(H35>0,K35<>""),K35/H35,"") | Q35: =IF(AND(N(P35)>0,N(H35)>0),P35/H35*1000,"")
A36: 30 | D36: =IF(C36="","",MONTH(C36)) | J36: =IF(AND(H36>0,I36<>""),I36/H36,"") | L36: =IF(AND(H36>0,K36<>""),K36/H36,"") | Q36: =IF(AND(N(P36)>0,N(H36)>0),P36/H36*1000,"")
A37: 31 | D37: =IF(C37="","",MONTH(C37)) | J37: =IF(AND(H37>0,I37<>""),I37/H37,"") | L37: =IF(AND(H37>0,K37<>""),K37/H37,"") | Q37: =IF(AND(N(P37)>0,N(H37)>0),P37/H37*1000,"")
A38: 32 | D38: =IF(C38="","",MONTH(C38)) | J38: =IF(AND(H38>0,I38<>""),I38/H38,"") | L38: =IF(AND(H38>0,K38<>""),K38/H38,"") | Q38: =IF(AND(N(P38)>0,N(H38)>0),P38/H38*1000,"")
A39: 33 | D39: =IF(C39="","",MONTH(C39)) | J39: =IF(AND(H39>0,I39<>""),I39/H39,"") | L39: =IF(AND(H39>0,K39<>""),K39/H39,"") | Q39: =IF(AND(N(P39)>0,N(H39)>0),P39/H39*1000,"")
A40: 34 | D40: =IF(C40="","",MONTH(C40)) | J40: =IF(AND(H40>0,I40<>""),I40/H40,"") | L40: =IF(AND(H40>0,K40<>""),K40/H40,"") | Q40: =IF(AND(N(P40)>0,N(H40)>0),P40/H40*1000,"")
... A66: 60 | D66: =IF(C66="","",MONTH(C66)) | J66: =IF(AND(H66>0,I66<>""),I66/H66,"") | L66: =IF(AND(H66>0,K66<>""),K66/H66,"") | Q66: =IF(AND(N(P66)>0,N(H66)>0),P66/H66*1000,"")

Sheet Abonnés LinkedIn
B1: Abonnés LinkedIn
B2: Nouveaux abonnés par mois : saisissez le mois en cours, le cumul et les KPI se mettent à jour.
B6: NOUVEAUX ABONNÉS PAR MOIS | Q6: REPÈRES ET OBJECTIF
B7: Année | C7: Janv. | D7: Févr. | E7: Mars | F7: Avri. | G7: Mai | H7: Juin | I7: Juil. | J7: Août | K7: Sept. | L7: Octo. | M7: Nove. | N7: Déce. | O7: Total
B8: 2024 | C8: 37 | D8: 11 | E8: 50 | F8: 47 | G8: 186 | H8: 169 | I8: 144 | J8: 153 | K8: 125 | L8: 206 | M8: 129 | N8: 79 | O8: =SUM(C8:N8) | Q8: Abonnés au 01/01/2024 | R8: 1067
B9: 2025 | C9: 132 | D9: 102 | E9: 144 | F9: 108 | G9: 191 | H9: 162 | I9: 88 | J9: 113 | K9: 93 | L9: 108 | M9: 65 | N9: 40 | O9: =SUM(C9:N9) | Q9: Abonnés au 31/12/2024 (relevé) | R9: 2397
B10: 2026 | C10: 47 | D10: 91 | E10: 124 | F10: 142 | G10: 125 | H10: 68 | I10: 70 | J10: 23 | K10: 68 | L10: 123 | O10: =SUM(C10:N10) | Q10: Abonnés au 31/12/2025 (relevé) | R10: 3743
Q11: Abonnés actuels | R11: =R10+SUM(C10:N10)
B12: ABONNÉS CUMULÉS | Q12: Croissance 2026 (à date) | R12: =R11-R10
B13: Année | C13: Janv. | D13: Févr. | E13: Mars | F13: Avri. | G13: Mai | H13: Juin | I13: Juil. | J13: Août | K13: Sept. | L13: Octo. | M13: Nove. | N13: Déce. | Q13: Croissance 2025 | R13: =R10-R9
B14: 2024 | C14: =IF(C8="",NA(),$R$8+SUM($C8:C8)) | D14: =IF(D8="",NA(),$R$8+SUM($C8:D8)) | E14: =IF(E8="",NA(),$R$8+SUM($C8:E8)) | F14: =IF(F8="",NA(),$R$8+SUM($C8:F8)) | G14: =IF(G8="",NA(),$R$8+SUM($C8:G8)) | H14: =IF(H8="",NA(),$R$8+SUM($C8:H8)) | I14: =IF(I8="",NA(),$R$8+SUM($C8:I8)) | J14: =IF(J8="",NA(),$R$8+SUM($C8:J8)) | ... N14: =IF(N8="",NA(),$R$8+SUM($C8:N8)) | Q14: Nouveaux abonnés / mois en 2026 (moyenne) | R14: =IFERROR(AVERAGE(C10:N10),0)
B15: 2025 | C15: =IF(C9="",NA(),$R$9+SUM($C9:C9)) | D15: =IF(D9="",NA(),$R$9+SUM($C9:D9)) | E15: =IF(E9="",NA(),$R$9+SUM($C9:E9)) | F15: =IF(F9="",NA(),$R$9+SUM($C9:F9)) | G15: =IF(G9="",NA(),$R$9+SUM($C9:G9)) | H15: =IF(H9="",NA(),$R$9+SUM($C9:H9)) | I15: =IF(I9="",NA(),$R$9+SUM($C9:I9)) | J15: =IF(J9="",NA(),$R$9+SUM($C9:J9)) | ... N15: =IF(N9="",NA(),$R$9+SUM($C9:N9)) | Q15: Objectif 2026 | R15: 5000
B16: 2026 | C16: =IF(C10="",NA(),$R$10+SUM($C10:C10)) | D16: =IF(D10="",NA(),$R$10+SUM($C10:D10)) | E16: =IF(E10="",NA(),$R$10+SUM($C10:E10)) | F16: =IF(F10="",NA(),$R$10+SUM($C10:F10)) | G16: =IF(G10="",NA(),$R$10+SUM($C10:G10)) | H16: =IF(H10="",NA(),$R$10+SUM($C10:H10)) | I16: =IF(I10="",NA(),$R$10+SUM($C10:I10)) | J16: =IF(J10="",NA(),$R$10+SUM($C10:J10)) | ... N16: =IF(N10="",NA(),$R$10+SUM($C10:N10)) | Q16: Restant à atteindre | R16: =MAX(R15-R11,0)
Q17: % de l'objectif atteint | R17: =R11/R15
Q18: Projection fin 2026 (rythme actuel) | R18: =R11+R14*(12-COUNT(C10:N10))
Q19: Même période 2025 (nouveaux abonnés) | R19: =SUMPRODUCT((C10:N10<>"")*C9:N9)
Q20: Évolution vs même période 2025 | R20: =IFERROR(R12/R19-1,"")
Q22: Note : le relevé au 31/12/2024 (2 397) est inférieur de 6 au calcul (1 067 + 1 336 = 2 403), l’écart correspond probablement à des désabonnements.

Sheet Salons
B1: Salons et événements
B2: Suivi des salons confirmés, du lieu et du nombre de posts LinkedIn liés (calcul automatique via le mot-clé).
B6: Événement | C6: Type | D6: Période | E6: Statut | F6: Lieu | G6: Posts liés | H6: Remarque | I6: Mot-clé
B7: Journées de la Géothermie | C7: Salon | D7: Février 2026 | E7: À valider | G7: =IF(I7="","",COUNTIF('Posts LinkedIn'!$B$7:$B$66,"*"&I7&"*"))
B8: GeoTHERM 2026 | C8: Salon | D8: Février 2026 | E8: Réalisé | F8: Offenburg (Allemagne) | G8: =IF(I8="","",COUNTIF('Posts LinkedIn'!$B$7:$B$66,"*"&I8&"*")) | H8: Annonce et retour publiés. | I8: GeoTHERM
B9: Think GeoEnergy | C9: Salon | D9: Mars 2026 | E9: À valider | G9: =IF(I9="","",COUNTIF('Posts LinkedIn'!$B$7:$B$66,"*"&I9&"*"))
B10: GeoRin | C10: Salon | D10: Avril 2026 | E10: À valider | G10: =IF(I10="","",COUNTIF('Posts LinkedIn'!$B$7:$B$66,"*"&I10&"*"))
B11: WPC Energy Congress | C11: Salon | D11: Avril 2026 | E11: À valider | G11: =IF(I11="","",COUNTIF('Posts LinkedIn'!$B$7:$B$66,"*"&I11&"*"))
B12: World Hydrogen Summit & Exhibition | C12: Salon | D12: Mai 2026 | E12: À valider | G12: =IF(I12="","",COUNTIF('Posts LinkedIn'!$B$7:$B$66,"*"&I12&"*"))
B13: Geodays | C13: Salon | D13: Juin 2026 | E13: Réalisé | G13: =IF(I13="","",COUNTIF('Posts LinkedIn'!$B$7:$B$66,"*"&I13&"*")) | H13: Annonce et retour publiés. | I13: Geodays
B14: GEOFLUID | C14: Salon | D14: 9 octobre 2026 | E14: Réalisé | F14: Piacenza (Italie) | G14: =IF(I14="","",COUNTIF('Posts LinkedIn'!$B$7:$B$66,"*"&I14&"*")) | H14: Représentant : Luigi Liberatore. | I14: GEOFLUID
B15: Journée mondiale de l’énergie | C15: Temps fort | D15: 16 octobre 2026 | E15: Réalisé | G15: =IF(I15="","",COUNTIF('Posts LinkedIn'!$B$7:$B$66,"*"&I15&"*")) | I15: énergie
B16: Octobre rose | C16: Temps fort | D16: Octobre 2026 | E16: Réalisé | G16: =IF(I16="","",COUNTIF('Posts LinkedIn'!$B$7:$B$66,"*"&I16&"*")) | I16: Octobre Rose
B17: ADIPEC 2026 | C17: Salon | D17: 2-5 novembre 2026 | E17: Confirmé | F17: Abu Dhabi (ADNEC) | G17: =IF(I17="","",COUNTIF('Posts LinkedIn'!$B$7:$B$66,"*"&I17&"*")) | H17: Post d’annonce à publier avant le 2 novembre. | I17: ADIPEC
B18: Movember | C18: Temps fort | D18: Novembre 2026 | E18: Confirmé | G18: =IF(I18="","",COUNTIF('Posts LinkedIn'!$B$7:$B$66,"*"&I18&"*")) | I18: Movember
B19: GeoTHERM 2027 | C19: Salon | D19: 25-26 février 2027 | E19: Confirmé | F19: Offenburg (Allemagne) | G19: =IF(I19="","",COUNTIF('Posts LinkedIn'!$B$7:$B$66,"*"&I19&"*")) | H19: Stand 274 (18 m²), co-exposant Fixndril. | I19: GeoTHERM 2027
